import android.app.AlarmManager;
import android.app.PendingIntent;
import android.content.Context;
import android.content.Intent;
import android.content.SharedPreferences;
import android.content.SharedPreferences.Editor;
import android.content.pm.PackageInfo;
import android.content.pm.PackageManager;
import android.content.pm.PackageManager.NameNotFoundException;
import android.os.Build;
import android.os.Build.VERSION;
import android.provider.Settings.Secure;
import android.telephony.TelephonyManager;
import android.util.Log;
import com.arrownock.exception.ArrownockException;
import com.arrownock.push.AnPush;
import com.arrownock.push.IAnPushCallback;
import com.arrownock.push.IAnPushRegisterAnIdCallback;
import com.arrownock.push.IAnPushRegistrationCallback;
import com.arrownock.push.IAnPushSettingsCallback;
import com.arrownock.push.PushService;
import java.io.BufferedReader;
import java.io.IOException;
import java.io.InputStream;
import java.io.InputStreamReader;
import java.io.UnsupportedEncodingException;
import java.net.URLEncoder;
import java.security.MessageDigest;
import java.security.NoSuchAlgorithmException;
import java.util.Calendar;
import java.util.Date;
import java.util.HashMap;
import java.util.Iterator;
import java.util.List;
import java.util.Map;
import java.util.Set;
import java.util.TimeZone;
import java.util.TreeMap;
import java.util.UUID;
import javax.net.ssl.HostnameVerifier;
import org.apache.http.NameValuePair;

public final class df
  implements dy
{
  private static final String jdField_a_of_type_JavaLangString = AnPush.class.getName();
  private static final HostnameVerifier jdField_a_of_type_JavaxNetSslHostnameVerifier = new cn();
  private Context jdField_a_of_type_AndroidContentContext = null;
  
  public df(Context paramContext)
  {
    jdField_a_of_type_AndroidContentContext = paramContext;
  }
  
  private static int a(Context paramContext)
  {
    try
    {
      int i = getPackageManagergetPackageInfogetPackageName0versionCode;
      return i;
    }
    catch (PackageManager.NameNotFoundException paramContext)
    {
      throw new RuntimeException("Could not get package name: " + paramContext);
    }
  }
  
  private static String a(InputStream paramInputStream)
  {
    BufferedReader localBufferedReader = new BufferedReader(new InputStreamReader(paramInputStream));
    StringBuilder localStringBuilder = new StringBuilder();
    try
    {
      for (;;)
      {
        String str = localBufferedReader.readLine();
        if (str == null) {
          break;
        }
        localStringBuilder.append(str + "\n");
      }
      try
      {
        paramInputStream.close();
        throw localObject;
      }
      catch (IOException paramInputStream)
      {
        for (;;)
        {
          paramInputStream.printStackTrace();
        }
      }
    }
    catch (IOException localIOException)
    {
      localIOException = localIOException;
      localIOException.printStackTrace();
      try
      {
        paramInputStream.close();
        for (;;)
        {
          return localStringBuilder.toString();
          try
          {
            paramInputStream.close();
          }
          catch (IOException paramInputStream)
          {
            paramInputStream.printStackTrace();
          }
        }
      }
      catch (IOException paramInputStream)
      {
        for (;;)
        {
          paramInputStream.printStackTrace();
        }
      }
    }
    finally {}
  }
  
  private static String a(List<NameValuePair> paramList)
    throws UnsupportedEncodingException
  {
    StringBuilder localStringBuilder = new StringBuilder();
    paramList = paramList.iterator();
    int i = 1;
    if (paramList.hasNext())
    {
      NameValuePair localNameValuePair = (NameValuePair)paramList.next();
      if (i != 0) {
        i = 0;
      }
      for (;;)
      {
        localStringBuilder.append(URLEncoder.encode(localNameValuePair.getName(), "UTF-8"));
        localStringBuilder.append("=");
        localStringBuilder.append(URLEncoder.encode(localNameValuePair.getValue(), "UTF-8"));
        break;
        localStringBuilder.append("&");
      }
    }
    return localStringBuilder.toString();
  }
  
  private static String a(List<NameValuePair> paramList, String paramString)
  {
    StringBuffer localStringBuffer = new StringBuffer();
    TreeMap localTreeMap = new TreeMap();
    localTreeMap.put("key", paramString);
    paramList = paramList.iterator();
    while (paramList.hasNext())
    {
      paramString = (NameValuePair)paramList.next();
      localTreeMap.put(paramString.getName(), paramString.getValue());
    }
    paramList = localTreeMap.keySet().iterator();
    while (paramList.hasNext())
    {
      paramString = (String)paramList.next();
      localStringBuffer.append(paramString + "=" + (String)localTreeMap.get(paramString) + "&");
    }
    if (localStringBuffer.length() > 0) {
      return localStringBuffer.substring(0, localStringBuffer.length() - 1);
    }
    return "";
  }
  
  private static Map<String, String> a(Context paramContext)
  {
    TelephonyManager localTelephonyManager = (TelephonyManager)paramContext.getSystemService("phone");
    paramContext = new HashMap();
    try
    {
      paramContext.put("phone_model", Build.MODEL);
      paramContext.put("manufacturer", Build.MANUFACTURER);
      paramContext.put("sdk_version", String.valueOf(Build.VERSION.SDK_INT));
      paramContext.put("release_version", Build.VERSION.RELEASE);
      paramContext.put("network_operator", localTelephonyManager.getNetworkOperatorName());
      paramContext.put("network_type", String.valueOf(localTelephonyManager.getNetworkType()));
      paramContext.put("sim_operator", localTelephonyManager.getSimOperatorName());
      return paramContext;
    }
    catch (Exception localException)
    {
      bk.a().a(jdField_a_of_type_JavaLangString, "Error on getPhoneStatus()", localException);
    }
    return paramContext;
  }
  
  /* Error */
  private Map<String, Object> a(String paramString)
  {
    // Byte code:
    //   0: new 207	java/util/HashMap
    //   3: dup
    //   4: invokespecial 208	java/util/HashMap:<init>	()V
    //   7: astore 7
    //   9: aconst_null
    //   10: astore 6
    //   12: aconst_null
    //   13: astore 5
    //   15: aload 5
    //   17: astore 4
    //   19: aload 6
    //   21: astore_3
    //   22: aload_0
    //   23: getfield 34	df:jdField_a_of_type_AndroidContentContext	Landroid/content/Context;
    //   26: invokestatic 267	com/arrownock/push/AnPush:getInstance	(Landroid/content/Context;)Lcom/arrownock/push/AnPush;
    //   29: invokevirtual 270	com/arrownock/push/AnPush:isSecureConnection	()Z
    //   32: ifeq +209 -> 241
    //   35: aload 5
    //   37: astore 4
    //   39: aload 6
    //   41: astore_3
    //   42: new 272	java/net/URL
    //   45: dup
    //   46: new 62	java/lang/StringBuilder
    //   49: dup
    //   50: ldc_w 274
    //   53: invokespecial 67	java/lang/StringBuilder:<init>	(Ljava/lang/String;)V
    //   56: aload_1
    //   57: invokevirtual 104	java/lang/StringBuilder:append	(Ljava/lang/String;)Ljava/lang/StringBuilder;
    //   60: invokevirtual 74	java/lang/StringBuilder:toString	()Ljava/lang/String;
    //   63: invokespecial 275	java/net/URL:<init>	(Ljava/lang/String;)V
    //   66: invokevirtual 279	java/net/URL:openConnection	()Ljava/net/URLConnection;
    //   69: checkcast 281	javax/net/ssl/HttpsURLConnection
    //   72: astore_1
    //   73: aload_1
    //   74: checkcast 281	javax/net/ssl/HttpsURLConnection
    //   77: getstatic 29	df:jdField_a_of_type_JavaxNetSslHostnameVerifier	Ljavax/net/ssl/HostnameVerifier;
    //   80: invokevirtual 285	javax/net/ssl/HttpsURLConnection:setHostnameVerifier	(Ljavax/net/ssl/HostnameVerifier;)V
    //   83: aload_1
    //   84: checkcast 281	javax/net/ssl/HttpsURLConnection
    //   87: aload_0
    //   88: invokespecial 288	df:f	()Ljava/lang/String;
    //   91: aload_0
    //   92: invokespecial 291	df:g	()Ljava/lang/String;
    //   95: aload_0
    //   96: invokespecial 294	df:h	()Ljava/lang/String;
    //   99: ldc -63
    //   101: ldc_w 296
    //   104: invokestatic 301	at:a	(Ljava/lang/String;Ljava/lang/String;Ljava/lang/String;Ljava/lang/String;Ljava/lang/String;)Ljavax/net/ssl/SSLSocketFactory;
    //   107: invokevirtual 305	javax/net/ssl/HttpsURLConnection:setSSLSocketFactory	(Ljavax/net/ssl/SSLSocketFactory;)V
    //   110: aload_1
    //   111: astore 4
    //   113: aload_1
    //   114: astore_3
    //   115: aload_1
    //   116: invokevirtual 310	java/net/HttpURLConnection:connect	()V
    //   119: aload_1
    //   120: astore 4
    //   122: aload_1
    //   123: astore_3
    //   124: aload_1
    //   125: invokevirtual 313	java/net/HttpURLConnection:getResponseCode	()I
    //   128: istore_2
    //   129: iload_2
    //   130: sipush 200
    //   133: if_icmpne +149 -> 282
    //   136: aload_1
    //   137: astore 4
    //   139: aload_1
    //   140: astore_3
    //   141: new 315	org/json/JSONObject
    //   144: dup
    //   145: new 317	java/io/BufferedInputStream
    //   148: dup
    //   149: aload_1
    //   150: invokevirtual 321	java/net/HttpURLConnection:getInputStream	()Ljava/io/InputStream;
    //   153: invokespecial 322	java/io/BufferedInputStream:<init>	(Ljava/io/InputStream;)V
    //   156: invokestatic 324	df:a	(Ljava/io/InputStream;)Ljava/lang/String;
    //   159: invokespecial 325	org/json/JSONObject:<init>	(Ljava/lang/String;)V
    //   162: ldc_w 327
    //   165: invokevirtual 331	org/json/JSONObject:getString	(Ljava/lang/String;)Ljava/lang/String;
    //   168: astore 5
    //   170: aload_1
    //   171: astore 4
    //   173: aload_1
    //   174: astore_3
    //   175: aload 7
    //   177: ldc_w 333
    //   180: iconst_1
    //   181: invokestatic 338	java/lang/Boolean:valueOf	(Z)Ljava/lang/Boolean;
    //   184: invokeinterface 167 3 0
    //   189: pop
    //   190: aload_1
    //   191: astore 4
    //   193: aload_1
    //   194: astore_3
    //   195: aload 7
    //   197: ldc_w 340
    //   200: sipush 200
    //   203: invokestatic 345	java/lang/Integer:valueOf	(I)Ljava/lang/Integer;
    //   206: invokeinterface 167 3 0
    //   211: pop
    //   212: aload_1
    //   213: astore 4
    //   215: aload_1
    //   216: astore_3
    //   217: aload 7
    //   219: ldc_w 347
    //   222: aload 5
    //   224: invokeinterface 167 3 0
    //   229: pop
    //   230: aload_1
    //   231: ifnull +7 -> 238
    //   234: aload_1
    //   235: invokevirtual 350	java/net/HttpURLConnection:disconnect	()V
    //   238: aload 7
    //   240: areturn
    //   241: aload 5
    //   243: astore 4
    //   245: aload 6
    //   247: astore_3
    //   248: new 272	java/net/URL
    //   251: dup
    //   252: new 62	java/lang/StringBuilder
    //   255: dup
    //   256: ldc_w 352
    //   259: invokespecial 67	java/lang/StringBuilder:<init>	(Ljava/lang/String;)V
    //   262: aload_1
    //   263: invokevirtual 104	java/lang/StringBuilder:append	(Ljava/lang/String;)Ljava/lang/StringBuilder;
    //   266: invokevirtual 74	java/lang/StringBuilder:toString	()Ljava/lang/String;
    //   269: invokespecial 275	java/net/URL:<init>	(Ljava/lang/String;)V
    //   272: invokevirtual 279	java/net/URL:openConnection	()Ljava/net/URLConnection;
    //   275: checkcast 307	java/net/HttpURLConnection
    //   278: astore_1
    //   279: goto -169 -> 110
    //   282: aload_1
    //   283: astore 4
    //   285: aload_1
    //   286: astore_3
    //   287: new 317	java/io/BufferedInputStream
    //   290: dup
    //   291: aload_1
    //   292: invokevirtual 355	java/net/HttpURLConnection:getErrorStream	()Ljava/io/InputStream;
    //   295: invokespecial 322	java/io/BufferedInputStream:<init>	(Ljava/io/InputStream;)V
    //   298: invokestatic 324	df:a	(Ljava/io/InputStream;)Ljava/lang/String;
    //   301: astore 5
    //   303: iload_2
    //   304: sipush 400
    //   307: if_icmpne +153 -> 460
    //   310: aload_1
    //   311: astore 4
    //   313: aload_1
    //   314: astore_3
    //   315: new 315	org/json/JSONObject
    //   318: dup
    //   319: aload 5
    //   321: invokespecial 325	org/json/JSONObject:<init>	(Ljava/lang/String;)V
    //   324: ldc_w 357
    //   327: invokevirtual 331	org/json/JSONObject:getString	(Ljava/lang/String;)Ljava/lang/String;
    //   330: astore 5
    //   332: aload_1
    //   333: astore 4
    //   335: aload_1
    //   336: astore_3
    //   337: aload 7
    //   339: ldc_w 333
    //   342: iconst_0
    //   343: invokestatic 338	java/lang/Boolean:valueOf	(Z)Ljava/lang/Boolean;
    //   346: invokeinterface 167 3 0
    //   351: pop
    //   352: aload_1
    //   353: astore 4
    //   355: aload_1
    //   356: astore_3
    //   357: aload 7
    //   359: ldc_w 340
    //   362: sipush 400
    //   365: invokestatic 345	java/lang/Integer:valueOf	(I)Ljava/lang/Integer;
    //   368: invokeinterface 167 3 0
    //   373: pop
    //   374: aload_1
    //   375: astore 4
    //   377: aload_1
    //   378: astore_3
    //   379: aload 7
    //   381: ldc_w 357
    //   384: aload 5
    //   386: invokeinterface 167 3 0
    //   391: pop
    //   392: goto -162 -> 230
    //   395: astore_1
    //   396: aload 4
    //   398: astore_3
    //   399: aload 7
    //   401: ldc_w 333
    //   404: iconst_0
    //   405: invokestatic 338	java/lang/Boolean:valueOf	(Z)Ljava/lang/Boolean;
    //   408: invokeinterface 167 3 0
    //   413: pop
    //   414: aload 4
    //   416: astore_3
    //   417: aload 7
    //   419: ldc_w 340
    //   422: iconst_m1
    //   423: invokestatic 345	java/lang/Integer:valueOf	(I)Ljava/lang/Integer;
    //   426: invokeinterface 167 3 0
    //   431: pop
    //   432: aload 4
    //   434: astore_3
    //   435: aload 7
    //   437: ldc_w 359
    //   440: aload_1
    //   441: invokeinterface 167 3 0
    //   446: pop
    //   447: aload 4
    //   449: ifnull -211 -> 238
    //   452: aload 4
    //   454: invokevirtual 350	java/net/HttpURLConnection:disconnect	()V
    //   457: aload 7
    //   459: areturn
    //   460: iload_2
    //   461: sipush 503
    //   464: if_icmpne +149 -> 613
    //   467: aload_1
    //   468: astore 4
    //   470: aload_1
    //   471: astore_3
    //   472: new 315	org/json/JSONObject
    //   475: dup
    //   476: aload 5
    //   478: invokespecial 325	org/json/JSONObject:<init>	(Ljava/lang/String;)V
    //   481: astore 5
    //   483: aload_1
    //   484: astore 4
    //   486: aload_1
    //   487: astore_3
    //   488: aload 5
    //   490: ldc_w 357
    //   493: invokevirtual 331	org/json/JSONObject:getString	(Ljava/lang/String;)Ljava/lang/String;
    //   496: astore 6
    //   498: aload_1
    //   499: astore 4
    //   501: aload_1
    //   502: astore_3
    //   503: aload 5
    //   505: ldc_w 361
    //   508: iconst_m1
    //   509: invokevirtual 365	org/json/JSONObject:optInt	(Ljava/lang/String;I)I
    //   512: istore_2
    //   513: aload_1
    //   514: astore 4
    //   516: aload_1
    //   517: astore_3
    //   518: aload 7
    //   520: ldc_w 333
    //   523: iconst_0
    //   524: invokestatic 338	java/lang/Boolean:valueOf	(Z)Ljava/lang/Boolean;
    //   527: invokeinterface 167 3 0
    //   532: pop
    //   533: aload_1
    //   534: astore 4
    //   536: aload_1
    //   537: astore_3
    //   538: aload 7
    //   540: ldc_w 340
    //   543: sipush 503
    //   546: invokestatic 345	java/lang/Integer:valueOf	(I)Ljava/lang/Integer;
    //   549: invokeinterface 167 3 0
    //   554: pop
    //   555: aload_1
    //   556: astore 4
    //   558: aload_1
    //   559: astore_3
    //   560: aload 7
    //   562: ldc_w 357
    //   565: aload 6
    //   567: invokeinterface 167 3 0
    //   572: pop
    //   573: aload_1
    //   574: astore 4
    //   576: aload_1
    //   577: astore_3
    //   578: aload 7
    //   580: ldc_w 361
    //   583: iload_2
    //   584: invokestatic 345	java/lang/Integer:valueOf	(I)Ljava/lang/Integer;
    //   587: invokeinterface 167 3 0
    //   592: pop
    //   593: goto -363 -> 230
    //   596: astore 4
    //   598: aload_3
    //   599: astore_1
    //   600: aload 4
    //   602: astore_3
    //   603: aload_1
    //   604: ifnull +7 -> 611
    //   607: aload_1
    //   608: invokevirtual 350	java/net/HttpURLConnection:disconnect	()V
    //   611: aload_3
    //   612: athrow
    //   613: aload_1
    //   614: astore 4
    //   616: aload_1
    //   617: astore_3
    //   618: aload 7
    //   620: ldc_w 333
    //   623: iconst_0
    //   624: invokestatic 338	java/lang/Boolean:valueOf	(Z)Ljava/lang/Boolean;
    //   627: invokeinterface 167 3 0
    //   632: pop
    //   633: aload_1
    //   634: astore 4
    //   636: aload_1
    //   637: astore_3
    //   638: aload 7
    //   640: ldc_w 340
    //   643: iload_2
    //   644: invokestatic 345	java/lang/Integer:valueOf	(I)Ljava/lang/Integer;
    //   647: invokeinterface 167 3 0
    //   652: pop
    //   653: aload_1
    //   654: astore 4
    //   656: aload_1
    //   657: astore_3
    //   658: aload 7
    //   660: ldc_w 367
    //   663: aload 5
    //   665: invokeinterface 167 3 0
    //   670: pop
    //   671: goto -441 -> 230
    //   674: astore_3
    //   675: goto -72 -> 603
    //   678: astore_3
    //   679: aload_1
    //   680: astore 4
    //   682: aload_3
    //   683: astore_1
    //   684: goto -288 -> 396
    // Local variable table:
    //   start	length	slot	name	signature
    //   0	687	0	this	df
    //   0	687	1	paramString	String
    //   128	516	2	i	int
    //   21	637	3	localObject1	Object
    //   674	1	3	localObject2	Object
    //   678	5	3	localException	Exception
    //   17	558	4	localObject3	Object
    //   596	5	4	localObject4	Object
    //   614	67	4	str1	String
    //   13	651	5	localObject5	Object
    //   10	556	6	str2	String
    //   7	652	7	localHashMap	HashMap
    // Exception table:
    //   from	to	target	type
    //   22	35	395	java/lang/Exception
    //   42	73	395	java/lang/Exception
    //   115	119	395	java/lang/Exception
    //   124	129	395	java/lang/Exception
    //   141	170	395	java/lang/Exception
    //   175	190	395	java/lang/Exception
    //   195	212	395	java/lang/Exception
    //   217	230	395	java/lang/Exception
    //   248	279	395	java/lang/Exception
    //   287	303	395	java/lang/Exception
    //   315	332	395	java/lang/Exception
    //   337	352	395	java/lang/Exception
    //   357	374	395	java/lang/Exception
    //   379	392	395	java/lang/Exception
    //   472	483	395	java/lang/Exception
    //   488	498	395	java/lang/Exception
    //   503	513	395	java/lang/Exception
    //   518	533	395	java/lang/Exception
    //   538	555	395	java/lang/Exception
    //   560	573	395	java/lang/Exception
    //   578	593	395	java/lang/Exception
    //   618	633	395	java/lang/Exception
    //   638	653	395	java/lang/Exception
    //   658	671	395	java/lang/Exception
    //   22	35	596	finally
    //   42	73	596	finally
    //   115	119	596	finally
    //   124	129	596	finally
    //   141	170	596	finally
    //   175	190	596	finally
    //   195	212	596	finally
    //   217	230	596	finally
    //   248	279	596	finally
    //   287	303	596	finally
    //   315	332	596	finally
    //   337	352	596	finally
    //   357	374	596	finally
    //   379	392	596	finally
    //   399	414	596	finally
    //   417	432	596	finally
    //   435	447	596	finally
    //   472	483	596	finally
    //   488	498	596	finally
    //   503	513	596	finally
    //   518	533	596	finally
    //   538	555	596	finally
    //   560	573	596	finally
    //   578	593	596	finally
    //   618	633	596	finally
    //   638	653	596	finally
    //   658	671	596	finally
    //   73	110	674	finally
    //   73	110	678	java/lang/Exception
  }
  
  /* Error */
  private void a(String paramString1, String paramString2, int paramInt1, int paramInt2, int paramInt3, boolean paramBoolean1, boolean paramBoolean2)
    throws ArrownockException
  {
    // Byte code:
    //   0: aconst_null
    //   1: astore 11
    //   3: aconst_null
    //   4: astore 9
    //   6: aload 9
    //   8: astore 10
    //   10: aload 11
    //   12: astore 8
    //   14: aload_0
    //   15: getfield 34	df:jdField_a_of_type_AndroidContentContext	Landroid/content/Context;
    //   18: invokestatic 267	com/arrownock/push/AnPush:getInstance	(Landroid/content/Context;)Lcom/arrownock/push/AnPush;
    //   21: invokevirtual 270	com/arrownock/push/AnPush:isSecureConnection	()Z
    //   24: ifeq +835 -> 859
    //   27: aload 9
    //   29: astore 10
    //   31: aload 11
    //   33: astore 8
    //   35: new 272	java/net/URL
    //   38: dup
    //   39: new 62	java/lang/StringBuilder
    //   42: dup
    //   43: ldc_w 274
    //   46: invokespecial 67	java/lang/StringBuilder:<init>	(Ljava/lang/String;)V
    //   49: aload_0
    //   50: invokespecial 445	df:c	()Ljava/lang/String;
    //   53: invokevirtual 104	java/lang/StringBuilder:append	(Ljava/lang/String;)Ljava/lang/StringBuilder;
    //   56: ldc_w 588
    //   59: invokevirtual 104	java/lang/StringBuilder:append	(Ljava/lang/String;)Ljava/lang/StringBuilder;
    //   62: aload_1
    //   63: invokevirtual 450	java/lang/String:trim	()Ljava/lang/String;
    //   66: invokevirtual 104	java/lang/StringBuilder:append	(Ljava/lang/String;)Ljava/lang/StringBuilder;
    //   69: invokevirtual 74	java/lang/StringBuilder:toString	()Ljava/lang/String;
    //   72: invokespecial 275	java/net/URL:<init>	(Ljava/lang/String;)V
    //   75: invokevirtual 279	java/net/URL:openConnection	()Ljava/net/URLConnection;
    //   78: checkcast 281	javax/net/ssl/HttpsURLConnection
    //   81: astore 9
    //   83: aload 9
    //   85: checkcast 281	javax/net/ssl/HttpsURLConnection
    //   88: getstatic 29	df:jdField_a_of_type_JavaxNetSslHostnameVerifier	Ljavax/net/ssl/HostnameVerifier;
    //   91: invokevirtual 285	javax/net/ssl/HttpsURLConnection:setHostnameVerifier	(Ljavax/net/ssl/HostnameVerifier;)V
    //   94: aload 9
    //   96: checkcast 281	javax/net/ssl/HttpsURLConnection
    //   99: aload_0
    //   100: invokespecial 288	df:f	()Ljava/lang/String;
    //   103: aload_0
    //   104: invokespecial 291	df:g	()Ljava/lang/String;
    //   107: aload_0
    //   108: invokespecial 294	df:h	()Ljava/lang/String;
    //   111: ldc -63
    //   113: ldc_w 296
    //   116: invokestatic 301	at:a	(Ljava/lang/String;Ljava/lang/String;Ljava/lang/String;Ljava/lang/String;Ljava/lang/String;)Ljavax/net/ssl/SSLSocketFactory;
    //   119: invokevirtual 305	javax/net/ssl/HttpsURLConnection:setSSLSocketFactory	(Ljavax/net/ssl/SSLSocketFactory;)V
    //   122: aload 9
    //   124: astore 10
    //   126: aload 9
    //   128: astore 8
    //   130: aload 9
    //   132: ldc_w 452
    //   135: invokevirtual 455	java/net/HttpURLConnection:setRequestMethod	(Ljava/lang/String;)V
    //   138: aload 9
    //   140: astore 10
    //   142: aload 9
    //   144: astore 8
    //   146: aload 9
    //   148: iconst_1
    //   149: invokevirtual 459	java/net/HttpURLConnection:setDoInput	(Z)V
    //   152: aload 9
    //   154: astore 10
    //   156: aload 9
    //   158: astore 8
    //   160: aload 9
    //   162: iconst_1
    //   163: invokevirtual 462	java/net/HttpURLConnection:setDoOutput	(Z)V
    //   166: aload 9
    //   168: astore 10
    //   170: aload 9
    //   172: astore 8
    //   174: new 464	java/text/SimpleDateFormat
    //   177: dup
    //   178: ldc_w 466
    //   181: getstatic 472	java/util/Locale:US	Ljava/util/Locale;
    //   184: invokespecial 475	java/text/SimpleDateFormat:<init>	(Ljava/lang/String;Ljava/util/Locale;)V
    //   187: new 477	java/util/Date
    //   190: dup
    //   191: invokespecial 478	java/util/Date:<init>	()V
    //   194: invokevirtual 482	java/text/SimpleDateFormat:format	(Ljava/util/Date;)Ljava/lang/String;
    //   197: astore 12
    //   199: aload 9
    //   201: astore 10
    //   203: aload 9
    //   205: astore 8
    //   207: new 484	java/util/ArrayList
    //   210: dup
    //   211: invokespecial 485	java/util/ArrayList:<init>	()V
    //   214: astore 11
    //   216: aload 9
    //   218: astore 10
    //   220: aload 9
    //   222: astore 8
    //   224: aload 11
    //   226: new 487	org/apache/http/message/BasicNameValuePair
    //   229: dup
    //   230: ldc_w 327
    //   233: aload_2
    //   234: invokespecial 489	org/apache/http/message/BasicNameValuePair:<init>	(Ljava/lang/String;Ljava/lang/String;)V
    //   237: invokeinterface 493 2 0
    //   242: pop
    //   243: aload 9
    //   245: astore 10
    //   247: aload 9
    //   249: astore 8
    //   251: aload 11
    //   253: new 487	org/apache/http/message/BasicNameValuePair
    //   256: dup
    //   257: ldc_w 495
    //   260: aload 12
    //   262: invokespecial 489	org/apache/http/message/BasicNameValuePair:<init>	(Ljava/lang/String;Ljava/lang/String;)V
    //   265: invokeinterface 493 2 0
    //   270: pop
    //   271: iload 7
    //   273: ifeq +780 -> 1053
    //   276: aload 9
    //   278: astore 10
    //   280: aload 9
    //   282: astore 8
    //   284: aload 11
    //   286: new 487	org/apache/http/message/BasicNameValuePair
    //   289: dup
    //   290: ldc_w 590
    //   293: iload_3
    //   294: invokestatic 345	java/lang/Integer:valueOf	(I)Ljava/lang/Integer;
    //   297: invokevirtual 591	java/lang/Integer:toString	()Ljava/lang/String;
    //   300: invokespecial 489	org/apache/http/message/BasicNameValuePair:<init>	(Ljava/lang/String;Ljava/lang/String;)V
    //   303: invokeinterface 493 2 0
    //   308: pop
    //   309: aload 9
    //   311: astore 10
    //   313: aload 9
    //   315: astore 8
    //   317: aload 11
    //   319: new 487	org/apache/http/message/BasicNameValuePair
    //   322: dup
    //   323: ldc_w 593
    //   326: iload 4
    //   328: invokestatic 345	java/lang/Integer:valueOf	(I)Ljava/lang/Integer;
    //   331: invokevirtual 591	java/lang/Integer:toString	()Ljava/lang/String;
    //   334: invokespecial 489	org/apache/http/message/BasicNameValuePair:<init>	(Ljava/lang/String;Ljava/lang/String;)V
    //   337: invokeinterface 493 2 0
    //   342: pop
    //   343: aload 9
    //   345: astore 10
    //   347: aload 9
    //   349: astore 8
    //   351: aload 11
    //   353: new 487	org/apache/http/message/BasicNameValuePair
    //   356: dup
    //   357: ldc_w 595
    //   360: iload 5
    //   362: invokestatic 345	java/lang/Integer:valueOf	(I)Ljava/lang/Integer;
    //   365: invokevirtual 591	java/lang/Integer:toString	()Ljava/lang/String;
    //   368: invokespecial 489	org/apache/http/message/BasicNameValuePair:<init>	(Ljava/lang/String;Ljava/lang/String;)V
    //   371: invokeinterface 493 2 0
    //   376: pop
    //   377: aload 9
    //   379: astore 10
    //   381: aload 9
    //   383: astore 8
    //   385: aload 11
    //   387: new 487	org/apache/http/message/BasicNameValuePair
    //   390: dup
    //   391: ldc_w 596
    //   394: ldc_w 598
    //   397: invokespecial 489	org/apache/http/message/BasicNameValuePair:<init>	(Ljava/lang/String;Ljava/lang/String;)V
    //   400: invokeinterface 493 2 0
    //   405: pop
    //   406: iload 6
    //   408: ifeq +510 -> 918
    //   411: aload 9
    //   413: astore 10
    //   415: aload 9
    //   417: astore 8
    //   419: aload 11
    //   421: new 487	org/apache/http/message/BasicNameValuePair
    //   424: dup
    //   425: ldc_w 600
    //   428: ldc_w 598
    //   431: invokespecial 489	org/apache/http/message/BasicNameValuePair:<init>	(Ljava/lang/String;Ljava/lang/String;)V
    //   434: invokeinterface 493 2 0
    //   439: pop
    //   440: aload 9
    //   442: astore 10
    //   444: aload 9
    //   446: astore 8
    //   448: new 62	java/lang/StringBuilder
    //   451: dup
    //   452: ldc_w 602
    //   455: invokespecial 67	java/lang/StringBuilder:<init>	(Ljava/lang/String;)V
    //   458: aload 12
    //   460: invokevirtual 104	java/lang/StringBuilder:append	(Ljava/lang/String;)Ljava/lang/StringBuilder;
    //   463: ldc_w 506
    //   466: invokevirtual 104	java/lang/StringBuilder:append	(Ljava/lang/String;)Ljava/lang/StringBuilder;
    //   469: aload_2
    //   470: invokevirtual 104	java/lang/StringBuilder:append	(Ljava/lang/String;)Ljava/lang/StringBuilder;
    //   473: ldc_w 604
    //   476: invokevirtual 104	java/lang/StringBuilder:append	(Ljava/lang/String;)Ljava/lang/StringBuilder;
    //   479: iload 5
    //   481: invokestatic 345	java/lang/Integer:valueOf	(I)Ljava/lang/Integer;
    //   484: invokevirtual 591	java/lang/Integer:toString	()Ljava/lang/String;
    //   487: invokevirtual 104	java/lang/StringBuilder:append	(Ljava/lang/String;)Ljava/lang/StringBuilder;
    //   490: ldc_w 606
    //   493: invokevirtual 104	java/lang/StringBuilder:append	(Ljava/lang/String;)Ljava/lang/StringBuilder;
    //   496: iload_3
    //   497: invokestatic 345	java/lang/Integer:valueOf	(I)Ljava/lang/Integer;
    //   500: invokevirtual 591	java/lang/Integer:toString	()Ljava/lang/String;
    //   503: invokevirtual 104	java/lang/StringBuilder:append	(Ljava/lang/String;)Ljava/lang/StringBuilder;
    //   506: ldc_w 508
    //   509: invokevirtual 104	java/lang/StringBuilder:append	(Ljava/lang/String;)Ljava/lang/StringBuilder;
    //   512: aload_1
    //   513: invokevirtual 104	java/lang/StringBuilder:append	(Ljava/lang/String;)Ljava/lang/StringBuilder;
    //   516: ldc_w 608
    //   519: invokevirtual 104	java/lang/StringBuilder:append	(Ljava/lang/String;)Ljava/lang/StringBuilder;
    //   522: iload 4
    //   524: invokestatic 345	java/lang/Integer:valueOf	(I)Ljava/lang/Integer;
    //   527: invokevirtual 591	java/lang/Integer:toString	()Ljava/lang/String;
    //   530: invokevirtual 104	java/lang/StringBuilder:append	(Ljava/lang/String;)Ljava/lang/StringBuilder;
    //   533: ldc_w 610
    //   536: invokevirtual 104	java/lang/StringBuilder:append	(Ljava/lang/String;)Ljava/lang/StringBuilder;
    //   539: invokevirtual 74	java/lang/StringBuilder:toString	()Ljava/lang/String;
    //   542: astore_1
    //   543: aload 9
    //   545: astore 8
    //   547: new 510	javax/crypto/spec/SecretKeySpec
    //   550: dup
    //   551: aload_0
    //   552: invokespecial 513	df:e	()Ljava/lang/String;
    //   555: invokevirtual 517	java/lang/String:getBytes	()[B
    //   558: ldc_w 519
    //   561: invokespecial 522	javax/crypto/spec/SecretKeySpec:<init>	([BLjava/lang/String;)V
    //   564: astore_2
    //   565: aload 9
    //   567: astore 8
    //   569: ldc_w 519
    //   572: invokestatic 527	javax/crypto/Mac:getInstance	(Ljava/lang/String;)Ljavax/crypto/Mac;
    //   575: astore 10
    //   577: aload 9
    //   579: astore 8
    //   581: aload 10
    //   583: aload_2
    //   584: invokevirtual 531	javax/crypto/Mac:init	(Ljava/security/Key;)V
    //   587: aload 9
    //   589: astore 8
    //   591: aload 11
    //   593: new 487	org/apache/http/message/BasicNameValuePair
    //   596: dup
    //   597: ldc_w 533
    //   600: aload 10
    //   602: aload_1
    //   603: invokevirtual 517	java/lang/String:getBytes	()[B
    //   606: invokevirtual 537	javax/crypto/Mac:doFinal	([B)[B
    //   609: iconst_2
    //   610: invokestatic 543	android/util/Base64:encodeToString	([BI)Ljava/lang/String;
    //   613: invokespecial 489	org/apache/http/message/BasicNameValuePair:<init>	(Ljava/lang/String;Ljava/lang/String;)V
    //   616: invokeinterface 493 2 0
    //   621: pop
    //   622: aload 9
    //   624: astore 10
    //   626: aload 9
    //   628: astore 8
    //   630: aload 9
    //   632: invokevirtual 547	java/net/HttpURLConnection:getOutputStream	()Ljava/io/OutputStream;
    //   635: astore_1
    //   636: aload 9
    //   638: astore 10
    //   640: aload 9
    //   642: astore 8
    //   644: new 549	java/io/BufferedWriter
    //   647: dup
    //   648: new 551	java/io/OutputStreamWriter
    //   651: dup
    //   652: aload_1
    //   653: ldc -118
    //   655: invokespecial 554	java/io/OutputStreamWriter:<init>	(Ljava/io/OutputStream;Ljava/lang/String;)V
    //   658: invokespecial 557	java/io/BufferedWriter:<init>	(Ljava/io/Writer;)V
    //   661: astore_2
    //   662: aload 9
    //   664: astore 10
    //   666: aload 9
    //   668: astore 8
    //   670: aload_2
    //   671: aload 11
    //   673: invokestatic 559	df:a	(Ljava/util/List;)Ljava/lang/String;
    //   676: invokevirtual 562	java/io/BufferedWriter:write	(Ljava/lang/String;)V
    //   679: aload 9
    //   681: astore 10
    //   683: aload 9
    //   685: astore 8
    //   687: aload_2
    //   688: invokevirtual 563	java/io/BufferedWriter:close	()V
    //   691: aload 9
    //   693: astore 10
    //   695: aload 9
    //   697: astore 8
    //   699: aload_1
    //   700: invokevirtual 566	java/io/OutputStream:close	()V
    //   703: aload 9
    //   705: astore 10
    //   707: aload 9
    //   709: astore 8
    //   711: aload 9
    //   713: invokevirtual 313	java/net/HttpURLConnection:getResponseCode	()I
    //   716: istore_3
    //   717: iload_3
    //   718: sipush 200
    //   721: if_icmpeq +441 -> 1162
    //   724: aload 9
    //   726: astore 10
    //   728: aload 9
    //   730: astore 8
    //   732: new 79	com/arrownock/exception/ArrownockException
    //   735: dup
    //   736: new 315	org/json/JSONObject
    //   739: dup
    //   740: new 317	java/io/BufferedInputStream
    //   743: dup
    //   744: aload 9
    //   746: invokevirtual 355	java/net/HttpURLConnection:getErrorStream	()Ljava/io/InputStream;
    //   749: invokespecial 322	java/io/BufferedInputStream:<init>	(Ljava/io/InputStream;)V
    //   752: invokestatic 324	df:a	(Ljava/io/InputStream;)Ljava/lang/String;
    //   755: invokespecial 325	org/json/JSONObject:<init>	(Ljava/lang/String;)V
    //   758: ldc_w 568
    //   761: invokevirtual 572	org/json/JSONObject:getJSONObject	(Ljava/lang/String;)Lorg/json/JSONObject;
    //   764: ldc_w 357
    //   767: invokevirtual 331	org/json/JSONObject:getString	(Ljava/lang/String;)Ljava/lang/String;
    //   770: sipush 2007
    //   773: invokespecial 575	com/arrownock/exception/ArrownockException:<init>	(Ljava/lang/String;I)V
    //   776: athrow
    //   777: astore_1
    //   778: aload 9
    //   780: astore 10
    //   782: aload 9
    //   784: astore 8
    //   786: new 79	com/arrownock/exception/ArrownockException
    //   789: dup
    //   790: aload_1
    //   791: invokevirtual 578	org/json/JSONException:getMessage	()Ljava/lang/String;
    //   794: sipush 2007
    //   797: invokespecial 575	com/arrownock/exception/ArrownockException:<init>	(Ljava/lang/String;I)V
    //   800: athrow
    //   801: astore_1
    //   802: aload 9
    //   804: astore 10
    //   806: aload 9
    //   808: astore 8
    //   810: new 79	com/arrownock/exception/ArrownockException
    //   813: dup
    //   814: aload_1
    //   815: invokevirtual 579	java/io/IOException:getMessage	()Ljava/lang/String;
    //   818: sipush 2007
    //   821: invokespecial 575	com/arrownock/exception/ArrownockException:<init>	(Ljava/lang/String;I)V
    //   824: athrow
    //   825: astore_1
    //   826: aload 10
    //   828: astore 8
    //   830: aload_1
    //   831: instanceof 79
    //   834: ifeq +339 -> 1173
    //   837: aload 10
    //   839: astore 8
    //   841: aload_1
    //   842: checkcast 79	com/arrownock/exception/ArrownockException
    //   845: athrow
    //   846: astore_1
    //   847: aload 8
    //   849: ifnull +8 -> 857
    //   852: aload 8
    //   854: invokevirtual 350	java/net/HttpURLConnection:disconnect	()V
    //   857: aload_1
    //   858: athrow
    //   859: aload 9
    //   861: astore 10
    //   863: aload 11
    //   865: astore 8
    //   867: new 272	java/net/URL
    //   870: dup
    //   871: new 62	java/lang/StringBuilder
    //   874: dup
    //   875: ldc_w 352
    //   878: invokespecial 67	java/lang/StringBuilder:<init>	(Ljava/lang/String;)V
    //   881: aload_0
    //   882: invokespecial 445	df:c	()Ljava/lang/String;
    //   885: invokevirtual 104	java/lang/StringBuilder:append	(Ljava/lang/String;)Ljava/lang/StringBuilder;
    //   888: ldc_w 588
    //   891: invokevirtual 104	java/lang/StringBuilder:append	(Ljava/lang/String;)Ljava/lang/StringBuilder;
    //   894: aload_1
    //   895: invokevirtual 450	java/lang/String:trim	()Ljava/lang/String;
    //   898: invokevirtual 104	java/lang/StringBuilder:append	(Ljava/lang/String;)Ljava/lang/StringBuilder;
    //   901: invokevirtual 74	java/lang/StringBuilder:toString	()Ljava/lang/String;
    //   904: invokespecial 275	java/net/URL:<init>	(Ljava/lang/String;)V
    //   907: invokevirtual 279	java/net/URL:openConnection	()Ljava/net/URLConnection;
    //   910: checkcast 307	java/net/HttpURLConnection
    //   913: astore 9
    //   915: goto -793 -> 122
    //   918: aload 9
    //   920: astore 10
    //   922: aload 9
    //   924: astore 8
    //   926: aload 11
    //   928: new 487	org/apache/http/message/BasicNameValuePair
    //   931: dup
    //   932: ldc_w 600
    //   935: ldc_w 612
    //   938: invokespecial 489	org/apache/http/message/BasicNameValuePair:<init>	(Ljava/lang/String;Ljava/lang/String;)V
    //   941: invokeinterface 493 2 0
    //   946: pop
    //   947: aload 9
    //   949: astore 10
    //   951: aload 9
    //   953: astore 8
    //   955: new 62	java/lang/StringBuilder
    //   958: dup
    //   959: ldc_w 602
    //   962: invokespecial 67	java/lang/StringBuilder:<init>	(Ljava/lang/String;)V
    //   965: aload 12
    //   967: invokevirtual 104	java/lang/StringBuilder:append	(Ljava/lang/String;)Ljava/lang/StringBuilder;
    //   970: ldc_w 506
    //   973: invokevirtual 104	java/lang/StringBuilder:append	(Ljava/lang/String;)Ljava/lang/StringBuilder;
    //   976: aload_2
    //   977: invokevirtual 104	java/lang/StringBuilder:append	(Ljava/lang/String;)Ljava/lang/StringBuilder;
    //   980: ldc_w 604
    //   983: invokevirtual 104	java/lang/StringBuilder:append	(Ljava/lang/String;)Ljava/lang/StringBuilder;
    //   986: iload 5
    //   988: invokestatic 345	java/lang/Integer:valueOf	(I)Ljava/lang/Integer;
    //   991: invokevirtual 591	java/lang/Integer:toString	()Ljava/lang/String;
    //   994: invokevirtual 104	java/lang/StringBuilder:append	(Ljava/lang/String;)Ljava/lang/StringBuilder;
    //   997: ldc_w 606
    //   1000: invokevirtual 104	java/lang/StringBuilder:append	(Ljava/lang/String;)Ljava/lang/StringBuilder;
    //   1003: iload_3
    //   1004: invokestatic 345	java/lang/Integer:valueOf	(I)Ljava/lang/Integer;
    //   1007: invokevirtual 591	java/lang/Integer:toString	()Ljava/lang/String;
    //   1010: invokevirtual 104	java/lang/StringBuilder:append	(Ljava/lang/String;)Ljava/lang/StringBuilder;
    //   1013: ldc_w 508
    //   1016: invokevirtual 104	java/lang/StringBuilder:append	(Ljava/lang/String;)Ljava/lang/StringBuilder;
    //   1019: aload_1
    //   1020: invokevirtual 104	java/lang/StringBuilder:append	(Ljava/lang/String;)Ljava/lang/StringBuilder;
    //   1023: ldc_w 608
    //   1026: invokevirtual 104	java/lang/StringBuilder:append	(Ljava/lang/String;)Ljava/lang/StringBuilder;
    //   1029: iload 4
    //   1031: invokestatic 345	java/lang/Integer:valueOf	(I)Ljava/lang/Integer;
    //   1034: invokevirtual 591	java/lang/Integer:toString	()Ljava/lang/String;
    //   1037: invokevirtual 104	java/lang/StringBuilder:append	(Ljava/lang/String;)Ljava/lang/StringBuilder;
    //   1040: ldc_w 614
    //   1043: invokevirtual 104	java/lang/StringBuilder:append	(Ljava/lang/String;)Ljava/lang/StringBuilder;
    //   1046: invokevirtual 74	java/lang/StringBuilder:toString	()Ljava/lang/String;
    //   1049: astore_1
    //   1050: goto -507 -> 543
    //   1053: aload 9
    //   1055: astore 10
    //   1057: aload 9
    //   1059: astore 8
    //   1061: aload 11
    //   1063: new 487	org/apache/http/message/BasicNameValuePair
    //   1066: dup
    //   1067: ldc_w 596
    //   1070: ldc_w 612
    //   1073: invokespecial 489	org/apache/http/message/BasicNameValuePair:<init>	(Ljava/lang/String;Ljava/lang/String;)V
    //   1076: invokeinterface 493 2 0
    //   1081: pop
    //   1082: aload 9
    //   1084: astore 10
    //   1086: aload 9
    //   1088: astore 8
    //   1090: new 62	java/lang/StringBuilder
    //   1093: dup
    //   1094: ldc_w 602
    //   1097: invokespecial 67	java/lang/StringBuilder:<init>	(Ljava/lang/String;)V
    //   1100: aload 12
    //   1102: invokevirtual 104	java/lang/StringBuilder:append	(Ljava/lang/String;)Ljava/lang/StringBuilder;
    //   1105: ldc_w 506
    //   1108: invokevirtual 104	java/lang/StringBuilder:append	(Ljava/lang/String;)Ljava/lang/StringBuilder;
    //   1111: aload_2
    //   1112: invokevirtual 104	java/lang/StringBuilder:append	(Ljava/lang/String;)Ljava/lang/StringBuilder;
    //   1115: ldc_w 508
    //   1118: invokevirtual 104	java/lang/StringBuilder:append	(Ljava/lang/String;)Ljava/lang/StringBuilder;
    //   1121: aload_1
    //   1122: invokevirtual 104	java/lang/StringBuilder:append	(Ljava/lang/String;)Ljava/lang/StringBuilder;
    //   1125: ldc_w 616
    //   1128: invokevirtual 104	java/lang/StringBuilder:append	(Ljava/lang/String;)Ljava/lang/StringBuilder;
    //   1131: invokevirtual 74	java/lang/StringBuilder:toString	()Ljava/lang/String;
    //   1134: astore_1
    //   1135: goto -592 -> 543
    //   1138: astore_1
    //   1139: aload 9
    //   1141: astore 10
    //   1143: aload 9
    //   1145: astore 8
    //   1147: new 79	com/arrownock/exception/ArrownockException
    //   1150: dup
    //   1151: aload_1
    //   1152: invokevirtual 580	java/lang/Exception:getMessage	()Ljava/lang/String;
    //   1155: sipush 2007
    //   1158: invokespecial 575	com/arrownock/exception/ArrownockException:<init>	(Ljava/lang/String;I)V
    //   1161: athrow
    //   1162: aload 9
    //   1164: ifnull +8 -> 1172
    //   1167: aload 9
    //   1169: invokevirtual 350	java/net/HttpURLConnection:disconnect	()V
    //   1172: return
    //   1173: aload 10
    //   1175: astore 8
    //   1177: new 79	com/arrownock/exception/ArrownockException
    //   1180: dup
    //   1181: aload_1
    //   1182: invokevirtual 580	java/lang/Exception:getMessage	()Ljava/lang/String;
    //   1185: sipush 2007
    //   1188: invokespecial 575	com/arrownock/exception/ArrownockException:<init>	(Ljava/lang/String;I)V
    //   1191: athrow
    //   1192: astore_1
    //   1193: aload 9
    //   1195: astore 8
    //   1197: goto -350 -> 847
    //   1200: astore_1
    //   1201: aload 9
    //   1203: astore 10
    //   1205: goto -379 -> 826
    // Local variable table:
    //   start	length	slot	name	signature
    //   0	1208	0	this	df
    //   0	1208	1	paramString1	String
    //   0	1208	2	paramString2	String
    //   0	1208	3	paramInt1	int
    //   0	1208	4	paramInt2	int
    //   0	1208	5	paramInt3	int
    //   0	1208	6	paramBoolean1	boolean
    //   0	1208	7	paramBoolean2	boolean
    //   12	1184	8	localObject1	Object
    //   4	1198	9	localObject2	Object
    //   8	1196	10	localObject3	Object
    //   1	1061	11	localArrayList	java.util.ArrayList
    //   197	904	12	str	String
    // Exception table:
    //   from	to	target	type
    //   732	777	777	org/json/JSONException
    //   174	199	801	java/io/IOException
    //   207	216	801	java/io/IOException
    //   224	243	801	java/io/IOException
    //   251	271	801	java/io/IOException
    //   284	309	801	java/io/IOException
    //   317	343	801	java/io/IOException
    //   351	377	801	java/io/IOException
    //   385	406	801	java/io/IOException
    //   419	440	801	java/io/IOException
    //   448	543	801	java/io/IOException
    //   547	565	801	java/io/IOException
    //   569	577	801	java/io/IOException
    //   581	587	801	java/io/IOException
    //   591	622	801	java/io/IOException
    //   630	636	801	java/io/IOException
    //   644	662	801	java/io/IOException
    //   670	679	801	java/io/IOException
    //   687	691	801	java/io/IOException
    //   699	703	801	java/io/IOException
    //   711	717	801	java/io/IOException
    //   732	777	801	java/io/IOException
    //   786	801	801	java/io/IOException
    //   926	947	801	java/io/IOException
    //   955	1050	801	java/io/IOException
    //   1061	1082	801	java/io/IOException
    //   1090	1135	801	java/io/IOException
    //   1147	1162	801	java/io/IOException
    //   14	27	825	java/lang/Exception
    //   35	83	825	java/lang/Exception
    //   130	138	825	java/lang/Exception
    //   146	152	825	java/lang/Exception
    //   160	166	825	java/lang/Exception
    //   174	199	825	java/lang/Exception
    //   207	216	825	java/lang/Exception
    //   224	243	825	java/lang/Exception
    //   251	271	825	java/lang/Exception
    //   284	309	825	java/lang/Exception
    //   317	343	825	java/lang/Exception
    //   351	377	825	java/lang/Exception
    //   385	406	825	java/lang/Exception
    //   419	440	825	java/lang/Exception
    //   448	543	825	java/lang/Exception
    //   630	636	825	java/lang/Exception
    //   644	662	825	java/lang/Exception
    //   670	679	825	java/lang/Exception
    //   687	691	825	java/lang/Exception
    //   699	703	825	java/lang/Exception
    //   711	717	825	java/lang/Exception
    //   732	777	825	java/lang/Exception
    //   786	801	825	java/lang/Exception
    //   810	825	825	java/lang/Exception
    //   867	915	825	java/lang/Exception
    //   926	947	825	java/lang/Exception
    //   955	1050	825	java/lang/Exception
    //   1061	1082	825	java/lang/Exception
    //   1090	1135	825	java/lang/Exception
    //   1147	1162	825	java/lang/Exception
    //   14	27	846	finally
    //   35	83	846	finally
    //   130	138	846	finally
    //   146	152	846	finally
    //   160	166	846	finally
    //   174	199	846	finally
    //   207	216	846	finally
    //   224	243	846	finally
    //   251	271	846	finally
    //   284	309	846	finally
    //   317	343	846	finally
    //   351	377	846	finally
    //   385	406	846	finally
    //   419	440	846	finally
    //   448	543	846	finally
    //   547	565	846	finally
    //   569	577	846	finally
    //   581	587	846	finally
    //   591	622	846	finally
    //   630	636	846	finally
    //   644	662	846	finally
    //   670	679	846	finally
    //   687	691	846	finally
    //   699	703	846	finally
    //   711	717	846	finally
    //   732	777	846	finally
    //   786	801	846	finally
    //   810	825	846	finally
    //   830	837	846	finally
    //   841	846	846	finally
    //   867	915	846	finally
    //   926	947	846	finally
    //   955	1050	846	finally
    //   1061	1082	846	finally
    //   1090	1135	846	finally
    //   1147	1162	846	finally
    //   1177	1192	846	finally
    //   547	565	1138	java/lang/Exception
    //   569	577	1138	java/lang/Exception
    //   581	587	1138	java/lang/Exception
    //   591	622	1138	java/lang/Exception
    //   83	122	1192	finally
    //   83	122	1200	java/lang/Exception
  }
  
  /* Error */
  private void a(String paramString1, String paramString2, boolean paramBoolean, int paramInt1, int paramInt2, int paramInt3)
    throws ArrownockException
  {
    // Byte code:
    //   0: aconst_null
    //   1: astore 10
    //   3: aconst_null
    //   4: astore 8
    //   6: aload 8
    //   8: astore 9
    //   10: aload 10
    //   12: astore 7
    //   14: aload_0
    //   15: getfield 34	df:jdField_a_of_type_AndroidContentContext	Landroid/content/Context;
    //   18: invokestatic 267	com/arrownock/push/AnPush:getInstance	(Landroid/content/Context;)Lcom/arrownock/push/AnPush;
    //   21: invokevirtual 270	com/arrownock/push/AnPush:isSecureConnection	()Z
    //   24: ifeq +765 -> 789
    //   27: aload 8
    //   29: astore 9
    //   31: aload 10
    //   33: astore 7
    //   35: new 272	java/net/URL
    //   38: dup
    //   39: new 62	java/lang/StringBuilder
    //   42: dup
    //   43: ldc_w 274
    //   46: invokespecial 67	java/lang/StringBuilder:<init>	(Ljava/lang/String;)V
    //   49: aload_0
    //   50: invokespecial 445	df:c	()Ljava/lang/String;
    //   53: invokevirtual 104	java/lang/StringBuilder:append	(Ljava/lang/String;)Ljava/lang/StringBuilder;
    //   56: ldc_w 618
    //   59: invokevirtual 104	java/lang/StringBuilder:append	(Ljava/lang/String;)Ljava/lang/StringBuilder;
    //   62: aload_1
    //   63: invokevirtual 450	java/lang/String:trim	()Ljava/lang/String;
    //   66: invokevirtual 104	java/lang/StringBuilder:append	(Ljava/lang/String;)Ljava/lang/StringBuilder;
    //   69: invokevirtual 74	java/lang/StringBuilder:toString	()Ljava/lang/String;
    //   72: invokespecial 275	java/net/URL:<init>	(Ljava/lang/String;)V
    //   75: invokevirtual 279	java/net/URL:openConnection	()Ljava/net/URLConnection;
    //   78: checkcast 281	javax/net/ssl/HttpsURLConnection
    //   81: astore 8
    //   83: aload 8
    //   85: checkcast 281	javax/net/ssl/HttpsURLConnection
    //   88: getstatic 29	df:jdField_a_of_type_JavaxNetSslHostnameVerifier	Ljavax/net/ssl/HostnameVerifier;
    //   91: invokevirtual 285	javax/net/ssl/HttpsURLConnection:setHostnameVerifier	(Ljavax/net/ssl/HostnameVerifier;)V
    //   94: aload 8
    //   96: checkcast 281	javax/net/ssl/HttpsURLConnection
    //   99: aload_0
    //   100: invokespecial 288	df:f	()Ljava/lang/String;
    //   103: aload_0
    //   104: invokespecial 291	df:g	()Ljava/lang/String;
    //   107: aload_0
    //   108: invokespecial 294	df:h	()Ljava/lang/String;
    //   111: ldc -63
    //   113: ldc_w 296
    //   116: invokestatic 301	at:a	(Ljava/lang/String;Ljava/lang/String;Ljava/lang/String;Ljava/lang/String;Ljava/lang/String;)Ljavax/net/ssl/SSLSocketFactory;
    //   119: invokevirtual 305	javax/net/ssl/HttpsURLConnection:setSSLSocketFactory	(Ljavax/net/ssl/SSLSocketFactory;)V
    //   122: aload 8
    //   124: astore 9
    //   126: aload 8
    //   128: astore 7
    //   130: aload 8
    //   132: ldc_w 452
    //   135: invokevirtual 455	java/net/HttpURLConnection:setRequestMethod	(Ljava/lang/String;)V
    //   138: aload 8
    //   140: astore 9
    //   142: aload 8
    //   144: astore 7
    //   146: aload 8
    //   148: iconst_1
    //   149: invokevirtual 459	java/net/HttpURLConnection:setDoInput	(Z)V
    //   152: aload 8
    //   154: astore 9
    //   156: aload 8
    //   158: astore 7
    //   160: aload 8
    //   162: iconst_1
    //   163: invokevirtual 462	java/net/HttpURLConnection:setDoOutput	(Z)V
    //   166: aload 8
    //   168: astore 9
    //   170: aload 8
    //   172: astore 7
    //   174: new 464	java/text/SimpleDateFormat
    //   177: dup
    //   178: ldc_w 466
    //   181: getstatic 472	java/util/Locale:US	Ljava/util/Locale;
    //   184: invokespecial 475	java/text/SimpleDateFormat:<init>	(Ljava/lang/String;Ljava/util/Locale;)V
    //   187: new 477	java/util/Date
    //   190: dup
    //   191: invokespecial 478	java/util/Date:<init>	()V
    //   194: invokevirtual 482	java/text/SimpleDateFormat:format	(Ljava/util/Date;)Ljava/lang/String;
    //   197: astore 11
    //   199: aload 8
    //   201: astore 9
    //   203: aload 8
    //   205: astore 7
    //   207: new 484	java/util/ArrayList
    //   210: dup
    //   211: invokespecial 485	java/util/ArrayList:<init>	()V
    //   214: astore 10
    //   216: aload 8
    //   218: astore 9
    //   220: aload 8
    //   222: astore 7
    //   224: aload 10
    //   226: new 487	org/apache/http/message/BasicNameValuePair
    //   229: dup
    //   230: ldc_w 327
    //   233: aload_2
    //   234: invokespecial 489	org/apache/http/message/BasicNameValuePair:<init>	(Ljava/lang/String;Ljava/lang/String;)V
    //   237: invokeinterface 493 2 0
    //   242: pop
    //   243: aload 8
    //   245: astore 9
    //   247: aload 8
    //   249: astore 7
    //   251: aload 10
    //   253: new 487	org/apache/http/message/BasicNameValuePair
    //   256: dup
    //   257: ldc_w 495
    //   260: aload 11
    //   262: invokespecial 489	org/apache/http/message/BasicNameValuePair:<init>	(Ljava/lang/String;Ljava/lang/String;)V
    //   265: invokeinterface 493 2 0
    //   270: pop
    //   271: iload 4
    //   273: iconst_m1
    //   274: if_icmpeq +105 -> 379
    //   277: aload 8
    //   279: astore 9
    //   281: aload 8
    //   283: astore 7
    //   285: aload 10
    //   287: new 487	org/apache/http/message/BasicNameValuePair
    //   290: dup
    //   291: ldc_w 590
    //   294: iload 4
    //   296: invokestatic 345	java/lang/Integer:valueOf	(I)Ljava/lang/Integer;
    //   299: invokevirtual 591	java/lang/Integer:toString	()Ljava/lang/String;
    //   302: invokespecial 489	org/apache/http/message/BasicNameValuePair:<init>	(Ljava/lang/String;Ljava/lang/String;)V
    //   305: invokeinterface 493 2 0
    //   310: pop
    //   311: aload 8
    //   313: astore 9
    //   315: aload 8
    //   317: astore 7
    //   319: aload 10
    //   321: new 487	org/apache/http/message/BasicNameValuePair
    //   324: dup
    //   325: ldc_w 593
    //   328: iload 5
    //   330: invokestatic 345	java/lang/Integer:valueOf	(I)Ljava/lang/Integer;
    //   333: invokevirtual 591	java/lang/Integer:toString	()Ljava/lang/String;
    //   336: invokespecial 489	org/apache/http/message/BasicNameValuePair:<init>	(Ljava/lang/String;Ljava/lang/String;)V
    //   339: invokeinterface 493 2 0
    //   344: pop
    //   345: aload 8
    //   347: astore 9
    //   349: aload 8
    //   351: astore 7
    //   353: aload 10
    //   355: new 487	org/apache/http/message/BasicNameValuePair
    //   358: dup
    //   359: ldc_w 595
    //   362: iload 6
    //   364: invokestatic 345	java/lang/Integer:valueOf	(I)Ljava/lang/Integer;
    //   367: invokevirtual 591	java/lang/Integer:toString	()Ljava/lang/String;
    //   370: invokespecial 489	org/apache/http/message/BasicNameValuePair:<init>	(Ljava/lang/String;Ljava/lang/String;)V
    //   373: invokeinterface 493 2 0
    //   378: pop
    //   379: iload_3
    //   380: ifeq +572 -> 952
    //   383: aload 8
    //   385: astore 9
    //   387: aload 8
    //   389: astore 7
    //   391: aload 10
    //   393: new 487	org/apache/http/message/BasicNameValuePair
    //   396: dup
    //   397: ldc_w 620
    //   400: ldc_w 598
    //   403: invokespecial 489	org/apache/http/message/BasicNameValuePair:<init>	(Ljava/lang/String;Ljava/lang/String;)V
    //   406: invokeinterface 493 2 0
    //   411: pop
    //   412: iload 4
    //   414: iconst_m1
    //   415: if_icmpne +433 -> 848
    //   418: aload 8
    //   420: astore 9
    //   422: aload 8
    //   424: astore 7
    //   426: new 62	java/lang/StringBuilder
    //   429: dup
    //   430: ldc_w 622
    //   433: invokespecial 67	java/lang/StringBuilder:<init>	(Ljava/lang/String;)V
    //   436: aload 11
    //   438: invokevirtual 104	java/lang/StringBuilder:append	(Ljava/lang/String;)Ljava/lang/StringBuilder;
    //   441: ldc_w 506
    //   444: invokevirtual 104	java/lang/StringBuilder:append	(Ljava/lang/String;)Ljava/lang/StringBuilder;
    //   447: aload_2
    //   448: invokevirtual 104	java/lang/StringBuilder:append	(Ljava/lang/String;)Ljava/lang/StringBuilder;
    //   451: ldc_w 508
    //   454: invokevirtual 104	java/lang/StringBuilder:append	(Ljava/lang/String;)Ljava/lang/StringBuilder;
    //   457: aload_1
    //   458: invokevirtual 104	java/lang/StringBuilder:append	(Ljava/lang/String;)Ljava/lang/StringBuilder;
    //   461: ldc_w 624
    //   464: invokevirtual 104	java/lang/StringBuilder:append	(Ljava/lang/String;)Ljava/lang/StringBuilder;
    //   467: invokevirtual 74	java/lang/StringBuilder:toString	()Ljava/lang/String;
    //   470: astore_1
    //   471: aload 8
    //   473: astore 7
    //   475: new 510	javax/crypto/spec/SecretKeySpec
    //   478: dup
    //   479: aload_0
    //   480: invokespecial 513	df:e	()Ljava/lang/String;
    //   483: invokevirtual 517	java/lang/String:getBytes	()[B
    //   486: ldc_w 519
    //   489: invokespecial 522	javax/crypto/spec/SecretKeySpec:<init>	([BLjava/lang/String;)V
    //   492: astore_2
    //   493: aload 8
    //   495: astore 7
    //   497: ldc_w 519
    //   500: invokestatic 527	javax/crypto/Mac:getInstance	(Ljava/lang/String;)Ljavax/crypto/Mac;
    //   503: astore 9
    //   505: aload 8
    //   507: astore 7
    //   509: aload 9
    //   511: aload_2
    //   512: invokevirtual 531	javax/crypto/Mac:init	(Ljava/security/Key;)V
    //   515: aload 8
    //   517: astore 7
    //   519: aload 10
    //   521: new 487	org/apache/http/message/BasicNameValuePair
    //   524: dup
    //   525: ldc_w 533
    //   528: aload 9
    //   530: aload_1
    //   531: invokevirtual 517	java/lang/String:getBytes	()[B
    //   534: invokevirtual 537	javax/crypto/Mac:doFinal	([B)[B
    //   537: iconst_2
    //   538: invokestatic 543	android/util/Base64:encodeToString	([BI)Ljava/lang/String;
    //   541: invokespecial 489	org/apache/http/message/BasicNameValuePair:<init>	(Ljava/lang/String;Ljava/lang/String;)V
    //   544: invokeinterface 493 2 0
    //   549: pop
    //   550: aload 8
    //   552: astore 9
    //   554: aload 8
    //   556: astore 7
    //   558: aload 8
    //   560: invokevirtual 547	java/net/HttpURLConnection:getOutputStream	()Ljava/io/OutputStream;
    //   563: astore_1
    //   564: aload 8
    //   566: astore 9
    //   568: aload 8
    //   570: astore 7
    //   572: new 549	java/io/BufferedWriter
    //   575: dup
    //   576: new 551	java/io/OutputStreamWriter
    //   579: dup
    //   580: aload_1
    //   581: ldc -118
    //   583: invokespecial 554	java/io/OutputStreamWriter:<init>	(Ljava/io/OutputStream;Ljava/lang/String;)V
    //   586: invokespecial 557	java/io/BufferedWriter:<init>	(Ljava/io/Writer;)V
    //   589: astore_2
    //   590: aload 8
    //   592: astore 9
    //   594: aload 8
    //   596: astore 7
    //   598: aload_2
    //   599: aload 10
    //   601: invokestatic 559	df:a	(Ljava/util/List;)Ljava/lang/String;
    //   604: invokevirtual 562	java/io/BufferedWriter:write	(Ljava/lang/String;)V
    //   607: aload 8
    //   609: astore 9
    //   611: aload 8
    //   613: astore 7
    //   615: aload_2
    //   616: invokevirtual 563	java/io/BufferedWriter:close	()V
    //   619: aload 8
    //   621: astore 9
    //   623: aload 8
    //   625: astore 7
    //   627: aload_1
    //   628: invokevirtual 566	java/io/OutputStream:close	()V
    //   631: aload 8
    //   633: astore 9
    //   635: aload 8
    //   637: astore 7
    //   639: aload 8
    //   641: invokevirtual 313	java/net/HttpURLConnection:getResponseCode	()I
    //   644: istore 4
    //   646: iload 4
    //   648: sipush 200
    //   651: if_icmpeq +410 -> 1061
    //   654: aload 8
    //   656: astore 9
    //   658: aload 8
    //   660: astore 7
    //   662: new 79	com/arrownock/exception/ArrownockException
    //   665: dup
    //   666: new 315	org/json/JSONObject
    //   669: dup
    //   670: new 317	java/io/BufferedInputStream
    //   673: dup
    //   674: aload 8
    //   676: invokevirtual 355	java/net/HttpURLConnection:getErrorStream	()Ljava/io/InputStream;
    //   679: invokespecial 322	java/io/BufferedInputStream:<init>	(Ljava/io/InputStream;)V
    //   682: invokestatic 324	df:a	(Ljava/io/InputStream;)Ljava/lang/String;
    //   685: invokespecial 325	org/json/JSONObject:<init>	(Ljava/lang/String;)V
    //   688: ldc_w 568
    //   691: invokevirtual 572	org/json/JSONObject:getJSONObject	(Ljava/lang/String;)Lorg/json/JSONObject;
    //   694: ldc_w 357
    //   697: invokevirtual 331	org/json/JSONObject:getString	(Ljava/lang/String;)Ljava/lang/String;
    //   700: sipush 2006
    //   703: invokespecial 575	com/arrownock/exception/ArrownockException:<init>	(Ljava/lang/String;I)V
    //   706: athrow
    //   707: astore_1
    //   708: aload 8
    //   710: astore 9
    //   712: aload 8
    //   714: astore 7
    //   716: new 79	com/arrownock/exception/ArrownockException
    //   719: dup
    //   720: aload_1
    //   721: invokevirtual 578	org/json/JSONException:getMessage	()Ljava/lang/String;
    //   724: sipush 2006
    //   727: invokespecial 575	com/arrownock/exception/ArrownockException:<init>	(Ljava/lang/String;I)V
    //   730: athrow
    //   731: astore_1
    //   732: aload 8
    //   734: astore 9
    //   736: aload 8
    //   738: astore 7
    //   740: new 79	com/arrownock/exception/ArrownockException
    //   743: dup
    //   744: aload_1
    //   745: invokevirtual 579	java/io/IOException:getMessage	()Ljava/lang/String;
    //   748: sipush 2006
    //   751: invokespecial 575	com/arrownock/exception/ArrownockException:<init>	(Ljava/lang/String;I)V
    //   754: athrow
    //   755: astore_1
    //   756: aload 9
    //   758: astore 7
    //   760: aload_1
    //   761: instanceof 79
    //   764: ifeq +308 -> 1072
    //   767: aload 9
    //   769: astore 7
    //   771: aload_1
    //   772: checkcast 79	com/arrownock/exception/ArrownockException
    //   775: athrow
    //   776: astore_1
    //   777: aload 7
    //   779: ifnull +8 -> 787
    //   782: aload 7
    //   784: invokevirtual 350	java/net/HttpURLConnection:disconnect	()V
    //   787: aload_1
    //   788: athrow
    //   789: aload 8
    //   791: astore 9
    //   793: aload 10
    //   795: astore 7
    //   797: new 272	java/net/URL
    //   800: dup
    //   801: new 62	java/lang/StringBuilder
    //   804: dup
    //   805: ldc_w 352
    //   808: invokespecial 67	java/lang/StringBuilder:<init>	(Ljava/lang/String;)V
    //   811: aload_0
    //   812: invokespecial 445	df:c	()Ljava/lang/String;
    //   815: invokevirtual 104	java/lang/StringBuilder:append	(Ljava/lang/String;)Ljava/lang/StringBuilder;
    //   818: ldc_w 618
    //   821: invokevirtual 104	java/lang/StringBuilder:append	(Ljava/lang/String;)Ljava/lang/StringBuilder;
    //   824: aload_1
    //   825: invokevirtual 450	java/lang/String:trim	()Ljava/lang/String;
    //   828: invokevirtual 104	java/lang/StringBuilder:append	(Ljava/lang/String;)Ljava/lang/StringBuilder;
    //   831: invokevirtual 74	java/lang/StringBuilder:toString	()Ljava/lang/String;
    //   834: invokespecial 275	java/net/URL:<init>	(Ljava/lang/String;)V
    //   837: invokevirtual 279	java/net/URL:openConnection	()Ljava/net/URLConnection;
    //   840: checkcast 307	java/net/HttpURLConnection
    //   843: astore 8
    //   845: goto -723 -> 122
    //   848: aload 8
    //   850: astore 9
    //   852: aload 8
    //   854: astore 7
    //   856: new 62	java/lang/StringBuilder
    //   859: dup
    //   860: ldc_w 622
    //   863: invokespecial 67	java/lang/StringBuilder:<init>	(Ljava/lang/String;)V
    //   866: aload 11
    //   868: invokevirtual 104	java/lang/StringBuilder:append	(Ljava/lang/String;)Ljava/lang/StringBuilder;
    //   871: ldc_w 506
    //   874: invokevirtual 104	java/lang/StringBuilder:append	(Ljava/lang/String;)Ljava/lang/StringBuilder;
    //   877: aload_2
    //   878: invokevirtual 104	java/lang/StringBuilder:append	(Ljava/lang/String;)Ljava/lang/StringBuilder;
    //   881: ldc_w 604
    //   884: invokevirtual 104	java/lang/StringBuilder:append	(Ljava/lang/String;)Ljava/lang/StringBuilder;
    //   887: iload 6
    //   889: invokestatic 345	java/lang/Integer:valueOf	(I)Ljava/lang/Integer;
    //   892: invokevirtual 591	java/lang/Integer:toString	()Ljava/lang/String;
    //   895: invokevirtual 104	java/lang/StringBuilder:append	(Ljava/lang/String;)Ljava/lang/StringBuilder;
    //   898: ldc_w 606
    //   901: invokevirtual 104	java/lang/StringBuilder:append	(Ljava/lang/String;)Ljava/lang/StringBuilder;
    //   904: iload 4
    //   906: invokestatic 345	java/lang/Integer:valueOf	(I)Ljava/lang/Integer;
    //   909: invokevirtual 591	java/lang/Integer:toString	()Ljava/lang/String;
    //   912: invokevirtual 104	java/lang/StringBuilder:append	(Ljava/lang/String;)Ljava/lang/StringBuilder;
    //   915: ldc_w 508
    //   918: invokevirtual 104	java/lang/StringBuilder:append	(Ljava/lang/String;)Ljava/lang/StringBuilder;
    //   921: aload_1
    //   922: invokevirtual 104	java/lang/StringBuilder:append	(Ljava/lang/String;)Ljava/lang/StringBuilder;
    //   925: ldc_w 608
    //   928: invokevirtual 104	java/lang/StringBuilder:append	(Ljava/lang/String;)Ljava/lang/StringBuilder;
    //   931: iload 5
    //   933: invokestatic 345	java/lang/Integer:valueOf	(I)Ljava/lang/Integer;
    //   936: invokevirtual 71	java/lang/StringBuilder:append	(Ljava/lang/Object;)Ljava/lang/StringBuilder;
    //   939: ldc_w 624
    //   942: invokevirtual 104	java/lang/StringBuilder:append	(Ljava/lang/String;)Ljava/lang/StringBuilder;
    //   945: invokevirtual 74	java/lang/StringBuilder:toString	()Ljava/lang/String;
    //   948: astore_1
    //   949: goto -478 -> 471
    //   952: aload 8
    //   954: astore 9
    //   956: aload 8
    //   958: astore 7
    //   960: aload 10
    //   962: new 487	org/apache/http/message/BasicNameValuePair
    //   965: dup
    //   966: ldc_w 620
    //   969: ldc_w 612
    //   972: invokespecial 489	org/apache/http/message/BasicNameValuePair:<init>	(Ljava/lang/String;Ljava/lang/String;)V
    //   975: invokeinterface 493 2 0
    //   980: pop
    //   981: aload 8
    //   983: astore 9
    //   985: aload 8
    //   987: astore 7
    //   989: new 62	java/lang/StringBuilder
    //   992: dup
    //   993: ldc_w 622
    //   996: invokespecial 67	java/lang/StringBuilder:<init>	(Ljava/lang/String;)V
    //   999: aload 11
    //   1001: invokevirtual 104	java/lang/StringBuilder:append	(Ljava/lang/String;)Ljava/lang/StringBuilder;
    //   1004: ldc_w 506
    //   1007: invokevirtual 104	java/lang/StringBuilder:append	(Ljava/lang/String;)Ljava/lang/StringBuilder;
    //   1010: aload_2
    //   1011: invokevirtual 104	java/lang/StringBuilder:append	(Ljava/lang/String;)Ljava/lang/StringBuilder;
    //   1014: ldc_w 508
    //   1017: invokevirtual 104	java/lang/StringBuilder:append	(Ljava/lang/String;)Ljava/lang/StringBuilder;
    //   1020: aload_1
    //   1021: invokevirtual 104	java/lang/StringBuilder:append	(Ljava/lang/String;)Ljava/lang/StringBuilder;
    //   1024: ldc_w 626
    //   1027: invokevirtual 104	java/lang/StringBuilder:append	(Ljava/lang/String;)Ljava/lang/StringBuilder;
    //   1030: invokevirtual 74	java/lang/StringBuilder:toString	()Ljava/lang/String;
    //   1033: astore_1
    //   1034: goto -563 -> 471
    //   1037: astore_1
    //   1038: aload 8
    //   1040: astore 9
    //   1042: aload 8
    //   1044: astore 7
    //   1046: new 79	com/arrownock/exception/ArrownockException
    //   1049: dup
    //   1050: aload_1
    //   1051: invokevirtual 580	java/lang/Exception:getMessage	()Ljava/lang/String;
    //   1054: sipush 2006
    //   1057: invokespecial 575	com/arrownock/exception/ArrownockException:<init>	(Ljava/lang/String;I)V
    //   1060: athrow
    //   1061: aload 8
    //   1063: ifnull +8 -> 1071
    //   1066: aload 8
    //   1068: invokevirtual 350	java/net/HttpURLConnection:disconnect	()V
    //   1071: return
    //   1072: aload 9
    //   1074: astore 7
    //   1076: new 79	com/arrownock/exception/ArrownockException
    //   1079: dup
    //   1080: aload_1
    //   1081: invokevirtual 580	java/lang/Exception:getMessage	()Ljava/lang/String;
    //   1084: sipush 2006
    //   1087: invokespecial 575	com/arrownock/exception/ArrownockException:<init>	(Ljava/lang/String;I)V
    //   1090: athrow
    //   1091: astore_1
    //   1092: aload 8
    //   1094: astore 7
    //   1096: goto -319 -> 777
    //   1099: astore_1
    //   1100: aload 8
    //   1102: astore 9
    //   1104: goto -348 -> 756
    // Local variable table:
    //   start	length	slot	name	signature
    //   0	1107	0	this	df
    //   0	1107	1	paramString1	String
    //   0	1107	2	paramString2	String
    //   0	1107	3	paramBoolean	boolean
    //   0	1107	4	paramInt1	int
    //   0	1107	5	paramInt2	int
    //   0	1107	6	paramInt3	int
    //   12	1083	7	localObject1	Object
    //   4	1097	8	localObject2	Object
    //   8	1095	9	localObject3	Object
    //   1	960	10	localArrayList	java.util.ArrayList
    //   197	803	11	str	String
    // Exception table:
    //   from	to	target	type
    //   662	707	707	org/json/JSONException
    //   174	199	731	java/io/IOException
    //   207	216	731	java/io/IOException
    //   224	243	731	java/io/IOException
    //   251	271	731	java/io/IOException
    //   285	311	731	java/io/IOException
    //   319	345	731	java/io/IOException
    //   353	379	731	java/io/IOException
    //   391	412	731	java/io/IOException
    //   426	471	731	java/io/IOException
    //   475	493	731	java/io/IOException
    //   497	505	731	java/io/IOException
    //   509	515	731	java/io/IOException
    //   519	550	731	java/io/IOException
    //   558	564	731	java/io/IOException
    //   572	590	731	java/io/IOException
    //   598	607	731	java/io/IOException
    //   615	619	731	java/io/IOException
    //   627	631	731	java/io/IOException
    //   639	646	731	java/io/IOException
    //   662	707	731	java/io/IOException
    //   716	731	731	java/io/IOException
    //   856	949	731	java/io/IOException
    //   960	981	731	java/io/IOException
    //   989	1034	731	java/io/IOException
    //   1046	1061	731	java/io/IOException
    //   14	27	755	java/lang/Exception
    //   35	83	755	java/lang/Exception
    //   130	138	755	java/lang/Exception
    //   146	152	755	java/lang/Exception
    //   160	166	755	java/lang/Exception
    //   174	199	755	java/lang/Exception
    //   207	216	755	java/lang/Exception
    //   224	243	755	java/lang/Exception
    //   251	271	755	java/lang/Exception
    //   285	311	755	java/lang/Exception
    //   319	345	755	java/lang/Exception
    //   353	379	755	java/lang/Exception
    //   391	412	755	java/lang/Exception
    //   426	471	755	java/lang/Exception
    //   558	564	755	java/lang/Exception
    //   572	590	755	java/lang/Exception
    //   598	607	755	java/lang/Exception
    //   615	619	755	java/lang/Exception
    //   627	631	755	java/lang/Exception
    //   639	646	755	java/lang/Exception
    //   662	707	755	java/lang/Exception
    //   716	731	755	java/lang/Exception
    //   740	755	755	java/lang/Exception
    //   797	845	755	java/lang/Exception
    //   856	949	755	java/lang/Exception
    //   960	981	755	java/lang/Exception
    //   989	1034	755	java/lang/Exception
    //   1046	1061	755	java/lang/Exception
    //   14	27	776	finally
    //   35	83	776	finally
    //   130	138	776	finally
    //   146	152	776	finally
    //   160	166	776	finally
    //   174	199	776	finally
    //   207	216	776	finally
    //   224	243	776	finally
    //   251	271	776	finally
    //   285	311	776	finally
    //   319	345	776	finally
    //   353	379	776	finally
    //   391	412	776	finally
    //   426	471	776	finally
    //   475	493	776	finally
    //   497	505	776	finally
    //   509	515	776	finally
    //   519	550	776	finally
    //   558	564	776	finally
    //   572	590	776	finally
    //   598	607	776	finally
    //   615	619	776	finally
    //   627	631	776	finally
    //   639	646	776	finally
    //   662	707	776	finally
    //   716	731	776	finally
    //   740	755	776	finally
    //   760	767	776	finally
    //   771	776	776	finally
    //   797	845	776	finally
    //   856	949	776	finally
    //   960	981	776	finally
    //   989	1034	776	finally
    //   1046	1061	776	finally
    //   1076	1091	776	finally
    //   475	493	1037	java/lang/Exception
    //   497	505	1037	java/lang/Exception
    //   509	515	1037	java/lang/Exception
    //   519	550	1037	java/lang/Exception
    //   83	122	1091	finally
    //   83	122	1099	java/lang/Exception
  }
  
  /* Error */
  private String b(String paramString1, String paramString2)
    throws ArrownockException
  {
    // Byte code:
    //   0: aload_0
    //   1: ldc_w 636
    //   4: ldc -63
    //   6: invokevirtual 638	df:a	(Ljava/lang/String;Ljava/lang/String;)Ljava/lang/String;
    //   9: astore 11
    //   11: aload 11
    //   13: ldc -63
    //   15: invokevirtual 641	java/lang/String:equals	(Ljava/lang/Object;)Z
    //   18: ifeq +884 -> 902
    //   21: aload_2
    //   22: ifnonnull +291 -> 313
    //   25: aload_0
    //   26: getfield 34	df:jdField_a_of_type_AndroidContentContext	Landroid/content/Context;
    //   29: ldc -57
    //   31: invokevirtual 203	android/content/Context:getSystemService	(Ljava/lang/String;)Ljava/lang/Object;
    //   34: checkcast 205	android/telephony/TelephonyManager
    //   37: invokevirtual 644	android/telephony/TelephonyManager:getDeviceId	()Ljava/lang/String;
    //   40: astore_2
    //   41: aload_2
    //   42: ifnull +25 -> 67
    //   45: aload_2
    //   46: ldc_w 646
    //   49: invokevirtual 641	java/lang/String:equals	(Ljava/lang/Object;)Z
    //   52: ifne +15 -> 67
    //   55: ldc -63
    //   57: aload_2
    //   58: invokevirtual 450	java/lang/String:trim	()Ljava/lang/String;
    //   61: invokevirtual 641	java/lang/String:equals	(Ljava/lang/Object;)Z
    //   64: ifeq +235 -> 299
    //   67: aload_0
    //   68: getfield 34	df:jdField_a_of_type_AndroidContentContext	Landroid/content/Context;
    //   71: invokevirtual 650	android/content/Context:getContentResolver	()Landroid/content/ContentResolver;
    //   74: ldc_w 652
    //   77: invokestatic 657	android/provider/Settings$Secure:getString	(Landroid/content/ContentResolver;Ljava/lang/String;)Ljava/lang/String;
    //   80: astore_2
    //   81: aload_2
    //   82: ifnull +15 -> 97
    //   85: ldc -63
    //   87: aload_2
    //   88: invokevirtual 450	java/lang/String:trim	()Ljava/lang/String;
    //   91: invokevirtual 641	java/lang/String:equals	(Ljava/lang/Object;)Z
    //   94: ifeq +191 -> 285
    //   97: ldc_w 646
    //   100: astore_2
    //   101: getstatic 662	dx:c	Ldx;
    //   104: invokevirtual 665	dx:ordinal	()I
    //   107: invokestatic 231	java/lang/String:valueOf	(I)Ljava/lang/String;
    //   110: astore 10
    //   112: new 62	java/lang/StringBuilder
    //   115: dup
    //   116: invokespecial 98	java/lang/StringBuilder:<init>	()V
    //   119: astore 12
    //   121: aload 12
    //   123: new 62	java/lang/StringBuilder
    //   126: dup
    //   127: invokespecial 98	java/lang/StringBuilder:<init>	()V
    //   130: aload_0
    //   131: invokespecial 667	df:d	()Ljava/lang/String;
    //   134: invokevirtual 104	java/lang/StringBuilder:append	(Ljava/lang/String;)Ljava/lang/StringBuilder;
    //   137: ldc_w 669
    //   140: invokevirtual 104	java/lang/StringBuilder:append	(Ljava/lang/String;)Ljava/lang/StringBuilder;
    //   143: aload_1
    //   144: invokevirtual 104	java/lang/StringBuilder:append	(Ljava/lang/String;)Ljava/lang/StringBuilder;
    //   147: ldc_w 671
    //   150: invokevirtual 104	java/lang/StringBuilder:append	(Ljava/lang/String;)Ljava/lang/StringBuilder;
    //   153: aload_0
    //   154: getfield 34	df:jdField_a_of_type_AndroidContentContext	Landroid/content/Context;
    //   157: invokevirtual 46	android/content/Context:getPackageName	()Ljava/lang/String;
    //   160: invokevirtual 104	java/lang/StringBuilder:append	(Ljava/lang/String;)Ljava/lang/StringBuilder;
    //   163: ldc_w 673
    //   166: invokevirtual 104	java/lang/StringBuilder:append	(Ljava/lang/String;)Ljava/lang/StringBuilder;
    //   169: aload_2
    //   170: invokevirtual 104	java/lang/StringBuilder:append	(Ljava/lang/String;)Ljava/lang/StringBuilder;
    //   173: ldc_w 675
    //   176: invokevirtual 104	java/lang/StringBuilder:append	(Ljava/lang/String;)Ljava/lang/StringBuilder;
    //   179: aload 10
    //   181: invokevirtual 104	java/lang/StringBuilder:append	(Ljava/lang/String;)Ljava/lang/StringBuilder;
    //   184: invokevirtual 74	java/lang/StringBuilder:toString	()Ljava/lang/String;
    //   187: invokevirtual 104	java/lang/StringBuilder:append	(Ljava/lang/String;)Ljava/lang/StringBuilder;
    //   190: pop
    //   191: aload_0
    //   192: getfield 34	df:jdField_a_of_type_AndroidContentContext	Landroid/content/Context;
    //   195: invokestatic 677	df:a	(Landroid/content/Context;)Ljava/util/Map;
    //   198: astore_1
    //   199: aload_1
    //   200: invokeinterface 171 1 0
    //   205: invokeinterface 174 1 0
    //   210: astore_2
    //   211: aload_2
    //   212: invokeinterface 129 1 0
    //   217: ifeq +107 -> 324
    //   220: aload_2
    //   221: invokeinterface 133 1 0
    //   226: checkcast 176	java/lang/String
    //   229: astore 10
    //   231: aload 12
    //   233: new 62	java/lang/StringBuilder
    //   236: dup
    //   237: ldc -106
    //   239: invokespecial 67	java/lang/StringBuilder:<init>	(Ljava/lang/String;)V
    //   242: aload 10
    //   244: invokevirtual 104	java/lang/StringBuilder:append	(Ljava/lang/String;)Ljava/lang/StringBuilder;
    //   247: ldc -111
    //   249: invokevirtual 104	java/lang/StringBuilder:append	(Ljava/lang/String;)Ljava/lang/StringBuilder;
    //   252: aload_1
    //   253: aload 10
    //   255: invokeinterface 180 2 0
    //   260: checkcast 176	java/lang/String
    //   263: invokestatic 679	java/net/URLEncoder:encode	(Ljava/lang/String;)Ljava/lang/String;
    //   266: invokevirtual 104	java/lang/StringBuilder:append	(Ljava/lang/String;)Ljava/lang/StringBuilder;
    //   269: invokevirtual 74	java/lang/StringBuilder:toString	()Ljava/lang/String;
    //   272: invokevirtual 104	java/lang/StringBuilder:append	(Ljava/lang/String;)Ljava/lang/StringBuilder;
    //   275: pop
    //   276: goto -65 -> 211
    //   279: astore_2
    //   280: aconst_null
    //   281: astore_2
    //   282: goto -241 -> 41
    //   285: getstatic 681	dx:b	Ldx;
    //   288: invokevirtual 665	dx:ordinal	()I
    //   291: invokestatic 231	java/lang/String:valueOf	(I)Ljava/lang/String;
    //   294: astore 10
    //   296: goto -184 -> 112
    //   299: getstatic 683	dx:a	Ldx;
    //   302: invokevirtual 665	dx:ordinal	()I
    //   305: invokestatic 231	java/lang/String:valueOf	(I)Ljava/lang/String;
    //   308: astore 10
    //   310: goto -198 -> 112
    //   313: getstatic 685	dx:d	Ldx;
    //   316: invokevirtual 688	dx:name	()Ljava/lang/String;
    //   319: astore 10
    //   321: goto -209 -> 112
    //   324: aload 12
    //   326: ldc_w 690
    //   329: invokevirtual 104	java/lang/StringBuilder:append	(Ljava/lang/String;)Ljava/lang/StringBuilder;
    //   332: pop
    //   333: aload 12
    //   335: invokevirtual 74	java/lang/StringBuilder:toString	()Ljava/lang/String;
    //   338: astore_2
    //   339: iconst_0
    //   340: istore_3
    //   341: aload 11
    //   343: astore_1
    //   344: aload_1
    //   345: ldc -63
    //   347: invokevirtual 641	java/lang/String:equals	(Ljava/lang/Object;)Z
    //   350: ifeq +507 -> 857
    //   353: iload_3
    //   354: iconst_1
    //   355: iadd
    //   356: istore_3
    //   357: iload_3
    //   358: iconst_5
    //   359: if_icmpgt +498 -> 857
    //   362: aload_0
    //   363: new 62	java/lang/StringBuilder
    //   366: dup
    //   367: invokespecial 98	java/lang/StringBuilder:<init>	()V
    //   370: aload_2
    //   371: invokevirtual 104	java/lang/StringBuilder:append	(Ljava/lang/String;)Ljava/lang/StringBuilder;
    //   374: ldc_w 692
    //   377: invokevirtual 104	java/lang/StringBuilder:append	(Ljava/lang/String;)Ljava/lang/StringBuilder;
    //   380: iload_3
    //   381: invokevirtual 502	java/lang/StringBuilder:append	(I)Ljava/lang/StringBuilder;
    //   384: invokevirtual 74	java/lang/StringBuilder:toString	()Ljava/lang/String;
    //   387: invokespecial 694	df:a	(Ljava/lang/String;)Ljava/util/Map;
    //   390: astore 11
    //   392: aload 11
    //   394: ldc_w 333
    //   397: invokeinterface 180 2 0
    //   402: iconst_1
    //   403: invokestatic 338	java/lang/Boolean:valueOf	(Z)Ljava/lang/Boolean;
    //   406: invokevirtual 695	java/lang/Object:equals	(Ljava/lang/Object;)Z
    //   409: ifeq +28 -> 437
    //   412: iconst_1
    //   413: istore 4
    //   415: iload 4
    //   417: ifeq +26 -> 443
    //   420: aload 11
    //   422: ldc_w 347
    //   425: invokeinterface 180 2 0
    //   430: invokevirtual 696	java/lang/Object:toString	()Ljava/lang/String;
    //   433: astore_1
    //   434: goto -90 -> 344
    //   437: iconst_0
    //   438: istore 4
    //   440: goto -25 -> 415
    //   443: aload 11
    //   445: ldc_w 340
    //   448: invokeinterface 180 2 0
    //   453: checkcast 342	java/lang/Integer
    //   456: invokevirtual 699	java/lang/Integer:intValue	()I
    //   459: istore 6
    //   461: iload 6
    //   463: sipush 503
    //   466: if_icmpne +181 -> 647
    //   469: aload 11
    //   471: ldc_w 357
    //   474: invokeinterface 180 2 0
    //   479: invokevirtual 696	java/lang/Object:toString	()Ljava/lang/String;
    //   482: astore 10
    //   484: aload 11
    //   486: ldc_w 361
    //   489: invokeinterface 180 2 0
    //   494: checkcast 342	java/lang/Integer
    //   497: invokevirtual 699	java/lang/Integer:intValue	()I
    //   500: istore 5
    //   502: iload 5
    //   504: istore 4
    //   506: iload 5
    //   508: ifgt +6 -> 514
    //   511: iconst_5
    //   512: istore 4
    //   514: iload 4
    //   516: istore 5
    //   518: iload 4
    //   520: sipush 1800
    //   523: if_icmple +8 -> 531
    //   526: sipush 1800
    //   529: istore 5
    //   531: new 62	java/lang/StringBuilder
    //   534: dup
    //   535: ldc_w 701
    //   538: invokespecial 67	java/lang/StringBuilder:<init>	(Ljava/lang/String;)V
    //   541: iload 6
    //   543: invokevirtual 502	java/lang/StringBuilder:append	(I)Ljava/lang/StringBuilder;
    //   546: ldc_w 703
    //   549: invokevirtual 104	java/lang/StringBuilder:append	(Ljava/lang/String;)Ljava/lang/StringBuilder;
    //   552: aload 10
    //   554: invokevirtual 104	java/lang/StringBuilder:append	(Ljava/lang/String;)Ljava/lang/StringBuilder;
    //   557: ldc_w 705
    //   560: invokevirtual 104	java/lang/StringBuilder:append	(Ljava/lang/String;)Ljava/lang/StringBuilder;
    //   563: iload 5
    //   565: invokevirtual 502	java/lang/StringBuilder:append	(I)Ljava/lang/StringBuilder;
    //   568: ldc_w 707
    //   571: invokevirtual 104	java/lang/StringBuilder:append	(Ljava/lang/String;)Ljava/lang/StringBuilder;
    //   574: invokevirtual 74	java/lang/StringBuilder:toString	()Ljava/lang/String;
    //   577: astore 10
    //   579: invokestatic 256	bk:a	()Lbk;
    //   582: getstatic 22	df:jdField_a_of_type_JavaLangString	Ljava/lang/String;
    //   585: aload 10
    //   587: invokevirtual 709	bk:c	(Ljava/lang/String;Ljava/lang/String;)V
    //   590: iload 5
    //   592: sipush 1000
    //   595: imul
    //   596: i2l
    //   597: lstore 7
    //   599: lload 7
    //   601: invokestatic 715	java/lang/Thread:sleep	(J)V
    //   604: aload_0
    //   605: getfield 34	df:jdField_a_of_type_AndroidContentContext	Landroid/content/Context;
    //   608: invokestatic 267	com/arrownock/push/AnPush:getInstance	(Landroid/content/Context;)Lcom/arrownock/push/AnPush;
    //   611: invokevirtual 371	com/arrownock/push/AnPush:a	()Z
    //   614: istore 9
    //   616: iload 9
    //   618: ifne +13 -> 631
    //   621: aconst_null
    //   622: areturn
    //   623: astore 11
    //   625: iconst_m1
    //   626: istore 5
    //   628: goto -126 -> 502
    //   631: goto -287 -> 344
    //   634: astore_1
    //   635: new 79	com/arrownock/exception/ArrownockException
    //   638: dup
    //   639: aload_1
    //   640: sipush 2003
    //   643: invokespecial 718	com/arrownock/exception/ArrownockException:<init>	(Ljava/lang/Exception;I)V
    //   646: athrow
    //   647: iload 6
    //   649: sipush 400
    //   652: if_icmpne +39 -> 691
    //   655: aload 11
    //   657: ldc_w 357
    //   660: invokeinterface 180 2 0
    //   665: invokevirtual 696	java/lang/Object:toString	()Ljava/lang/String;
    //   668: astore_1
    //   669: invokestatic 256	bk:a	()Lbk;
    //   672: getstatic 22	df:jdField_a_of_type_JavaLangString	Ljava/lang/String;
    //   675: aload_1
    //   676: invokevirtual 720	bk:d	(Ljava/lang/String;Ljava/lang/String;)V
    //   679: new 79	com/arrownock/exception/ArrownockException
    //   682: dup
    //   683: aload_1
    //   684: sipush 2003
    //   687: invokespecial 575	com/arrownock/exception/ArrownockException:<init>	(Ljava/lang/String;I)V
    //   690: athrow
    //   691: iload 6
    //   693: iconst_m1
    //   694: if_icmpne +59 -> 753
    //   697: aload 11
    //   699: ldc_w 359
    //   702: invokeinterface 180 2 0
    //   707: checkcast 197	java/lang/Exception
    //   710: astore_1
    //   711: invokestatic 256	bk:a	()Lbk;
    //   714: getstatic 22	df:jdField_a_of_type_JavaLangString	Ljava/lang/String;
    //   717: new 62	java/lang/StringBuilder
    //   720: dup
    //   721: ldc_w 722
    //   724: invokespecial 67	java/lang/StringBuilder:<init>	(Ljava/lang/String;)V
    //   727: aload_1
    //   728: invokevirtual 580	java/lang/Exception:getMessage	()Ljava/lang/String;
    //   731: invokevirtual 104	java/lang/StringBuilder:append	(Ljava/lang/String;)Ljava/lang/StringBuilder;
    //   734: invokevirtual 74	java/lang/StringBuilder:toString	()Ljava/lang/String;
    //   737: aload_1
    //   738: invokevirtual 261	bk:a	(Ljava/lang/String;Ljava/lang/String;Ljava/lang/Throwable;)V
    //   741: new 79	com/arrownock/exception/ArrownockException
    //   744: dup
    //   745: aload_1
    //   746: sipush 2003
    //   749: invokespecial 718	com/arrownock/exception/ArrownockException:<init>	(Ljava/lang/Exception;I)V
    //   752: athrow
    //   753: aload 11
    //   755: ldc_w 367
    //   758: invokeinterface 180 2 0
    //   763: invokevirtual 696	java/lang/Object:toString	()Ljava/lang/String;
    //   766: astore 10
    //   768: new 62	java/lang/StringBuilder
    //   771: dup
    //   772: ldc_w 701
    //   775: invokespecial 67	java/lang/StringBuilder:<init>	(Ljava/lang/String;)V
    //   778: iload 6
    //   780: invokevirtual 502	java/lang/StringBuilder:append	(I)Ljava/lang/StringBuilder;
    //   783: ldc_w 724
    //   786: invokevirtual 104	java/lang/StringBuilder:append	(Ljava/lang/String;)Ljava/lang/StringBuilder;
    //   789: aload 10
    //   791: invokevirtual 104	java/lang/StringBuilder:append	(Ljava/lang/String;)Ljava/lang/StringBuilder;
    //   794: ldc_w 726
    //   797: invokevirtual 104	java/lang/StringBuilder:append	(Ljava/lang/String;)Ljava/lang/StringBuilder;
    //   800: invokevirtual 74	java/lang/StringBuilder:toString	()Ljava/lang/String;
    //   803: astore 10
    //   805: invokestatic 256	bk:a	()Lbk;
    //   808: getstatic 22	df:jdField_a_of_type_JavaLangString	Ljava/lang/String;
    //   811: aload 10
    //   813: invokevirtual 709	bk:c	(Ljava/lang/String;Ljava/lang/String;)V
    //   816: ldc2_w 727
    //   819: invokestatic 715	java/lang/Thread:sleep	(J)V
    //   822: aload_0
    //   823: getfield 34	df:jdField_a_of_type_AndroidContentContext	Landroid/content/Context;
    //   826: invokestatic 267	com/arrownock/push/AnPush:getInstance	(Landroid/content/Context;)Lcom/arrownock/push/AnPush;
    //   829: invokevirtual 371	com/arrownock/push/AnPush:a	()Z
    //   832: istore 9
    //   834: iload 9
    //   836: ifne +5 -> 841
    //   839: aconst_null
    //   840: areturn
    //   841: goto -497 -> 344
    //   844: astore_1
    //   845: new 79	com/arrownock/exception/ArrownockException
    //   848: dup
    //   849: aload_1
    //   850: sipush 2003
    //   853: invokespecial 718	com/arrownock/exception/ArrownockException:<init>	(Ljava/lang/Exception;I)V
    //   856: athrow
    //   857: aload_1
    //   858: ldc -63
    //   860: invokevirtual 641	java/lang/String:equals	(Ljava/lang/Object;)Z
    //   863: ifne +13 -> 876
    //   866: aload_0
    //   867: ldc_w 636
    //   870: aload_1
    //   871: invokevirtual 426	df:a	(Ljava/lang/String;Ljava/lang/String;)V
    //   874: aload_1
    //   875: areturn
    //   876: invokestatic 256	bk:a	()Lbk;
    //   879: getstatic 22	df:jdField_a_of_type_JavaLangString	Ljava/lang/String;
    //   882: ldc_w 730
    //   885: invokevirtual 720	bk:d	(Ljava/lang/String;Ljava/lang/String;)V
    //   888: new 79	com/arrownock/exception/ArrownockException
    //   891: dup
    //   892: ldc_w 730
    //   895: sipush 2003
    //   898: invokespecial 575	com/arrownock/exception/ArrownockException:<init>	(Ljava/lang/String;I)V
    //   901: athrow
    //   902: aload 11
    //   904: areturn
    // Local variable table:
    //   start	length	slot	name	signature
    //   0	905	0	this	df
    //   0	905	1	paramString1	String
    //   0	905	2	paramString2	String
    //   340	41	3	i	int
    //   413	111	4	j	int
    //   500	127	5	k	int
    //   459	320	6	m	int
    //   597	3	7	l	long
    //   614	221	9	bool	boolean
    //   110	702	10	str	String
    //   9	476	11	localObject	Object
    //   623	280	11	localException	Exception
    //   119	215	12	localStringBuilder	StringBuilder
    // Exception table:
    //   from	to	target	type
    //   25	41	279	java/lang/Exception
    //   484	502	623	java/lang/Exception
    //   599	616	634	java/lang/InterruptedException
    //   816	834	844	java/lang/InterruptedException
  }
  
  /* Error */
  private Map<String, Object> b(String paramString)
  {
    // Byte code:
    //   0: new 207	java/util/HashMap
    //   3: dup
    //   4: invokespecial 208	java/util/HashMap:<init>	()V
    //   7: astore 11
    //   9: aconst_null
    //   10: astore 10
    //   12: aconst_null
    //   13: astore 9
    //   15: aload 9
    //   17: astore 8
    //   19: aload 10
    //   21: astore 7
    //   23: aload_0
    //   24: getfield 34	df:jdField_a_of_type_AndroidContentContext	Landroid/content/Context;
    //   27: invokestatic 267	com/arrownock/push/AnPush:getInstance	(Landroid/content/Context;)Lcom/arrownock/push/AnPush;
    //   30: invokevirtual 270	com/arrownock/push/AnPush:isSecureConnection	()Z
    //   33: ifeq +343 -> 376
    //   36: aload 9
    //   38: astore 8
    //   40: aload 10
    //   42: astore 7
    //   44: new 272	java/net/URL
    //   47: dup
    //   48: new 62	java/lang/StringBuilder
    //   51: dup
    //   52: ldc_w 274
    //   55: invokespecial 67	java/lang/StringBuilder:<init>	(Ljava/lang/String;)V
    //   58: aload_1
    //   59: invokevirtual 104	java/lang/StringBuilder:append	(Ljava/lang/String;)Ljava/lang/StringBuilder;
    //   62: invokevirtual 74	java/lang/StringBuilder:toString	()Ljava/lang/String;
    //   65: invokespecial 275	java/net/URL:<init>	(Ljava/lang/String;)V
    //   68: invokevirtual 279	java/net/URL:openConnection	()Ljava/net/URLConnection;
    //   71: checkcast 281	javax/net/ssl/HttpsURLConnection
    //   74: astore_1
    //   75: aload_1
    //   76: checkcast 281	javax/net/ssl/HttpsURLConnection
    //   79: getstatic 29	df:jdField_a_of_type_JavaxNetSslHostnameVerifier	Ljavax/net/ssl/HostnameVerifier;
    //   82: invokevirtual 285	javax/net/ssl/HttpsURLConnection:setHostnameVerifier	(Ljavax/net/ssl/HostnameVerifier;)V
    //   85: aload_1
    //   86: checkcast 281	javax/net/ssl/HttpsURLConnection
    //   89: aload_0
    //   90: invokespecial 288	df:f	()Ljava/lang/String;
    //   93: aload_0
    //   94: invokespecial 291	df:g	()Ljava/lang/String;
    //   97: aload_0
    //   98: invokespecial 294	df:h	()Ljava/lang/String;
    //   101: ldc -63
    //   103: ldc_w 296
    //   106: invokestatic 301	at:a	(Ljava/lang/String;Ljava/lang/String;Ljava/lang/String;Ljava/lang/String;Ljava/lang/String;)Ljavax/net/ssl/SSLSocketFactory;
    //   109: invokevirtual 305	javax/net/ssl/HttpsURLConnection:setSSLSocketFactory	(Ljavax/net/ssl/SSLSocketFactory;)V
    //   112: aload_1
    //   113: astore 8
    //   115: aload_1
    //   116: astore 7
    //   118: aload_1
    //   119: invokevirtual 310	java/net/HttpURLConnection:connect	()V
    //   122: aload_1
    //   123: astore 8
    //   125: aload_1
    //   126: astore 7
    //   128: aload_1
    //   129: invokevirtual 313	java/net/HttpURLConnection:getResponseCode	()I
    //   132: istore_2
    //   133: iload_2
    //   134: sipush 200
    //   137: if_icmpne +281 -> 418
    //   140: aload_1
    //   141: astore 8
    //   143: aload_1
    //   144: astore 7
    //   146: new 315	org/json/JSONObject
    //   149: dup
    //   150: new 317	java/io/BufferedInputStream
    //   153: dup
    //   154: aload_1
    //   155: invokevirtual 321	java/net/HttpURLConnection:getInputStream	()Ljava/io/InputStream;
    //   158: invokespecial 322	java/io/BufferedInputStream:<init>	(Ljava/io/InputStream;)V
    //   161: invokestatic 324	df:a	(Ljava/io/InputStream;)Ljava/lang/String;
    //   164: invokespecial 325	org/json/JSONObject:<init>	(Ljava/lang/String;)V
    //   167: astore 9
    //   169: aload_1
    //   170: astore 8
    //   172: aload_1
    //   173: astore 7
    //   175: aload 9
    //   177: ldc_w 732
    //   180: invokevirtual 331	org/json/JSONObject:getString	(Ljava/lang/String;)Ljava/lang/String;
    //   183: astore 10
    //   185: aload_1
    //   186: astore 8
    //   188: aload_1
    //   189: astore 7
    //   191: aload 9
    //   193: ldc_w 734
    //   196: sipush 1883
    //   199: invokevirtual 365	org/json/JSONObject:optInt	(Ljava/lang/String;I)I
    //   202: istore_2
    //   203: aload_1
    //   204: astore 8
    //   206: aload_1
    //   207: astore 7
    //   209: aload 9
    //   211: ldc_w 736
    //   214: sipush 8883
    //   217: invokevirtual 365	org/json/JSONObject:optInt	(Ljava/lang/String;I)I
    //   220: istore_3
    //   221: aload_1
    //   222: astore 8
    //   224: aload_1
    //   225: astore 7
    //   227: aload 9
    //   229: ldc_w 738
    //   232: lconst_0
    //   233: invokevirtual 742	org/json/JSONObject:optLong	(Ljava/lang/String;J)J
    //   236: lstore 4
    //   238: aload_1
    //   239: astore 8
    //   241: aload_1
    //   242: astore 7
    //   244: aload 11
    //   246: ldc_w 333
    //   249: iconst_1
    //   250: invokestatic 338	java/lang/Boolean:valueOf	(Z)Ljava/lang/Boolean;
    //   253: invokeinterface 167 3 0
    //   258: pop
    //   259: aload_1
    //   260: astore 8
    //   262: aload_1
    //   263: astore 7
    //   265: aload 11
    //   267: ldc_w 340
    //   270: sipush 200
    //   273: invokestatic 345	java/lang/Integer:valueOf	(I)Ljava/lang/Integer;
    //   276: invokeinterface 167 3 0
    //   281: pop
    //   282: aload_1
    //   283: astore 8
    //   285: aload_1
    //   286: astore 7
    //   288: aload 11
    //   290: ldc_w 732
    //   293: aload 10
    //   295: invokeinterface 167 3 0
    //   300: pop
    //   301: aload_1
    //   302: astore 8
    //   304: aload_1
    //   305: astore 7
    //   307: aload 11
    //   309: ldc_w 734
    //   312: iload_2
    //   313: invokestatic 345	java/lang/Integer:valueOf	(I)Ljava/lang/Integer;
    //   316: invokeinterface 167 3 0
    //   321: pop
    //   322: aload_1
    //   323: astore 8
    //   325: aload_1
    //   326: astore 7
    //   328: aload 11
    //   330: ldc_w 736
    //   333: iload_3
    //   334: invokestatic 345	java/lang/Integer:valueOf	(I)Ljava/lang/Integer;
    //   337: invokeinterface 167 3 0
    //   342: pop
    //   343: aload_1
    //   344: astore 8
    //   346: aload_1
    //   347: astore 7
    //   349: aload 11
    //   351: ldc_w 738
    //   354: lload 4
    //   356: invokestatic 747	java/lang/Long:valueOf	(J)Ljava/lang/Long;
    //   359: invokeinterface 167 3 0
    //   364: pop
    //   365: aload_1
    //   366: ifnull +7 -> 373
    //   369: aload_1
    //   370: invokevirtual 350	java/net/HttpURLConnection:disconnect	()V
    //   373: aload 11
    //   375: areturn
    //   376: aload 9
    //   378: astore 8
    //   380: aload 10
    //   382: astore 7
    //   384: new 272	java/net/URL
    //   387: dup
    //   388: new 62	java/lang/StringBuilder
    //   391: dup
    //   392: ldc_w 352
    //   395: invokespecial 67	java/lang/StringBuilder:<init>	(Ljava/lang/String;)V
    //   398: aload_1
    //   399: invokevirtual 104	java/lang/StringBuilder:append	(Ljava/lang/String;)Ljava/lang/StringBuilder;
    //   402: invokevirtual 74	java/lang/StringBuilder:toString	()Ljava/lang/String;
    //   405: invokespecial 275	java/net/URL:<init>	(Ljava/lang/String;)V
    //   408: invokevirtual 279	java/net/URL:openConnection	()Ljava/net/URLConnection;
    //   411: checkcast 307	java/net/HttpURLConnection
    //   414: astore_1
    //   415: goto -303 -> 112
    //   418: aload_1
    //   419: astore 8
    //   421: aload_1
    //   422: astore 7
    //   424: new 317	java/io/BufferedInputStream
    //   427: dup
    //   428: aload_1
    //   429: invokevirtual 355	java/net/HttpURLConnection:getErrorStream	()Ljava/io/InputStream;
    //   432: invokespecial 322	java/io/BufferedInputStream:<init>	(Ljava/io/InputStream;)V
    //   435: invokestatic 324	df:a	(Ljava/io/InputStream;)Ljava/lang/String;
    //   438: astore 9
    //   440: iload_2
    //   441: sipush 400
    //   444: if_icmpne +160 -> 604
    //   447: aload_1
    //   448: astore 8
    //   450: aload_1
    //   451: astore 7
    //   453: new 315	org/json/JSONObject
    //   456: dup
    //   457: aload 9
    //   459: invokespecial 325	org/json/JSONObject:<init>	(Ljava/lang/String;)V
    //   462: ldc_w 357
    //   465: invokevirtual 331	org/json/JSONObject:getString	(Ljava/lang/String;)Ljava/lang/String;
    //   468: astore 9
    //   470: aload_1
    //   471: astore 8
    //   473: aload_1
    //   474: astore 7
    //   476: aload 11
    //   478: ldc_w 333
    //   481: iconst_0
    //   482: invokestatic 338	java/lang/Boolean:valueOf	(Z)Ljava/lang/Boolean;
    //   485: invokeinterface 167 3 0
    //   490: pop
    //   491: aload_1
    //   492: astore 8
    //   494: aload_1
    //   495: astore 7
    //   497: aload 11
    //   499: ldc_w 340
    //   502: sipush 400
    //   505: invokestatic 345	java/lang/Integer:valueOf	(I)Ljava/lang/Integer;
    //   508: invokeinterface 167 3 0
    //   513: pop
    //   514: aload_1
    //   515: astore 8
    //   517: aload_1
    //   518: astore 7
    //   520: aload 11
    //   522: ldc_w 357
    //   525: aload 9
    //   527: invokeinterface 167 3 0
    //   532: pop
    //   533: goto -168 -> 365
    //   536: astore_1
    //   537: aload 8
    //   539: astore 7
    //   541: aload 11
    //   543: ldc_w 333
    //   546: iconst_0
    //   547: invokestatic 338	java/lang/Boolean:valueOf	(Z)Ljava/lang/Boolean;
    //   550: invokeinterface 167 3 0
    //   555: pop
    //   556: aload 8
    //   558: astore 7
    //   560: aload 11
    //   562: ldc_w 340
    //   565: iconst_m1
    //   566: invokestatic 345	java/lang/Integer:valueOf	(I)Ljava/lang/Integer;
    //   569: invokeinterface 167 3 0
    //   574: pop
    //   575: aload 8
    //   577: astore 7
    //   579: aload 11
    //   581: ldc_w 359
    //   584: aload_1
    //   585: invokeinterface 167 3 0
    //   590: pop
    //   591: aload 8
    //   593: ifnull -220 -> 373
    //   596: aload 8
    //   598: invokevirtual 350	java/net/HttpURLConnection:disconnect	()V
    //   601: aload 11
    //   603: areturn
    //   604: iload_2
    //   605: sipush 403
    //   608: if_icmpne +161 -> 769
    //   611: aload_1
    //   612: astore 8
    //   614: aload_1
    //   615: astore 7
    //   617: new 315	org/json/JSONObject
    //   620: dup
    //   621: aload 9
    //   623: invokespecial 325	org/json/JSONObject:<init>	(Ljava/lang/String;)V
    //   626: astore 9
    //   628: aload_1
    //   629: astore 8
    //   631: aload_1
    //   632: astore 7
    //   634: aload 9
    //   636: ldc_w 357
    //   639: invokevirtual 331	org/json/JSONObject:getString	(Ljava/lang/String;)Ljava/lang/String;
    //   642: astore 10
    //   644: aload_1
    //   645: astore 8
    //   647: aload_1
    //   648: astore 7
    //   650: aload 9
    //   652: ldc_w 749
    //   655: iconst_0
    //   656: invokevirtual 753	org/json/JSONObject:optBoolean	(Ljava/lang/String;Z)Z
    //   659: istore 6
    //   661: aload_1
    //   662: astore 8
    //   664: aload_1
    //   665: astore 7
    //   667: aload 11
    //   669: ldc_w 333
    //   672: iconst_0
    //   673: invokestatic 338	java/lang/Boolean:valueOf	(Z)Ljava/lang/Boolean;
    //   676: invokeinterface 167 3 0
    //   681: pop
    //   682: aload_1
    //   683: astore 8
    //   685: aload_1
    //   686: astore 7
    //   688: aload 11
    //   690: ldc_w 340
    //   693: sipush 403
    //   696: invokestatic 345	java/lang/Integer:valueOf	(I)Ljava/lang/Integer;
    //   699: invokeinterface 167 3 0
    //   704: pop
    //   705: aload_1
    //   706: astore 8
    //   708: aload_1
    //   709: astore 7
    //   711: aload 11
    //   713: ldc_w 357
    //   716: aload 10
    //   718: invokeinterface 167 3 0
    //   723: pop
    //   724: aload_1
    //   725: astore 8
    //   727: aload_1
    //   728: astore 7
    //   730: aload 11
    //   732: ldc_w 749
    //   735: iload 6
    //   737: invokestatic 338	java/lang/Boolean:valueOf	(Z)Ljava/lang/Boolean;
    //   740: invokeinterface 167 3 0
    //   745: pop
    //   746: goto -381 -> 365
    //   749: astore 8
    //   751: aload 7
    //   753: astore_1
    //   754: aload 8
    //   756: astore 7
    //   758: aload_1
    //   759: ifnull +7 -> 766
    //   762: aload_1
    //   763: invokevirtual 350	java/net/HttpURLConnection:disconnect	()V
    //   766: aload 7
    //   768: athrow
    //   769: iload_2
    //   770: sipush 503
    //   773: if_icmpne +139 -> 912
    //   776: aload_1
    //   777: astore 8
    //   779: aload_1
    //   780: astore 7
    //   782: new 315	org/json/JSONObject
    //   785: dup
    //   786: aload 9
    //   788: invokespecial 325	org/json/JSONObject:<init>	(Ljava/lang/String;)V
    //   791: astore 9
    //   793: aload_1
    //   794: astore 8
    //   796: aload_1
    //   797: astore 7
    //   799: aload 9
    //   801: ldc_w 357
    //   804: invokevirtual 331	org/json/JSONObject:getString	(Ljava/lang/String;)Ljava/lang/String;
    //   807: astore 10
    //   809: aload_1
    //   810: astore 8
    //   812: aload_1
    //   813: astore 7
    //   815: aload 9
    //   817: ldc_w 361
    //   820: iconst_m1
    //   821: invokevirtual 365	org/json/JSONObject:optInt	(Ljava/lang/String;I)I
    //   824: istore_2
    //   825: aload_1
    //   826: astore 8
    //   828: aload_1
    //   829: astore 7
    //   831: aload 11
    //   833: ldc_w 333
    //   836: iconst_0
    //   837: invokestatic 338	java/lang/Boolean:valueOf	(Z)Ljava/lang/Boolean;
    //   840: invokeinterface 167 3 0
    //   845: pop
    //   846: aload_1
    //   847: astore 8
    //   849: aload_1
    //   850: astore 7
    //   852: aload 11
    //   854: ldc_w 340
    //   857: sipush 503
    //   860: invokestatic 345	java/lang/Integer:valueOf	(I)Ljava/lang/Integer;
    //   863: invokeinterface 167 3 0
    //   868: pop
    //   869: aload_1
    //   870: astore 8
    //   872: aload_1
    //   873: astore 7
    //   875: aload 11
    //   877: ldc_w 357
    //   880: aload 10
    //   882: invokeinterface 167 3 0
    //   887: pop
    //   888: aload_1
    //   889: astore 8
    //   891: aload_1
    //   892: astore 7
    //   894: aload 11
    //   896: ldc_w 361
    //   899: iload_2
    //   900: invokestatic 345	java/lang/Integer:valueOf	(I)Ljava/lang/Integer;
    //   903: invokeinterface 167 3 0
    //   908: pop
    //   909: goto -544 -> 365
    //   912: aload_1
    //   913: astore 8
    //   915: aload_1
    //   916: astore 7
    //   918: aload 11
    //   920: ldc_w 333
    //   923: iconst_0
    //   924: invokestatic 338	java/lang/Boolean:valueOf	(Z)Ljava/lang/Boolean;
    //   927: invokeinterface 167 3 0
    //   932: pop
    //   933: aload_1
    //   934: astore 8
    //   936: aload_1
    //   937: astore 7
    //   939: aload 11
    //   941: ldc_w 340
    //   944: iload_2
    //   945: invokestatic 345	java/lang/Integer:valueOf	(I)Ljava/lang/Integer;
    //   948: invokeinterface 167 3 0
    //   953: pop
    //   954: aload_1
    //   955: astore 8
    //   957: aload_1
    //   958: astore 7
    //   960: aload 11
    //   962: ldc_w 367
    //   965: aload 9
    //   967: invokeinterface 167 3 0
    //   972: pop
    //   973: goto -608 -> 365
    //   976: astore 7
    //   978: goto -220 -> 758
    //   981: astore 7
    //   983: aload_1
    //   984: astore 8
    //   986: aload 7
    //   988: astore_1
    //   989: goto -452 -> 537
    // Local variable table:
    //   start	length	slot	name	signature
    //   0	992	0	this	df
    //   0	992	1	paramString	String
    //   132	813	2	i	int
    //   220	114	3	j	int
    //   236	119	4	l	long
    //   659	77	6	bool	boolean
    //   21	938	7	localObject1	Object
    //   976	1	7	localObject2	Object
    //   981	6	7	localException	Exception
    //   17	709	8	localObject3	Object
    //   749	6	8	localObject4	Object
    //   777	208	8	str1	String
    //   13	953	9	localObject5	Object
    //   10	871	10	str2	String
    //   7	954	11	localHashMap	HashMap
    // Exception table:
    //   from	to	target	type
    //   23	36	536	java/lang/Exception
    //   44	75	536	java/lang/Exception
    //   118	122	536	java/lang/Exception
    //   128	133	536	java/lang/Exception
    //   146	169	536	java/lang/Exception
    //   175	185	536	java/lang/Exception
    //   191	203	536	java/lang/Exception
    //   209	221	536	java/lang/Exception
    //   227	238	536	java/lang/Exception
    //   244	259	536	java/lang/Exception
    //   265	282	536	java/lang/Exception
    //   288	301	536	java/lang/Exception
    //   307	322	536	java/lang/Exception
    //   328	343	536	java/lang/Exception
    //   349	365	536	java/lang/Exception
    //   384	415	536	java/lang/Exception
    //   424	440	536	java/lang/Exception
    //   453	470	536	java/lang/Exception
    //   476	491	536	java/lang/Exception
    //   497	514	536	java/lang/Exception
    //   520	533	536	java/lang/Exception
    //   617	628	536	java/lang/Exception
    //   634	644	536	java/lang/Exception
    //   650	661	536	java/lang/Exception
    //   667	682	536	java/lang/Exception
    //   688	705	536	java/lang/Exception
    //   711	724	536	java/lang/Exception
    //   730	746	536	java/lang/Exception
    //   782	793	536	java/lang/Exception
    //   799	809	536	java/lang/Exception
    //   815	825	536	java/lang/Exception
    //   831	846	536	java/lang/Exception
    //   852	869	536	java/lang/Exception
    //   875	888	536	java/lang/Exception
    //   894	909	536	java/lang/Exception
    //   918	933	536	java/lang/Exception
    //   939	954	536	java/lang/Exception
    //   960	973	536	java/lang/Exception
    //   23	36	749	finally
    //   44	75	749	finally
    //   118	122	749	finally
    //   128	133	749	finally
    //   146	169	749	finally
    //   175	185	749	finally
    //   191	203	749	finally
    //   209	221	749	finally
    //   227	238	749	finally
    //   244	259	749	finally
    //   265	282	749	finally
    //   288	301	749	finally
    //   307	322	749	finally
    //   328	343	749	finally
    //   349	365	749	finally
    //   384	415	749	finally
    //   424	440	749	finally
    //   453	470	749	finally
    //   476	491	749	finally
    //   497	514	749	finally
    //   520	533	749	finally
    //   541	556	749	finally
    //   560	575	749	finally
    //   579	591	749	finally
    //   617	628	749	finally
    //   634	644	749	finally
    //   650	661	749	finally
    //   667	682	749	finally
    //   688	705	749	finally
    //   711	724	749	finally
    //   730	746	749	finally
    //   782	793	749	finally
    //   799	809	749	finally
    //   815	825	749	finally
    //   831	846	749	finally
    //   852	869	749	finally
    //   875	888	749	finally
    //   894	909	749	finally
    //   918	933	749	finally
    //   939	954	749	finally
    //   960	973	749	finally
    //   75	112	976	finally
    //   75	112	981	java/lang/Exception
  }
  
  private String c()
  {
    String str2 = a("apiHost", "");
    String str1 = str2;
    if ("".equals(str2)) {
      str1 = "10.1.215.152:3000";
    }
    return str1;
  }
  
  private String d()
  {
    String str2 = a("dsHost", "");
    String str1 = str2;
    if ("".equals(str2)) {
      str1 = "10.1.215.152:9999";
    }
    return str1;
  }
  
  private String e()
  {
    String str2 = a("apiSecret", "");
    String str1 = str2;
    if ("".equals(str2)) {
      str1 = "lLgweiDSIdEosPeFW3jfeOQOwe83wfwef42ytHSOI9wwiwelQVWE";
    }
    return str1;
  }
  
  private String f()
  {
    return a("serverCert", "LS0tLS1CRUdJTiBDRVJUSUZJQ0FURS0tLS0tCk1JSUVWRENDQXp5Z0F3SUJBZ0lCQVRBTkJna3Foa2lHOXcwQkFRVUZBREJpTVFzd0NRWURWUVFHRXdKRFRqRVEKTUE0R0ExVUVDQXdIUW1WcGFtbHVaekVRTUE0R0ExVUVCd3dIUW1WcGFtbHVaekVTTUJBR0ExVUVDd3dKUVhKeQpiM2R1YjJOck1Sc3dHUVlEVlFRRERCSkJjbkp2ZDI1dlkyc2dRMjh1TEV4MFpDNHdIaGNOTVRZd05qQTFNVFUxCk5qTXdXaGNOTXpZd05UTXhNVFUxTmpNd1dqQmlNUXN3Q1FZRFZRUUdFd0pEVGpFUU1BNEdBMVVFQ0F3SFFtVnAKYW1sdVp6RVFNQTRHQTFVRUJ3d0hRbVZwYW1sdVp6RVNNQkFHQTFVRUN3d0pRWEp5YjNkdWIyTnJNUnN3R1FZRApWUVFEREJKQmNuSnZkMjV2WTJzZ1EyOHVMRXgwWkM0d2dnRWlNQTBHQ1NxR1NJYjNEUUVCQVFVQUE0SUJEd0F3CmdnRUtBb0lCQVFEVUhxemtra3VaeElQbFI4ZDdnZU4wQzlJQkpLZkJWY0ZNM1FsVzhCbC9sZW9BZHMreDBpbXUKb3VCY2p6czN4aWFUR1Z1dklKODRvbUxNbHMyeUlGNWt5NE5RM0R1citIU280eE1pMVNBRXpFcXJhZ2hXeGRFSQovZlVtUnFrWHFLUUhtQmVUVUdqaXZDVExEOUp4a0trR2lFVWFSNmhGdjJseWZuM3U4emFYeGRFOTRWMkg2VkhPCmg5Y1N3d2xIZHhjcXZ5Z2dTUVE1cERkS2UrNEcyckZZSWlqeVJ1elNrWkhjNndDZ1NwVVRpMUE3ckZGZkVPdUsKU1ZDZ3ZnSmtkbFZzUzlOWVp4WGx1RmJNd3Jtd3pqdUM0WEliamlQZExmd21ya25PQ2Y3VE9lYkNDbmo3WHVoZApiNnIxdWdqUC80Wmk2bTM2anEyeVFKZEVRcWVmMXpXZEFnTUJBQUdqZ2dFVE1JSUJEekFKQmdOVkhSTUVBakFBCk1Bc0dBMVVkRHdRRUF3SUY0REFSQmdsZ2hrZ0JodmhDQVFFRUJBTUNCa0F3SFFZRFZSME9CQllFRkVmTnAyZGIKS2JEbG5NTk5uWlZlckJHU09pVUNNSUdVQmdOVkhTTUVnWXd3Z1ltQUZOQ0JPcEw4TlcvYkhYc2tUc1FVdit0YworR3dYb1dha1pEQmlNUXN3Q1FZRFZRUUdFd0pEVGpFUU1BNEdBMVVFQ0F3SFFtVnBhbWx1WnpFUU1BNEdBMVVFCkJ3d0hRbVZwYW1sdVp6RVNNQkFHQTFVRUN3d0pRWEp5YjNkdWIyTnJNUnN3R1FZRFZRUUREQkpCY25KdmQyNXYKWTJzZ1EyOHVMRXgwWkM2Q0NRRFQzVTJldUp4dENqQXNCZ05WSFJFRUpUQWpnZ29xTGpFeU16QTJMbU51Z2c4cQpMbUZ5Y205M2JtOWpheTVqYjIySEJBb0M2MU13RFFZSktvWklodmNOQVFFRkJRQURnZ0VCQUVPaWFRekFleDZXCnUzVkIzTkw5Q2JpR2VqZVlxNStVVXpiMzFMaGlMSDdyeXU1M0F4dmtSS1VQRjNJdTRZcmhObk44MWxYL0w3dFoKLzJvQXZMV0V3Y0NVdVNnNENHYURnYlZycjVPd0ozK1pNNnhKb1NJQTZ3RzExQkNWa1l0NTJ0cnZuZ0VJU2FhMwppd3dZWmJPbldhL0ZVZHA3N093K1VCbExiZXRZSndqSXk2UlZrMGxJOHEyb24zMEd6VWZOSGF6blVpVU1sdWV4CkdjRGU5Q2srYTJqL1BGVjlkRWIyYkRvSW52NkdhSXd1V29KR094ZnJRUVRaUFdVTDZrM0JVMHdDVThKWTdQaXQKSGlIZ1dNLzVWRzhUdGU4Mm1XcjV4Rmk3NEkyUFZ3SDdUd3RUbEFOaGN0a0Z6VUROd0Iyem1nVWZxZklGWCtHMApETUQwT3h2bldicz0KLS0tLS1FTkQgQ0VSVElGSUNBVEUtLS0tLQo=");
  }
  
  private String g()
  {
    return a("clientCert", "LS0tLS1CRUdJTiBDRVJUSUZJQ0FURS0tLS0tCk1JSURYekNDQWtlZ0F3SUJBZ0lCQVRBTkJna3Foa2lHOXcwQkFRVUZBREJpTVFzd0NRWURWUVFHRXdKRFRqRVEKTUE0R0ExVUVDQXdIUW1WcGFtbHVaekVRTUE0R0ExVUVCd3dIUW1WcGFtbHVaekVTTUJBR0ExVUVDd3dKUVhKeQpiM2R1YjJOck1Sc3dHUVlEVlFRRERCSkJjbkp2ZDI1dlkyc2dRMjh1TEV4MFpDNHdIaGNOTVRZd05qQTFNVFUxCk5qTXdXaGNOTXpZd05UTXhNVFUxTmpNd1dqQmlNUXN3Q1FZRFZRUUdFd0pEVGpFUU1BNEdBMVVFQ0F3SFFtVnAKYW1sdVp6RVFNQTRHQTFVRUJ3d0hRbVZwYW1sdVp6RVNNQkFHQTFVRUN3d0pRWEp5YjNkdWIyTnJNUnN3R1FZRApWUVFEREJKQmNuSnZkMjV2WTJzZ1EyOHVMRXgwWkM0d2dnRWlNQTBHQ1NxR1NJYjNEUUVCQVFVQUE0SUJEd0F3CmdnRUtBb0lCQVFERTREa1dWT1BmVlY2TjVkRktxaUtsaUNodUNreEQ4SDdLUTNyUm1ZdnY0K3NKdzFDUXBpU3cKOUpDQlJ6dDk5anM3VWdZK3htUnl1S0dNMWIrN3UwUERtT0xhNithTktZVEpRREZVaUE1Qlp2SWNHZFdKWjZJNwpjMk0zc1lzSU5uV1Q3Q0EySnV3TDR2V094eXB5UlhvQm8rWUFtYm12ZVlTcnpyK1VzT2JybENwSjdaOEhhRkowCm15VmFLL3FqQllqVzVWTFFiUHhNSGxrWURmbHYxdytwQUJNRDhLREtwSGc4Y1RmOGVoR1FPSHZ4NUtxMFNDU3UKZTlnNzkyV3hNOGdKWTZPRHJ3OW53d1QxUHVZZmJUNm5XU0kwY0VYZUZhK2pNVXVzaWJwSWhYdVRiNzR5ZmVyUwpjeE55WlE3TzNydEJFbThPVk15NzBFcmpjemlVU1NIM0FnTUJBQUdqSURBZU1Ba0dBMVVkRXdRQ01BQXdFUVlKCllJWklBWWI0UWdFQkJBUURBZ2VBTUEwR0NTcUdTSWIzRFFFQkJRVUFBNElCQVFBemYwQnphUWhGcklHUnUzTjgKZU4ycEhQMzZEK1o4OXQzcTVDWG5TbW9ERTBObUY0Yjc2T1dKU2YyOERoZHoycjBPS3pUOThjR3RlY25ZMHE4VApvTW5pZHdiK21DUFloQ09qTkpnbitwUjNIWGh0YjdwaSt4RkVieituOWNHT3kxWW02bTZidUdHSitaUHZ6Z2JOClA5N1BPdi92aVl0SUkxZmFVdzZaMDBSdmxqUlBqNFZJQjN2ZTNWa3NrOUpRSXJxRTVhUFhGNEwxTFpyV21jRkwKWlJURVMyUnpQZ2ZQZktJOTlyWVlJYnE0MVRQRDlFemhmdkJORyt0WmdnSG9uY0ROdnhYcE1USmZlOEZzUVNmeQphaFFXQ0lrcnE0YXZIWGlETmtqNlFocXJQT0tZRTR6K1VBY0VLSHpUQnZ2Z2ZKUTZ0TVJjUjcvMmNZTHMxZTNKCmlXdkYKLS0tLS1FTkQgQ0VSVElGSUNBVEUtLS0tLQo=");
  }
  
  private String h()
  {
    return a("clientKey", "LS0tLS1CRUdJTiBSU0EgUFJJVkFURSBLRVktLS0tLQpNSUlFcEFJQkFBS0NBUUVBeE9BNUZsVGozMVZlamVYUlNxb2lwWWdvYmdwTVEvQit5a042MFptTDcrUHJDY05RCmtLWWtzUFNRZ1VjN2ZmWTdPMUlHUHNaa2NyaWhqTlcvdTd0RHc1amkydXZtalNtRXlVQXhWSWdPUVdieUhCblYKaVdlaU8zTmpON0dMQ0RaMWsrd2dOaWJzQytMMWpzY3Fja1Y2QWFQbUFKbTVyM21FcTg2L2xMRG02NVFxU2UyZgpCMmhTZEpzbFdpdjZvd1dJMXVWUzBHejhUQjVaR0EzNWI5Y1BxUUFUQS9DZ3lxUjRQSEUzL0hvUmtEaDc4ZVNxCnRFZ2tybnZZTy9kbHNUUElDV09qZzY4UFo4TUU5VDdtSDIwK3Axa2lOSEJGM2hXdm96RkxySW02U0lWN2syKysKTW4zcTBuTVRjbVVPenQ2N1FSSnZEbFRNdTlCSzQzTTRsRWtoOXdJREFRQUJBb0lCQVFDMTNWdGU0YlJPanBIMgpDcUkza3NyR2x1eWlHaWt4YVd2MmREZDBmNTdoVDIzRGF3VjFXY1R6SWppSzg3NWxNWnl0dzZ1NU9aTjQxazJGCng3NkNNUTc4RkxNYkFHZk5adGtlLzRtU1NNekNaZEtwV3NRRFZoUnJUc0FNcHBtRVVLcDBwdDlxcHJIT21TMjEKWXc0MjJTOUhiSnYvV2dKSnNydDM2bGpYaGtNS3dnY0I3Vk8yRnh5cWNyOUl5VW5uYkVCOWhEN3F2cm54VHNaTwpicWtMSW9ncnkyNjZOb3R0YmVhR3dMUW5XTG1NSFRjcFdIV0dibURaLzBjNUVkS1N3UmpHbllRN2c3TncrU2o3Cjd2NUpiYkc0UWNEK1BwUlh6bW9Hc29QUkVoMzlzNi8wQjVCUWQzNjdmM05oQ0hVa0QzNWFiMDJEVGdTdW13cW4KOXRTUUJPSmhBb0dCQVBqdmRNS1BibUZPV2hxdENVdlEwL1FSOStaS09XVGREZmdZZVdVZGVJUEg0bzVlelZoQwovOGVLVXp3d1FHdGduUk1reXNEbVRqR1ZnRTFjZUwxN1BxUU51VmxaeWZqbkVyK1MzVmFJVDE1M1VvRnJzTWtNCmJmbm45c1hVWlJQc0JqL3U2R3A4Q3dramRWMTBSMXEySDZjdjFWRnBobjFXTUVOM1JmL0E3VWtyQW9HQkFNcDIKakhWR3NWRVFpZFdJZXI2M3RxVzZHVjJrejBrNHFnT3RJcVZkS1p0dVNPMUZWRDVoblRLQzVUQ0ZGRkN5WlF5bwpUQWtaMnQwb2NSd01WSnY2cklNUGNnVXVwZXE1cTdaNE43MHdtUytDRUNtYTVROTlxY3l0OXlSWjYyR3NMSDlhCk5XaXZ2QW8yL2FYalYxYTF1Z0xCZHBkZHJzUElWc1JwYWM2b2w4eGxBb0dCQU0yN2dRRG03MittQkp1MVZGQi8KVnh5STJSdFBUcDNJZjZvQitCb1VRQ3lSUHZFdzhuNjJhSlB1QXhwa09tbEQ0SzBZcENUR2NldFN4a1dwWGZRagpia0xCUU9UU2F6UzFMRzU5bjBYTHcrU3JzdGxaT2pMK2ZjbWk1dlRhczJyQ2p1dTV0QVdGWE0yQnE1YS82ZFRUClhkZWJsYTRDQzI5OGtzaS9RMis2YjZFZkFvR0FXZ1FQT3UwdFZROTNXTnNQUjlCQ2dyaVZJbzl1SWUzeG1TVFgKTEpLWk55UDNoSmE0ZCt2S2luU3NGY0IxWWRPUEhldU5zdFl0K3ZwS0grQlRsZTREMlZsNnBsY3hLWVZYbFE4cQpLUkY4YWlUM3JxZlJnK3VwSFBtVDBqT3dkWUtwWGczcmhSbnREdFdZUExNeFY3b0FjODAwUHVSR0dZSHZJZkNFClBIKzB6Z2tDZ1lBSE5LS1RGTUxaZU9RTXBiNXYyYzNVdUNEaG1kQjczcGI4RTV1SnJidktIV09pc3kyVHcrRkEKL0E4WmJzMEp5UGFqZnhyODQ4ZFlFNU00OHlnSDVUc3gycFBsdXNOQjVnT054WlNLWkxRaGpKY3k5RUlQZEx6QwpGUWllblM4NXUwdTRDZ21DMG9JTnMrQnFFZE91eUhwUkdiRzV3Z285U3kya1pKaXJuZzZHOGc9PQotLS0tLUVORCBSU0EgUFJJVkFURSBLRVktLS0tLQo=");
  }
  
  /* Error */
  public final cp<String, Integer> a(String paramString)
    throws ArrownockException
  {
    // Byte code:
    //   0: aload_0
    //   1: getfield 34	df:jdField_a_of_type_AndroidContentContext	Landroid/content/Context;
    //   4: getstatic 781	com/arrownock/push/PushService:LOG_TAG	Ljava/lang/String;
    //   7: iconst_0
    //   8: invokevirtual 785	android/content/Context:getSharedPreferences	(Ljava/lang/String;I)Landroid/content/SharedPreferences;
    //   11: astore 13
    //   13: aload 13
    //   15: ldc_w 787
    //   18: aconst_null
    //   19: invokeinterface 791 3 0
    //   24: astore 12
    //   26: aload 13
    //   28: ldc_w 793
    //   31: sipush 1883
    //   34: invokeinterface 796 3 0
    //   39: istore_3
    //   40: aload 13
    //   42: ldc_w 798
    //   45: lconst_0
    //   46: invokeinterface 801 4 0
    //   51: lstore 7
    //   53: invokestatic 402	java/lang/System:currentTimeMillis	()J
    //   56: lload 7
    //   58: lcmp
    //   59: ifle +209 -> 268
    //   62: iconst_1
    //   63: istore_2
    //   64: iload_2
    //   65: ifeq +65 -> 130
    //   68: aconst_null
    //   69: astore 12
    //   71: aload_0
    //   72: getfield 34	df:jdField_a_of_type_AndroidContentContext	Landroid/content/Context;
    //   75: getstatic 781	com/arrownock/push/PushService:LOG_TAG	Ljava/lang/String;
    //   78: iconst_0
    //   79: invokevirtual 785	android/content/Context:getSharedPreferences	(Ljava/lang/String;I)Landroid/content/SharedPreferences;
    //   82: invokeinterface 805 1 0
    //   87: astore 13
    //   89: aload 13
    //   91: ldc_w 787
    //   94: invokeinterface 811 2 0
    //   99: pop
    //   100: aload 13
    //   102: ldc_w 793
    //   105: invokeinterface 811 2 0
    //   110: pop
    //   111: aload 13
    //   113: ldc_w 798
    //   116: invokeinterface 811 2 0
    //   121: pop
    //   122: aload 13
    //   124: invokeinterface 814 1 0
    //   129: pop
    //   130: aload 12
    //   132: ifnonnull +936 -> 1068
    //   135: new 62	java/lang/StringBuilder
    //   138: dup
    //   139: invokespecial 98	java/lang/StringBuilder:<init>	()V
    //   142: astore 13
    //   144: aload 13
    //   146: new 62	java/lang/StringBuilder
    //   149: dup
    //   150: invokespecial 98	java/lang/StringBuilder:<init>	()V
    //   153: aload_0
    //   154: invokespecial 667	df:d	()Ljava/lang/String;
    //   157: invokevirtual 104	java/lang/StringBuilder:append	(Ljava/lang/String;)Ljava/lang/StringBuilder;
    //   160: ldc_w 816
    //   163: invokevirtual 104	java/lang/StringBuilder:append	(Ljava/lang/String;)Ljava/lang/StringBuilder;
    //   166: aload_1
    //   167: invokevirtual 104	java/lang/StringBuilder:append	(Ljava/lang/String;)Ljava/lang/StringBuilder;
    //   170: invokevirtual 74	java/lang/StringBuilder:toString	()Ljava/lang/String;
    //   173: invokevirtual 104	java/lang/StringBuilder:append	(Ljava/lang/String;)Ljava/lang/StringBuilder;
    //   176: pop
    //   177: aload_0
    //   178: getfield 34	df:jdField_a_of_type_AndroidContentContext	Landroid/content/Context;
    //   181: invokestatic 677	df:a	(Landroid/content/Context;)Ljava/util/Map;
    //   184: astore_1
    //   185: aload_1
    //   186: invokeinterface 171 1 0
    //   191: invokeinterface 174 1 0
    //   196: astore 14
    //   198: aload 14
    //   200: invokeinterface 129 1 0
    //   205: ifeq +68 -> 273
    //   208: aload 14
    //   210: invokeinterface 133 1 0
    //   215: checkcast 176	java/lang/String
    //   218: astore 15
    //   220: aload 13
    //   222: new 62	java/lang/StringBuilder
    //   225: dup
    //   226: ldc -106
    //   228: invokespecial 67	java/lang/StringBuilder:<init>	(Ljava/lang/String;)V
    //   231: aload 15
    //   233: invokevirtual 104	java/lang/StringBuilder:append	(Ljava/lang/String;)Ljava/lang/StringBuilder;
    //   236: ldc -111
    //   238: invokevirtual 104	java/lang/StringBuilder:append	(Ljava/lang/String;)Ljava/lang/StringBuilder;
    //   241: aload_1
    //   242: aload 15
    //   244: invokeinterface 180 2 0
    //   249: checkcast 176	java/lang/String
    //   252: invokestatic 679	java/net/URLEncoder:encode	(Ljava/lang/String;)Ljava/lang/String;
    //   255: invokevirtual 104	java/lang/StringBuilder:append	(Ljava/lang/String;)Ljava/lang/StringBuilder;
    //   258: invokevirtual 74	java/lang/StringBuilder:toString	()Ljava/lang/String;
    //   261: invokevirtual 104	java/lang/StringBuilder:append	(Ljava/lang/String;)Ljava/lang/StringBuilder;
    //   264: pop
    //   265: goto -67 -> 198
    //   268: iconst_0
    //   269: istore_2
    //   270: goto -206 -> 64
    //   273: aload 13
    //   275: ldc_w 690
    //   278: invokevirtual 104	java/lang/StringBuilder:append	(Ljava/lang/String;)Ljava/lang/StringBuilder;
    //   281: pop
    //   282: aload 13
    //   284: invokevirtual 74	java/lang/StringBuilder:toString	()Ljava/lang/String;
    //   287: astore_1
    //   288: iconst_0
    //   289: istore_2
    //   290: aload 12
    //   292: ifnonnull +672 -> 964
    //   295: iload_2
    //   296: iconst_1
    //   297: iadd
    //   298: istore_2
    //   299: iload_2
    //   300: iconst_5
    //   301: if_icmpgt +663 -> 964
    //   304: aload_0
    //   305: new 62	java/lang/StringBuilder
    //   308: dup
    //   309: invokespecial 98	java/lang/StringBuilder:<init>	()V
    //   312: aload_1
    //   313: invokevirtual 104	java/lang/StringBuilder:append	(Ljava/lang/String;)Ljava/lang/StringBuilder;
    //   316: ldc_w 692
    //   319: invokevirtual 104	java/lang/StringBuilder:append	(Ljava/lang/String;)Ljava/lang/StringBuilder;
    //   322: iload_2
    //   323: invokevirtual 502	java/lang/StringBuilder:append	(I)Ljava/lang/StringBuilder;
    //   326: invokevirtual 74	java/lang/StringBuilder:toString	()Ljava/lang/String;
    //   329: invokespecial 818	df:b	(Ljava/lang/String;)Ljava/util/Map;
    //   332: astore 13
    //   334: aload 13
    //   336: ldc_w 333
    //   339: invokeinterface 180 2 0
    //   344: iconst_1
    //   345: invokestatic 338	java/lang/Boolean:valueOf	(Z)Ljava/lang/Boolean;
    //   348: invokevirtual 695	java/lang/Object:equals	(Ljava/lang/Object;)Z
    //   351: ifeq +77 -> 428
    //   354: iconst_1
    //   355: istore 4
    //   357: iload 4
    //   359: ifeq +95 -> 454
    //   362: aload 13
    //   364: ldc_w 732
    //   367: invokeinterface 180 2 0
    //   372: invokevirtual 696	java/lang/Object:toString	()Ljava/lang/String;
    //   375: astore 12
    //   377: aload_0
    //   378: getfield 34	df:jdField_a_of_type_AndroidContentContext	Landroid/content/Context;
    //   381: invokestatic 267	com/arrownock/push/AnPush:getInstance	(Landroid/content/Context;)Lcom/arrownock/push/AnPush;
    //   384: invokevirtual 270	com/arrownock/push/AnPush:isSecureConnection	()Z
    //   387: ifeq +47 -> 434
    //   390: aload 13
    //   392: ldc_w 736
    //   395: invokeinterface 180 2 0
    //   400: checkcast 342	java/lang/Integer
    //   403: invokevirtual 699	java/lang/Integer:intValue	()I
    //   406: istore_3
    //   407: aload 13
    //   409: ldc_w 738
    //   412: invokeinterface 180 2 0
    //   417: checkcast 744	java/lang/Long
    //   420: invokevirtual 821	java/lang/Long:longValue	()J
    //   423: lstore 7
    //   425: goto -135 -> 290
    //   428: iconst_0
    //   429: istore 4
    //   431: goto -74 -> 357
    //   434: aload 13
    //   436: ldc_w 734
    //   439: invokeinterface 180 2 0
    //   444: checkcast 342	java/lang/Integer
    //   447: invokevirtual 699	java/lang/Integer:intValue	()I
    //   450: istore_3
    //   451: goto -44 -> 407
    //   454: aload 13
    //   456: ldc_w 340
    //   459: invokeinterface 180 2 0
    //   464: checkcast 342	java/lang/Integer
    //   467: invokevirtual 699	java/lang/Integer:intValue	()I
    //   470: istore 6
    //   472: iload 6
    //   474: sipush 503
    //   477: if_icmpne +181 -> 658
    //   480: aload 13
    //   482: ldc_w 357
    //   485: invokeinterface 180 2 0
    //   490: invokevirtual 696	java/lang/Object:toString	()Ljava/lang/String;
    //   493: astore 14
    //   495: aload 13
    //   497: ldc_w 361
    //   500: invokeinterface 180 2 0
    //   505: checkcast 342	java/lang/Integer
    //   508: invokevirtual 699	java/lang/Integer:intValue	()I
    //   511: istore 5
    //   513: iload 5
    //   515: istore 4
    //   517: iload 5
    //   519: ifgt +6 -> 525
    //   522: iconst_5
    //   523: istore 4
    //   525: iload 4
    //   527: istore 5
    //   529: iload 4
    //   531: sipush 1800
    //   534: if_icmple +8 -> 542
    //   537: sipush 1800
    //   540: istore 5
    //   542: new 62	java/lang/StringBuilder
    //   545: dup
    //   546: ldc_w 823
    //   549: invokespecial 67	java/lang/StringBuilder:<init>	(Ljava/lang/String;)V
    //   552: iload 6
    //   554: invokevirtual 502	java/lang/StringBuilder:append	(I)Ljava/lang/StringBuilder;
    //   557: ldc_w 703
    //   560: invokevirtual 104	java/lang/StringBuilder:append	(Ljava/lang/String;)Ljava/lang/StringBuilder;
    //   563: aload 14
    //   565: invokevirtual 104	java/lang/StringBuilder:append	(Ljava/lang/String;)Ljava/lang/StringBuilder;
    //   568: ldc_w 705
    //   571: invokevirtual 104	java/lang/StringBuilder:append	(Ljava/lang/String;)Ljava/lang/StringBuilder;
    //   574: iload 5
    //   576: invokevirtual 502	java/lang/StringBuilder:append	(I)Ljava/lang/StringBuilder;
    //   579: ldc_w 707
    //   582: invokevirtual 104	java/lang/StringBuilder:append	(Ljava/lang/String;)Ljava/lang/StringBuilder;
    //   585: invokevirtual 74	java/lang/StringBuilder:toString	()Ljava/lang/String;
    //   588: astore 13
    //   590: invokestatic 256	bk:a	()Lbk;
    //   593: getstatic 22	df:jdField_a_of_type_JavaLangString	Ljava/lang/String;
    //   596: aload 13
    //   598: invokevirtual 709	bk:c	(Ljava/lang/String;Ljava/lang/String;)V
    //   601: iload 5
    //   603: sipush 1000
    //   606: imul
    //   607: i2l
    //   608: lstore 9
    //   610: lload 9
    //   612: invokestatic 715	java/lang/Thread:sleep	(J)V
    //   615: aload_0
    //   616: getfield 34	df:jdField_a_of_type_AndroidContentContext	Landroid/content/Context;
    //   619: invokestatic 267	com/arrownock/push/AnPush:getInstance	(Landroid/content/Context;)Lcom/arrownock/push/AnPush;
    //   622: invokevirtual 371	com/arrownock/push/AnPush:a	()Z
    //   625: istore 11
    //   627: iload 11
    //   629: ifne +13 -> 642
    //   632: aconst_null
    //   633: areturn
    //   634: astore 13
    //   636: iconst_m1
    //   637: istore 5
    //   639: goto -126 -> 513
    //   642: goto -352 -> 290
    //   645: astore_1
    //   646: new 79	com/arrownock/exception/ArrownockException
    //   649: dup
    //   650: aload_1
    //   651: sipush 3001
    //   654: invokespecial 718	com/arrownock/exception/ArrownockException:<init>	(Ljava/lang/Exception;I)V
    //   657: athrow
    //   658: iload 6
    //   660: sipush 403
    //   663: if_icmpne +107 -> 770
    //   666: aload 13
    //   668: ldc_w 357
    //   671: invokeinterface 180 2 0
    //   676: invokevirtual 696	java/lang/Object:toString	()Ljava/lang/String;
    //   679: astore_1
    //   680: aload 13
    //   682: ldc_w 749
    //   685: invokeinterface 180 2 0
    //   690: checkcast 335	java/lang/Boolean
    //   693: invokevirtual 826	java/lang/Boolean:booleanValue	()Z
    //   696: istore 11
    //   698: new 62	java/lang/StringBuilder
    //   701: dup
    //   702: ldc_w 828
    //   705: invokespecial 67	java/lang/StringBuilder:<init>	(Ljava/lang/String;)V
    //   708: aload_1
    //   709: invokevirtual 104	java/lang/StringBuilder:append	(Ljava/lang/String;)Ljava/lang/StringBuilder;
    //   712: astore 12
    //   714: iload 11
    //   716: ifeq +48 -> 764
    //   719: ldc_w 830
    //   722: astore_1
    //   723: aload 12
    //   725: aload_1
    //   726: invokevirtual 104	java/lang/StringBuilder:append	(Ljava/lang/String;)Ljava/lang/StringBuilder;
    //   729: invokevirtual 74	java/lang/StringBuilder:toString	()Ljava/lang/String;
    //   732: astore_1
    //   733: invokestatic 256	bk:a	()Lbk;
    //   736: getstatic 22	df:jdField_a_of_type_JavaLangString	Ljava/lang/String;
    //   739: aload_1
    //   740: invokevirtual 720	bk:d	(Ljava/lang/String;Ljava/lang/String;)V
    //   743: iload 11
    //   745: ifeq +17 -> 762
    //   748: aload_0
    //   749: ldc_w 636
    //   752: invokevirtual 832	df:a	(Ljava/lang/String;)V
    //   755: aload_0
    //   756: getfield 34	df:jdField_a_of_type_AndroidContentContext	Landroid/content/Context;
    //   759: invokestatic 835	com/arrownock/push/PushService:actionStop	(Landroid/content/Context;)V
    //   762: aconst_null
    //   763: areturn
    //   764: ldc -63
    //   766: astore_1
    //   767: goto -44 -> 723
    //   770: iload 6
    //   772: sipush 400
    //   775: if_icmpne +39 -> 814
    //   778: aload 13
    //   780: ldc_w 357
    //   783: invokeinterface 180 2 0
    //   788: invokevirtual 696	java/lang/Object:toString	()Ljava/lang/String;
    //   791: astore_1
    //   792: invokestatic 256	bk:a	()Lbk;
    //   795: getstatic 22	df:jdField_a_of_type_JavaLangString	Ljava/lang/String;
    //   798: aload_1
    //   799: invokevirtual 720	bk:d	(Ljava/lang/String;Ljava/lang/String;)V
    //   802: new 79	com/arrownock/exception/ArrownockException
    //   805: dup
    //   806: aload_1
    //   807: sipush 3001
    //   810: invokespecial 575	com/arrownock/exception/ArrownockException:<init>	(Ljava/lang/String;I)V
    //   813: athrow
    //   814: iload 6
    //   816: iconst_m1
    //   817: if_icmpne +43 -> 860
    //   820: aload 13
    //   822: ldc_w 359
    //   825: invokeinterface 180 2 0
    //   830: checkcast 197	java/lang/Exception
    //   833: astore_1
    //   834: invokestatic 256	bk:a	()Lbk;
    //   837: getstatic 22	df:jdField_a_of_type_JavaLangString	Ljava/lang/String;
    //   840: aload_1
    //   841: invokevirtual 580	java/lang/Exception:getMessage	()Ljava/lang/String;
    //   844: aload_1
    //   845: invokevirtual 261	bk:a	(Ljava/lang/String;Ljava/lang/String;Ljava/lang/Throwable;)V
    //   848: new 79	com/arrownock/exception/ArrownockException
    //   851: dup
    //   852: aload_1
    //   853: sipush 3001
    //   856: invokespecial 718	com/arrownock/exception/ArrownockException:<init>	(Ljava/lang/Exception;I)V
    //   859: athrow
    //   860: aload 13
    //   862: ldc_w 367
    //   865: invokeinterface 180 2 0
    //   870: invokevirtual 696	java/lang/Object:toString	()Ljava/lang/String;
    //   873: astore 13
    //   875: new 62	java/lang/StringBuilder
    //   878: dup
    //   879: ldc_w 823
    //   882: invokespecial 67	java/lang/StringBuilder:<init>	(Ljava/lang/String;)V
    //   885: iload 6
    //   887: invokevirtual 502	java/lang/StringBuilder:append	(I)Ljava/lang/StringBuilder;
    //   890: ldc_w 724
    //   893: invokevirtual 104	java/lang/StringBuilder:append	(Ljava/lang/String;)Ljava/lang/StringBuilder;
    //   896: aload 13
    //   898: invokevirtual 104	java/lang/StringBuilder:append	(Ljava/lang/String;)Ljava/lang/StringBuilder;
    //   901: ldc_w 726
    //   904: invokevirtual 104	java/lang/StringBuilder:append	(Ljava/lang/String;)Ljava/lang/StringBuilder;
    //   907: invokevirtual 74	java/lang/StringBuilder:toString	()Ljava/lang/String;
    //   910: astore 13
    //   912: invokestatic 256	bk:a	()Lbk;
    //   915: getstatic 22	df:jdField_a_of_type_JavaLangString	Ljava/lang/String;
    //   918: aload 13
    //   920: invokevirtual 709	bk:c	(Ljava/lang/String;Ljava/lang/String;)V
    //   923: ldc2_w 727
    //   926: invokestatic 715	java/lang/Thread:sleep	(J)V
    //   929: aload_0
    //   930: getfield 34	df:jdField_a_of_type_AndroidContentContext	Landroid/content/Context;
    //   933: invokestatic 267	com/arrownock/push/AnPush:getInstance	(Landroid/content/Context;)Lcom/arrownock/push/AnPush;
    //   936: invokevirtual 371	com/arrownock/push/AnPush:a	()Z
    //   939: istore 11
    //   941: iload 11
    //   943: ifne +5 -> 948
    //   946: aconst_null
    //   947: areturn
    //   948: goto -658 -> 290
    //   951: astore_1
    //   952: new 79	com/arrownock/exception/ArrownockException
    //   955: dup
    //   956: aload_1
    //   957: sipush 3001
    //   960: invokespecial 718	com/arrownock/exception/ArrownockException:<init>	(Ljava/lang/Exception;I)V
    //   963: athrow
    //   964: aload 12
    //   966: ifnull +76 -> 1042
    //   969: aload_0
    //   970: getfield 34	df:jdField_a_of_type_AndroidContentContext	Landroid/content/Context;
    //   973: getstatic 781	com/arrownock/push/PushService:LOG_TAG	Ljava/lang/String;
    //   976: iconst_0
    //   977: invokevirtual 785	android/content/Context:getSharedPreferences	(Ljava/lang/String;I)Landroid/content/SharedPreferences;
    //   980: invokeinterface 805 1 0
    //   985: astore_1
    //   986: aload_1
    //   987: ldc_w 787
    //   990: aload 12
    //   992: invokeinterface 839 3 0
    //   997: pop
    //   998: aload_1
    //   999: ldc_w 793
    //   1002: iload_3
    //   1003: invokeinterface 843 3 0
    //   1008: pop
    //   1009: aload_1
    //   1010: ldc_w 798
    //   1013: lload 7
    //   1015: invokeinterface 847 4 0
    //   1020: pop
    //   1021: aload_1
    //   1022: invokeinterface 814 1 0
    //   1027: pop
    //   1028: new 849	cp
    //   1031: dup
    //   1032: aload 12
    //   1034: iload_3
    //   1035: invokestatic 345	java/lang/Integer:valueOf	(I)Ljava/lang/Integer;
    //   1038: invokespecial 852	cp:<init>	(Ljava/lang/Object;Ljava/lang/Object;)V
    //   1041: areturn
    //   1042: invokestatic 256	bk:a	()Lbk;
    //   1045: getstatic 22	df:jdField_a_of_type_JavaLangString	Ljava/lang/String;
    //   1048: ldc_w 854
    //   1051: invokevirtual 720	bk:d	(Ljava/lang/String;Ljava/lang/String;)V
    //   1054: new 79	com/arrownock/exception/ArrownockException
    //   1057: dup
    //   1058: ldc_w 854
    //   1061: sipush 3001
    //   1064: invokespecial 575	com/arrownock/exception/ArrownockException:<init>	(Ljava/lang/String;I)V
    //   1067: athrow
    //   1068: goto -40 -> 1028
    // Local variable table:
    //   start	length	slot	name	signature
    //   0	1071	0	this	df
    //   0	1071	1	paramString	String
    //   63	260	2	i	int
    //   39	996	3	j	int
    //   355	180	4	k	int
    //   511	127	5	m	int
    //   470	416	6	n	int
    //   51	963	7	l1	long
    //   608	3	9	l2	long
    //   625	317	11	bool	boolean
    //   24	1009	12	localObject1	Object
    //   11	586	13	localObject2	Object
    //   634	227	13	localException	Exception
    //   873	46	13	str1	String
    //   196	368	14	localObject3	Object
    //   218	25	15	str2	String
    // Exception table:
    //   from	to	target	type
    //   495	513	634	java/lang/Exception
    //   610	627	645	java/lang/InterruptedException
    //   923	941	951	java/lang/InterruptedException
  }
  
  public final String a()
    throws ArrownockException
  {
    String str1 = a("MIPUSH_REG_ID", "");
    if (str1.isEmpty()) {
      str1 = "";
    }
    String str2;
    do
    {
      return str1;
      str2 = a("MIPUSH_APP", "");
      if (str2.isEmpty()) {
        return "";
      }
    } while ((a("com.arrownock.push.MIPUSH_APPID", "") + a("com.arrownock.push.MIPUSH_APPKEY", "")).equals(str2));
    return "";
  }
  
  public final String a(Context paramContext)
    throws ArrownockException
  {
    String str1 = a("GCM_REG_ID", "");
    if (str1.isEmpty()) {
      return "";
    }
    String str2 = a("GCM_REG_VERSION_CODE", "");
    int j = Integer.MIN_VALUE;
    int i = j;
    if (!str2.isEmpty()) {}
    try
    {
      i = Integer.parseInt(str2);
      if (i != a(paramContext)) {
        return "";
      }
      return str1;
    }
    catch (Exception localException)
    {
      for (;;)
      {
        i = j;
      }
    }
  }
  
  public final String a(Context paramContext, String paramString)
  {
    try
    {
      Object localObject1 = ((TelephonyManager)paramContext.getSystemService("phone")).getDeviceId();
      for (;;)
      {
        try
        {
          String str2 = Build.SERIAL;
          str1 = Settings.Secure.getString(paramContext.getContentResolver(), "android_id");
          if ((localObject1 != null) && (!((String)localObject1).equals("000000000000000")))
          {
            if ("".equals(((String)localObject1).trim()))
            {
              break label351;
              if (str2 == null) {
                break label357;
              }
              if (str2.trim().equals("unknown"))
              {
                break label357;
                if (str1 == null) {
                  break label364;
                }
                if (!"".equals(str1.trim())) {
                  continue;
                }
                break label364;
                if ((!"".equals(paramContext)) || (!"".equals(localObject1)) || (!"".equals(str1))) {
                  continue;
                }
                return "";
              }
            }
            else
            {
              paramContext = "D" + (String)localObject1;
              continue;
            }
            localObject1 = "S" + str2;
            continue;
            str1 = "A" + str1;
            continue;
            paramString = paramContext + (String)localObject1 + str1 + "K" + paramString;
            try
            {
              paramContext = MessageDigest.getInstance("MD5").digest(paramString.getBytes());
              localObject1 = new StringBuffer();
              int i = 0;
              if (i < paramContext.length)
              {
                ((StringBuffer)localObject1).append(Integer.toHexString(paramContext[i] & 0xFF | 0x100).substring(1, 3));
                i += 1;
                continue;
              }
              paramContext = ((StringBuffer)localObject1).toString();
            }
            catch (NoSuchAlgorithmException paramContext)
            {
              paramContext = UUID.nameUUIDFromBytes(paramString.getBytes()).toString();
              continue;
            }
            return "2" + paramContext;
          }
        }
        catch (Exception paramContext)
        {
          paramContext.printStackTrace();
          return "";
        }
        label351:
        paramContext = "";
        continue;
        label357:
        localObject1 = "";
        continue;
        label364:
        String str1 = "";
      }
    }
    catch (Exception localException)
    {
      for (;;)
      {
        Object localObject2 = null;
      }
    }
  }
  
  public final String a(String paramString)
  {
    return a(paramString, "");
  }
  
  public final String a(String paramString1, String paramString2)
  {
    return jdField_a_of_type_AndroidContentContext.getSharedPreferences(PushService.LOG_TAG, 0).getString(paramString1, paramString2);
  }
  
  /* Error */
  public final String a(String paramString1, String paramString2, String paramString3, boolean paramBoolean, String paramString4, String paramString5)
    throws ArrownockException
  {
    // Byte code:
    //   0: aconst_null
    //   1: astore 11
    //   3: aconst_null
    //   4: astore 8
    //   6: aload 8
    //   8: astore 10
    //   10: aload 11
    //   12: astore 9
    //   14: aload_0
    //   15: getfield 34	df:jdField_a_of_type_AndroidContentContext	Landroid/content/Context;
    //   18: invokestatic 267	com/arrownock/push/AnPush:getInstance	(Landroid/content/Context;)Lcom/arrownock/push/AnPush;
    //   21: invokevirtual 270	com/arrownock/push/AnPush:isSecureConnection	()Z
    //   24: ifeq +834 -> 858
    //   27: aload 8
    //   29: astore 10
    //   31: aload 11
    //   33: astore 9
    //   35: new 272	java/net/URL
    //   38: dup
    //   39: new 62	java/lang/StringBuilder
    //   42: dup
    //   43: ldc_w 274
    //   46: invokespecial 67	java/lang/StringBuilder:<init>	(Ljava/lang/String;)V
    //   49: aload_0
    //   50: invokespecial 445	df:c	()Ljava/lang/String;
    //   53: invokevirtual 104	java/lang/StringBuilder:append	(Ljava/lang/String;)Ljava/lang/StringBuilder;
    //   56: ldc_w 916
    //   59: invokevirtual 104	java/lang/StringBuilder:append	(Ljava/lang/String;)Ljava/lang/StringBuilder;
    //   62: aload_1
    //   63: invokevirtual 450	java/lang/String:trim	()Ljava/lang/String;
    //   66: invokevirtual 104	java/lang/StringBuilder:append	(Ljava/lang/String;)Ljava/lang/StringBuilder;
    //   69: invokevirtual 74	java/lang/StringBuilder:toString	()Ljava/lang/String;
    //   72: invokespecial 275	java/net/URL:<init>	(Ljava/lang/String;)V
    //   75: invokevirtual 279	java/net/URL:openConnection	()Ljava/net/URLConnection;
    //   78: checkcast 281	javax/net/ssl/HttpsURLConnection
    //   81: astore 8
    //   83: aload 8
    //   85: checkcast 281	javax/net/ssl/HttpsURLConnection
    //   88: getstatic 29	df:jdField_a_of_type_JavaxNetSslHostnameVerifier	Ljavax/net/ssl/HostnameVerifier;
    //   91: invokevirtual 285	javax/net/ssl/HttpsURLConnection:setHostnameVerifier	(Ljavax/net/ssl/HostnameVerifier;)V
    //   94: aload 8
    //   96: checkcast 281	javax/net/ssl/HttpsURLConnection
    //   99: aload_0
    //   100: invokespecial 288	df:f	()Ljava/lang/String;
    //   103: aload_0
    //   104: invokespecial 291	df:g	()Ljava/lang/String;
    //   107: aload_0
    //   108: invokespecial 294	df:h	()Ljava/lang/String;
    //   111: ldc -63
    //   113: ldc_w 296
    //   116: invokestatic 301	at:a	(Ljava/lang/String;Ljava/lang/String;Ljava/lang/String;Ljava/lang/String;Ljava/lang/String;)Ljavax/net/ssl/SSLSocketFactory;
    //   119: invokevirtual 305	javax/net/ssl/HttpsURLConnection:setSSLSocketFactory	(Ljavax/net/ssl/SSLSocketFactory;)V
    //   122: aload 8
    //   124: astore 10
    //   126: aload 8
    //   128: astore 9
    //   130: aload 8
    //   132: ldc_w 452
    //   135: invokevirtual 455	java/net/HttpURLConnection:setRequestMethod	(Ljava/lang/String;)V
    //   138: aload 8
    //   140: astore 10
    //   142: aload 8
    //   144: astore 9
    //   146: aload 8
    //   148: iconst_1
    //   149: invokevirtual 459	java/net/HttpURLConnection:setDoInput	(Z)V
    //   152: aload 8
    //   154: astore 10
    //   156: aload 8
    //   158: astore 9
    //   160: aload 8
    //   162: iconst_1
    //   163: invokevirtual 462	java/net/HttpURLConnection:setDoOutput	(Z)V
    //   166: aload 8
    //   168: astore 10
    //   170: aload 8
    //   172: astore 9
    //   174: new 464	java/text/SimpleDateFormat
    //   177: dup
    //   178: ldc_w 466
    //   181: getstatic 472	java/util/Locale:US	Ljava/util/Locale;
    //   184: invokespecial 475	java/text/SimpleDateFormat:<init>	(Ljava/lang/String;Ljava/util/Locale;)V
    //   187: new 477	java/util/Date
    //   190: dup
    //   191: invokespecial 478	java/util/Date:<init>	()V
    //   194: invokevirtual 482	java/text/SimpleDateFormat:format	(Ljava/util/Date;)Ljava/lang/String;
    //   197: astore 13
    //   199: aload 8
    //   201: astore 10
    //   203: aload 8
    //   205: astore 9
    //   207: new 484	java/util/ArrayList
    //   210: dup
    //   211: invokespecial 485	java/util/ArrayList:<init>	()V
    //   214: astore 12
    //   216: aload 8
    //   218: astore 10
    //   220: aload 8
    //   222: astore 9
    //   224: aload 12
    //   226: new 487	org/apache/http/message/BasicNameValuePair
    //   229: dup
    //   230: ldc_w 327
    //   233: aload_2
    //   234: invokespecial 489	org/apache/http/message/BasicNameValuePair:<init>	(Ljava/lang/String;Ljava/lang/String;)V
    //   237: invokeinterface 493 2 0
    //   242: pop
    //   243: aload 8
    //   245: astore 10
    //   247: aload 8
    //   249: astore 9
    //   251: aload 12
    //   253: new 487	org/apache/http/message/BasicNameValuePair
    //   256: dup
    //   257: ldc_w 495
    //   260: aload 13
    //   262: invokespecial 489	org/apache/http/message/BasicNameValuePair:<init>	(Ljava/lang/String;Ljava/lang/String;)V
    //   265: invokeinterface 493 2 0
    //   270: pop
    //   271: aload 8
    //   273: astore 10
    //   275: aload 8
    //   277: astore 9
    //   279: aload 12
    //   281: new 487	org/apache/http/message/BasicNameValuePair
    //   284: dup
    //   285: ldc_w 918
    //   288: aload 5
    //   290: invokespecial 489	org/apache/http/message/BasicNameValuePair:<init>	(Ljava/lang/String;Ljava/lang/String;)V
    //   293: invokeinterface 493 2 0
    //   298: pop
    //   299: aload 8
    //   301: astore 10
    //   303: aload 8
    //   305: astore 9
    //   307: aload 12
    //   309: new 487	org/apache/http/message/BasicNameValuePair
    //   312: dup
    //   313: ldc_w 920
    //   316: aload_3
    //   317: invokespecial 489	org/apache/http/message/BasicNameValuePair:<init>	(Ljava/lang/String;Ljava/lang/String;)V
    //   320: invokeinterface 493 2 0
    //   325: pop
    //   326: aload 6
    //   328: ifnonnull +589 -> 917
    //   331: ldc -63
    //   333: astore 11
    //   335: aload 8
    //   337: astore 10
    //   339: aload 8
    //   341: astore 9
    //   343: aload 12
    //   345: new 487	org/apache/http/message/BasicNameValuePair
    //   348: dup
    //   349: ldc_w 922
    //   352: aload 11
    //   354: invokespecial 489	org/apache/http/message/BasicNameValuePair:<init>	(Ljava/lang/String;Ljava/lang/String;)V
    //   357: invokeinterface 493 2 0
    //   362: pop
    //   363: aload 8
    //   365: astore 10
    //   367: aload 8
    //   369: astore 9
    //   371: getstatic 927	cm:a	Ljava/lang/Boolean;
    //   374: invokevirtual 826	java/lang/Boolean:booleanValue	()Z
    //   377: ifeq +1007 -> 1384
    //   380: aload 8
    //   382: astore 10
    //   384: aload 8
    //   386: astore 9
    //   388: aload_0
    //   389: getfield 34	df:jdField_a_of_type_AndroidContentContext	Landroid/content/Context;
    //   392: aload_1
    //   393: invokestatic 932	be:a	(Landroid/content/Context;Ljava/lang/String;)Lbe;
    //   396: invokevirtual 934	be:a	()Ljava/lang/String;
    //   399: astore 11
    //   401: aload 8
    //   403: astore 10
    //   405: aload 8
    //   407: astore 9
    //   409: ldc -63
    //   411: aload 11
    //   413: invokevirtual 641	java/lang/String:equals	(Ljava/lang/Object;)Z
    //   416: ifeq +652 -> 1068
    //   419: iload 4
    //   421: ifeq +531 -> 952
    //   424: aload 8
    //   426: astore 10
    //   428: aload 8
    //   430: astore 9
    //   432: aload 12
    //   434: new 487	org/apache/http/message/BasicNameValuePair
    //   437: dup
    //   438: ldc_w 936
    //   441: ldc_w 598
    //   444: invokespecial 489	org/apache/http/message/BasicNameValuePair:<init>	(Ljava/lang/String;Ljava/lang/String;)V
    //   447: invokeinterface 493 2 0
    //   452: pop
    //   453: aload 8
    //   455: astore 10
    //   457: aload 8
    //   459: astore 9
    //   461: new 62	java/lang/StringBuilder
    //   464: dup
    //   465: ldc_w 938
    //   468: invokespecial 67	java/lang/StringBuilder:<init>	(Ljava/lang/String;)V
    //   471: aload_3
    //   472: invokevirtual 104	java/lang/StringBuilder:append	(Ljava/lang/String;)Ljava/lang/StringBuilder;
    //   475: ldc_w 504
    //   478: invokevirtual 104	java/lang/StringBuilder:append	(Ljava/lang/String;)Ljava/lang/StringBuilder;
    //   481: aload 13
    //   483: invokevirtual 104	java/lang/StringBuilder:append	(Ljava/lang/String;)Ljava/lang/StringBuilder;
    //   486: ldc_w 506
    //   489: invokevirtual 104	java/lang/StringBuilder:append	(Ljava/lang/String;)Ljava/lang/StringBuilder;
    //   492: aload_2
    //   493: invokevirtual 104	java/lang/StringBuilder:append	(Ljava/lang/String;)Ljava/lang/StringBuilder;
    //   496: ldc_w 940
    //   499: invokevirtual 104	java/lang/StringBuilder:append	(Ljava/lang/String;)Ljava/lang/StringBuilder;
    //   502: astore_3
    //   503: aload 6
    //   505: ifnonnull +430 -> 935
    //   508: ldc -63
    //   510: astore_2
    //   511: aload 8
    //   513: astore 10
    //   515: aload 8
    //   517: astore 9
    //   519: aload_3
    //   520: aload_2
    //   521: invokevirtual 104	java/lang/StringBuilder:append	(Ljava/lang/String;)Ljava/lang/StringBuilder;
    //   524: ldc_w 508
    //   527: invokevirtual 104	java/lang/StringBuilder:append	(Ljava/lang/String;)Ljava/lang/StringBuilder;
    //   530: aload_1
    //   531: invokevirtual 104	java/lang/StringBuilder:append	(Ljava/lang/String;)Ljava/lang/StringBuilder;
    //   534: ldc_w 942
    //   537: invokevirtual 104	java/lang/StringBuilder:append	(Ljava/lang/String;)Ljava/lang/StringBuilder;
    //   540: aload 5
    //   542: invokevirtual 104	java/lang/StringBuilder:append	(Ljava/lang/String;)Ljava/lang/StringBuilder;
    //   545: invokevirtual 74	java/lang/StringBuilder:toString	()Ljava/lang/String;
    //   548: astore_1
    //   549: aload 8
    //   551: astore 9
    //   553: new 510	javax/crypto/spec/SecretKeySpec
    //   556: dup
    //   557: aload_0
    //   558: invokespecial 513	df:e	()Ljava/lang/String;
    //   561: invokevirtual 517	java/lang/String:getBytes	()[B
    //   564: ldc_w 519
    //   567: invokespecial 522	javax/crypto/spec/SecretKeySpec:<init>	([BLjava/lang/String;)V
    //   570: astore_2
    //   571: aload 8
    //   573: astore 9
    //   575: ldc_w 519
    //   578: invokestatic 527	javax/crypto/Mac:getInstance	(Ljava/lang/String;)Ljavax/crypto/Mac;
    //   581: astore_3
    //   582: aload 8
    //   584: astore 9
    //   586: aload_3
    //   587: aload_2
    //   588: invokevirtual 531	javax/crypto/Mac:init	(Ljava/security/Key;)V
    //   591: aload 8
    //   593: astore 9
    //   595: aload 12
    //   597: new 487	org/apache/http/message/BasicNameValuePair
    //   600: dup
    //   601: ldc_w 533
    //   604: aload_3
    //   605: aload_1
    //   606: invokevirtual 517	java/lang/String:getBytes	()[B
    //   609: invokevirtual 537	javax/crypto/Mac:doFinal	([B)[B
    //   612: iconst_2
    //   613: invokestatic 543	android/util/Base64:encodeToString	([BI)Ljava/lang/String;
    //   616: invokespecial 489	org/apache/http/message/BasicNameValuePair:<init>	(Ljava/lang/String;Ljava/lang/String;)V
    //   619: invokeinterface 493 2 0
    //   624: pop
    //   625: aload 8
    //   627: astore 10
    //   629: aload 8
    //   631: astore 9
    //   633: aload 8
    //   635: invokevirtual 547	java/net/HttpURLConnection:getOutputStream	()Ljava/io/OutputStream;
    //   638: astore_1
    //   639: aload 8
    //   641: astore 10
    //   643: aload 8
    //   645: astore 9
    //   647: new 549	java/io/BufferedWriter
    //   650: dup
    //   651: new 551	java/io/OutputStreamWriter
    //   654: dup
    //   655: aload_1
    //   656: ldc -118
    //   658: invokespecial 554	java/io/OutputStreamWriter:<init>	(Ljava/io/OutputStream;Ljava/lang/String;)V
    //   661: invokespecial 557	java/io/BufferedWriter:<init>	(Ljava/io/Writer;)V
    //   664: astore_2
    //   665: aload 8
    //   667: astore 10
    //   669: aload 8
    //   671: astore 9
    //   673: aload_2
    //   674: aload 12
    //   676: invokestatic 559	df:a	(Ljava/util/List;)Ljava/lang/String;
    //   679: invokevirtual 562	java/io/BufferedWriter:write	(Ljava/lang/String;)V
    //   682: aload 8
    //   684: astore 10
    //   686: aload 8
    //   688: astore 9
    //   690: aload_2
    //   691: invokevirtual 563	java/io/BufferedWriter:close	()V
    //   694: aload 8
    //   696: astore 10
    //   698: aload 8
    //   700: astore 9
    //   702: aload_1
    //   703: invokevirtual 566	java/io/OutputStream:close	()V
    //   706: aload 8
    //   708: astore 10
    //   710: aload 8
    //   712: astore 9
    //   714: aload 8
    //   716: invokevirtual 313	java/net/HttpURLConnection:getResponseCode	()I
    //   719: istore 7
    //   721: iload 7
    //   723: sipush 200
    //   726: if_icmpne +1078 -> 1804
    //   729: aload 8
    //   731: astore 10
    //   733: aload 8
    //   735: astore 9
    //   737: new 315	org/json/JSONObject
    //   740: dup
    //   741: new 317	java/io/BufferedInputStream
    //   744: dup
    //   745: aload 8
    //   747: invokevirtual 321	java/net/HttpURLConnection:getInputStream	()Ljava/io/InputStream;
    //   750: invokespecial 322	java/io/BufferedInputStream:<init>	(Ljava/io/InputStream;)V
    //   753: invokestatic 324	df:a	(Ljava/io/InputStream;)Ljava/lang/String;
    //   756: invokespecial 325	org/json/JSONObject:<init>	(Ljava/lang/String;)V
    //   759: ldc_w 944
    //   762: invokevirtual 572	org/json/JSONObject:getJSONObject	(Ljava/lang/String;)Lorg/json/JSONObject;
    //   765: astore_1
    //   766: aload_1
    //   767: ifnull +1015 -> 1782
    //   770: aload 8
    //   772: astore 10
    //   774: aload 8
    //   776: astore 9
    //   778: aload_1
    //   779: ldc_w 946
    //   782: invokevirtual 572	org/json/JSONObject:getJSONObject	(Ljava/lang/String;)Lorg/json/JSONObject;
    //   785: ifnull +997 -> 1782
    //   788: aload 8
    //   790: astore 10
    //   792: aload 8
    //   794: astore 9
    //   796: aload_1
    //   797: ldc_w 946
    //   800: invokevirtual 572	org/json/JSONObject:getJSONObject	(Ljava/lang/String;)Lorg/json/JSONObject;
    //   803: astore_1
    //   804: aload_1
    //   805: ifnull +931 -> 1736
    //   808: aload 8
    //   810: astore 10
    //   812: aload 8
    //   814: astore 9
    //   816: aload_1
    //   817: ldc_w 948
    //   820: invokevirtual 331	org/json/JSONObject:getString	(Ljava/lang/String;)Ljava/lang/String;
    //   823: ifnull +913 -> 1736
    //   826: aload 8
    //   828: astore 10
    //   830: aload 8
    //   832: astore 9
    //   834: aload_1
    //   835: ldc_w 948
    //   838: invokevirtual 331	org/json/JSONObject:getString	(Ljava/lang/String;)Ljava/lang/String;
    //   841: astore_1
    //   842: aload_1
    //   843: astore_2
    //   844: aload 8
    //   846: ifnull +10 -> 856
    //   849: aload 8
    //   851: invokevirtual 350	java/net/HttpURLConnection:disconnect	()V
    //   854: aload_1
    //   855: astore_2
    //   856: aload_2
    //   857: areturn
    //   858: aload 8
    //   860: astore 10
    //   862: aload 11
    //   864: astore 9
    //   866: new 272	java/net/URL
    //   869: dup
    //   870: new 62	java/lang/StringBuilder
    //   873: dup
    //   874: ldc_w 352
    //   877: invokespecial 67	java/lang/StringBuilder:<init>	(Ljava/lang/String;)V
    //   880: aload_0
    //   881: invokespecial 445	df:c	()Ljava/lang/String;
    //   884: invokevirtual 104	java/lang/StringBuilder:append	(Ljava/lang/String;)Ljava/lang/StringBuilder;
    //   887: ldc_w 916
    //   890: invokevirtual 104	java/lang/StringBuilder:append	(Ljava/lang/String;)Ljava/lang/StringBuilder;
    //   893: aload_1
    //   894: invokevirtual 450	java/lang/String:trim	()Ljava/lang/String;
    //   897: invokevirtual 104	java/lang/StringBuilder:append	(Ljava/lang/String;)Ljava/lang/StringBuilder;
    //   900: invokevirtual 74	java/lang/StringBuilder:toString	()Ljava/lang/String;
    //   903: invokespecial 275	java/net/URL:<init>	(Ljava/lang/String;)V
    //   906: invokevirtual 279	java/net/URL:openConnection	()Ljava/net/URLConnection;
    //   909: checkcast 307	java/net/HttpURLConnection
    //   912: astore 8
    //   914: goto -792 -> 122
    //   917: aload 8
    //   919: astore 10
    //   921: aload 8
    //   923: astore 9
    //   925: aload 6
    //   927: invokevirtual 450	java/lang/String:trim	()Ljava/lang/String;
    //   930: astore 11
    //   932: goto -597 -> 335
    //   935: aload 8
    //   937: astore 10
    //   939: aload 8
    //   941: astore 9
    //   943: aload 6
    //   945: invokevirtual 450	java/lang/String:trim	()Ljava/lang/String;
    //   948: astore_2
    //   949: goto -438 -> 511
    //   952: aload 8
    //   954: astore 10
    //   956: aload 8
    //   958: astore 9
    //   960: new 62	java/lang/StringBuilder
    //   963: dup
    //   964: ldc_w 938
    //   967: invokespecial 67	java/lang/StringBuilder:<init>	(Ljava/lang/String;)V
    //   970: aload_3
    //   971: invokevirtual 104	java/lang/StringBuilder:append	(Ljava/lang/String;)Ljava/lang/StringBuilder;
    //   974: ldc_w 504
    //   977: invokevirtual 104	java/lang/StringBuilder:append	(Ljava/lang/String;)Ljava/lang/StringBuilder;
    //   980: aload 13
    //   982: invokevirtual 104	java/lang/StringBuilder:append	(Ljava/lang/String;)Ljava/lang/StringBuilder;
    //   985: ldc_w 506
    //   988: invokevirtual 104	java/lang/StringBuilder:append	(Ljava/lang/String;)Ljava/lang/StringBuilder;
    //   991: aload_2
    //   992: invokevirtual 104	java/lang/StringBuilder:append	(Ljava/lang/String;)Ljava/lang/StringBuilder;
    //   995: ldc_w 940
    //   998: invokevirtual 104	java/lang/StringBuilder:append	(Ljava/lang/String;)Ljava/lang/StringBuilder;
    //   1001: astore_3
    //   1002: aload 6
    //   1004: ifnonnull +47 -> 1051
    //   1007: ldc -63
    //   1009: astore_2
    //   1010: aload 8
    //   1012: astore 10
    //   1014: aload 8
    //   1016: astore 9
    //   1018: aload_3
    //   1019: aload_2
    //   1020: invokevirtual 104	java/lang/StringBuilder:append	(Ljava/lang/String;)Ljava/lang/StringBuilder;
    //   1023: ldc_w 508
    //   1026: invokevirtual 104	java/lang/StringBuilder:append	(Ljava/lang/String;)Ljava/lang/StringBuilder;
    //   1029: aload_1
    //   1030: invokevirtual 104	java/lang/StringBuilder:append	(Ljava/lang/String;)Ljava/lang/StringBuilder;
    //   1033: ldc_w 675
    //   1036: invokevirtual 104	java/lang/StringBuilder:append	(Ljava/lang/String;)Ljava/lang/StringBuilder;
    //   1039: aload 5
    //   1041: invokevirtual 104	java/lang/StringBuilder:append	(Ljava/lang/String;)Ljava/lang/StringBuilder;
    //   1044: invokevirtual 74	java/lang/StringBuilder:toString	()Ljava/lang/String;
    //   1047: astore_1
    //   1048: goto -499 -> 549
    //   1051: aload 8
    //   1053: astore 10
    //   1055: aload 8
    //   1057: astore 9
    //   1059: aload 6
    //   1061: invokevirtual 450	java/lang/String:trim	()Ljava/lang/String;
    //   1064: astore_2
    //   1065: goto -55 -> 1010
    //   1068: aload 8
    //   1070: astore 10
    //   1072: aload 8
    //   1074: astore 9
    //   1076: aload 12
    //   1078: new 487	org/apache/http/message/BasicNameValuePair
    //   1081: dup
    //   1082: ldc_w 950
    //   1085: aload 11
    //   1087: invokespecial 489	org/apache/http/message/BasicNameValuePair:<init>	(Ljava/lang/String;Ljava/lang/String;)V
    //   1090: invokeinterface 493 2 0
    //   1095: pop
    //   1096: iload 4
    //   1098: ifeq +159 -> 1257
    //   1101: aload 8
    //   1103: astore 10
    //   1105: aload 8
    //   1107: astore 9
    //   1109: aload 12
    //   1111: new 487	org/apache/http/message/BasicNameValuePair
    //   1114: dup
    //   1115: ldc_w 936
    //   1118: ldc_w 598
    //   1121: invokespecial 489	org/apache/http/message/BasicNameValuePair:<init>	(Ljava/lang/String;Ljava/lang/String;)V
    //   1124: invokeinterface 493 2 0
    //   1129: pop
    //   1130: aload 8
    //   1132: astore 10
    //   1134: aload 8
    //   1136: astore 9
    //   1138: new 62	java/lang/StringBuilder
    //   1141: dup
    //   1142: ldc_w 938
    //   1145: invokespecial 67	java/lang/StringBuilder:<init>	(Ljava/lang/String;)V
    //   1148: aload_3
    //   1149: invokevirtual 104	java/lang/StringBuilder:append	(Ljava/lang/String;)Ljava/lang/StringBuilder;
    //   1152: ldc_w 504
    //   1155: invokevirtual 104	java/lang/StringBuilder:append	(Ljava/lang/String;)Ljava/lang/StringBuilder;
    //   1158: aload 13
    //   1160: invokevirtual 104	java/lang/StringBuilder:append	(Ljava/lang/String;)Ljava/lang/StringBuilder;
    //   1163: ldc_w 506
    //   1166: invokevirtual 104	java/lang/StringBuilder:append	(Ljava/lang/String;)Ljava/lang/StringBuilder;
    //   1169: aload_2
    //   1170: invokevirtual 104	java/lang/StringBuilder:append	(Ljava/lang/String;)Ljava/lang/StringBuilder;
    //   1173: ldc_w 940
    //   1176: invokevirtual 104	java/lang/StringBuilder:append	(Ljava/lang/String;)Ljava/lang/StringBuilder;
    //   1179: astore_3
    //   1180: aload 6
    //   1182: ifnonnull +58 -> 1240
    //   1185: ldc -63
    //   1187: astore_2
    //   1188: aload 8
    //   1190: astore 10
    //   1192: aload 8
    //   1194: astore 9
    //   1196: aload_3
    //   1197: aload_2
    //   1198: invokevirtual 104	java/lang/StringBuilder:append	(Ljava/lang/String;)Ljava/lang/StringBuilder;
    //   1201: ldc_w 508
    //   1204: invokevirtual 104	java/lang/StringBuilder:append	(Ljava/lang/String;)Ljava/lang/StringBuilder;
    //   1207: aload_1
    //   1208: invokevirtual 104	java/lang/StringBuilder:append	(Ljava/lang/String;)Ljava/lang/StringBuilder;
    //   1211: ldc_w 952
    //   1214: invokevirtual 104	java/lang/StringBuilder:append	(Ljava/lang/String;)Ljava/lang/StringBuilder;
    //   1217: aload 11
    //   1219: invokevirtual 104	java/lang/StringBuilder:append	(Ljava/lang/String;)Ljava/lang/StringBuilder;
    //   1222: ldc_w 675
    //   1225: invokevirtual 104	java/lang/StringBuilder:append	(Ljava/lang/String;)Ljava/lang/StringBuilder;
    //   1228: aload 5
    //   1230: invokevirtual 104	java/lang/StringBuilder:append	(Ljava/lang/String;)Ljava/lang/StringBuilder;
    //   1233: invokevirtual 74	java/lang/StringBuilder:toString	()Ljava/lang/String;
    //   1236: astore_1
    //   1237: goto -688 -> 549
    //   1240: aload 8
    //   1242: astore 10
    //   1244: aload 8
    //   1246: astore 9
    //   1248: aload 6
    //   1250: invokevirtual 450	java/lang/String:trim	()Ljava/lang/String;
    //   1253: astore_2
    //   1254: goto -66 -> 1188
    //   1257: aload 8
    //   1259: astore 10
    //   1261: aload 8
    //   1263: astore 9
    //   1265: new 62	java/lang/StringBuilder
    //   1268: dup
    //   1269: ldc_w 938
    //   1272: invokespecial 67	java/lang/StringBuilder:<init>	(Ljava/lang/String;)V
    //   1275: aload_3
    //   1276: invokevirtual 104	java/lang/StringBuilder:append	(Ljava/lang/String;)Ljava/lang/StringBuilder;
    //   1279: ldc_w 504
    //   1282: invokevirtual 104	java/lang/StringBuilder:append	(Ljava/lang/String;)Ljava/lang/StringBuilder;
    //   1285: aload 13
    //   1287: invokevirtual 104	java/lang/StringBuilder:append	(Ljava/lang/String;)Ljava/lang/StringBuilder;
    //   1290: ldc_w 506
    //   1293: invokevirtual 104	java/lang/StringBuilder:append	(Ljava/lang/String;)Ljava/lang/StringBuilder;
    //   1296: aload_2
    //   1297: invokevirtual 104	java/lang/StringBuilder:append	(Ljava/lang/String;)Ljava/lang/StringBuilder;
    //   1300: ldc_w 940
    //   1303: invokevirtual 104	java/lang/StringBuilder:append	(Ljava/lang/String;)Ljava/lang/StringBuilder;
    //   1306: astore_3
    //   1307: aload 6
    //   1309: ifnonnull +58 -> 1367
    //   1312: ldc -63
    //   1314: astore_2
    //   1315: aload 8
    //   1317: astore 10
    //   1319: aload 8
    //   1321: astore 9
    //   1323: aload_3
    //   1324: aload_2
    //   1325: invokevirtual 104	java/lang/StringBuilder:append	(Ljava/lang/String;)Ljava/lang/StringBuilder;
    //   1328: ldc_w 508
    //   1331: invokevirtual 104	java/lang/StringBuilder:append	(Ljava/lang/String;)Ljava/lang/StringBuilder;
    //   1334: aload_1
    //   1335: invokevirtual 104	java/lang/StringBuilder:append	(Ljava/lang/String;)Ljava/lang/StringBuilder;
    //   1338: ldc_w 954
    //   1341: invokevirtual 104	java/lang/StringBuilder:append	(Ljava/lang/String;)Ljava/lang/StringBuilder;
    //   1344: aload 11
    //   1346: invokevirtual 104	java/lang/StringBuilder:append	(Ljava/lang/String;)Ljava/lang/StringBuilder;
    //   1349: ldc_w 675
    //   1352: invokevirtual 104	java/lang/StringBuilder:append	(Ljava/lang/String;)Ljava/lang/StringBuilder;
    //   1355: aload 5
    //   1357: invokevirtual 104	java/lang/StringBuilder:append	(Ljava/lang/String;)Ljava/lang/StringBuilder;
    //   1360: invokevirtual 74	java/lang/StringBuilder:toString	()Ljava/lang/String;
    //   1363: astore_1
    //   1364: goto -815 -> 549
    //   1367: aload 8
    //   1369: astore 10
    //   1371: aload 8
    //   1373: astore 9
    //   1375: aload 6
    //   1377: invokevirtual 450	java/lang/String:trim	()Ljava/lang/String;
    //   1380: astore_2
    //   1381: goto -66 -> 1315
    //   1384: iload 4
    //   1386: ifeq +148 -> 1534
    //   1389: aload 8
    //   1391: astore 10
    //   1393: aload 8
    //   1395: astore 9
    //   1397: aload 12
    //   1399: new 487	org/apache/http/message/BasicNameValuePair
    //   1402: dup
    //   1403: ldc_w 936
    //   1406: ldc_w 598
    //   1409: invokespecial 489	org/apache/http/message/BasicNameValuePair:<init>	(Ljava/lang/String;Ljava/lang/String;)V
    //   1412: invokeinterface 493 2 0
    //   1417: pop
    //   1418: aload 8
    //   1420: astore 10
    //   1422: aload 8
    //   1424: astore 9
    //   1426: new 62	java/lang/StringBuilder
    //   1429: dup
    //   1430: ldc_w 938
    //   1433: invokespecial 67	java/lang/StringBuilder:<init>	(Ljava/lang/String;)V
    //   1436: aload_3
    //   1437: invokevirtual 104	java/lang/StringBuilder:append	(Ljava/lang/String;)Ljava/lang/StringBuilder;
    //   1440: ldc_w 504
    //   1443: invokevirtual 104	java/lang/StringBuilder:append	(Ljava/lang/String;)Ljava/lang/StringBuilder;
    //   1446: aload 13
    //   1448: invokevirtual 104	java/lang/StringBuilder:append	(Ljava/lang/String;)Ljava/lang/StringBuilder;
    //   1451: ldc_w 506
    //   1454: invokevirtual 104	java/lang/StringBuilder:append	(Ljava/lang/String;)Ljava/lang/StringBuilder;
    //   1457: aload_2
    //   1458: invokevirtual 104	java/lang/StringBuilder:append	(Ljava/lang/String;)Ljava/lang/StringBuilder;
    //   1461: ldc_w 940
    //   1464: invokevirtual 104	java/lang/StringBuilder:append	(Ljava/lang/String;)Ljava/lang/StringBuilder;
    //   1467: astore_3
    //   1468: aload 6
    //   1470: ifnonnull +47 -> 1517
    //   1473: ldc -63
    //   1475: astore_2
    //   1476: aload 8
    //   1478: astore 10
    //   1480: aload 8
    //   1482: astore 9
    //   1484: aload_3
    //   1485: aload_2
    //   1486: invokevirtual 104	java/lang/StringBuilder:append	(Ljava/lang/String;)Ljava/lang/StringBuilder;
    //   1489: ldc_w 508
    //   1492: invokevirtual 104	java/lang/StringBuilder:append	(Ljava/lang/String;)Ljava/lang/StringBuilder;
    //   1495: aload_1
    //   1496: invokevirtual 104	java/lang/StringBuilder:append	(Ljava/lang/String;)Ljava/lang/StringBuilder;
    //   1499: ldc_w 942
    //   1502: invokevirtual 104	java/lang/StringBuilder:append	(Ljava/lang/String;)Ljava/lang/StringBuilder;
    //   1505: aload 5
    //   1507: invokevirtual 104	java/lang/StringBuilder:append	(Ljava/lang/String;)Ljava/lang/StringBuilder;
    //   1510: invokevirtual 74	java/lang/StringBuilder:toString	()Ljava/lang/String;
    //   1513: astore_1
    //   1514: goto -965 -> 549
    //   1517: aload 8
    //   1519: astore 10
    //   1521: aload 8
    //   1523: astore 9
    //   1525: aload 6
    //   1527: invokevirtual 450	java/lang/String:trim	()Ljava/lang/String;
    //   1530: astore_2
    //   1531: goto -55 -> 1476
    //   1534: aload 8
    //   1536: astore 10
    //   1538: aload 8
    //   1540: astore 9
    //   1542: new 62	java/lang/StringBuilder
    //   1545: dup
    //   1546: ldc_w 938
    //   1549: invokespecial 67	java/lang/StringBuilder:<init>	(Ljava/lang/String;)V
    //   1552: aload_3
    //   1553: invokevirtual 104	java/lang/StringBuilder:append	(Ljava/lang/String;)Ljava/lang/StringBuilder;
    //   1556: ldc_w 504
    //   1559: invokevirtual 104	java/lang/StringBuilder:append	(Ljava/lang/String;)Ljava/lang/StringBuilder;
    //   1562: aload 13
    //   1564: invokevirtual 104	java/lang/StringBuilder:append	(Ljava/lang/String;)Ljava/lang/StringBuilder;
    //   1567: ldc_w 506
    //   1570: invokevirtual 104	java/lang/StringBuilder:append	(Ljava/lang/String;)Ljava/lang/StringBuilder;
    //   1573: aload_2
    //   1574: invokevirtual 104	java/lang/StringBuilder:append	(Ljava/lang/String;)Ljava/lang/StringBuilder;
    //   1577: ldc_w 940
    //   1580: invokevirtual 104	java/lang/StringBuilder:append	(Ljava/lang/String;)Ljava/lang/StringBuilder;
    //   1583: astore_3
    //   1584: aload 6
    //   1586: ifnonnull +47 -> 1633
    //   1589: ldc -63
    //   1591: astore_2
    //   1592: aload 8
    //   1594: astore 10
    //   1596: aload 8
    //   1598: astore 9
    //   1600: aload_3
    //   1601: aload_2
    //   1602: invokevirtual 104	java/lang/StringBuilder:append	(Ljava/lang/String;)Ljava/lang/StringBuilder;
    //   1605: ldc_w 508
    //   1608: invokevirtual 104	java/lang/StringBuilder:append	(Ljava/lang/String;)Ljava/lang/StringBuilder;
    //   1611: aload_1
    //   1612: invokevirtual 104	java/lang/StringBuilder:append	(Ljava/lang/String;)Ljava/lang/StringBuilder;
    //   1615: ldc_w 675
    //   1618: invokevirtual 104	java/lang/StringBuilder:append	(Ljava/lang/String;)Ljava/lang/StringBuilder;
    //   1621: aload 5
    //   1623: invokevirtual 104	java/lang/StringBuilder:append	(Ljava/lang/String;)Ljava/lang/StringBuilder;
    //   1626: invokevirtual 74	java/lang/StringBuilder:toString	()Ljava/lang/String;
    //   1629: astore_1
    //   1630: goto -1081 -> 549
    //   1633: aload 8
    //   1635: astore 10
    //   1637: aload 8
    //   1639: astore 9
    //   1641: aload 6
    //   1643: invokevirtual 450	java/lang/String:trim	()Ljava/lang/String;
    //   1646: astore_2
    //   1647: goto -55 -> 1592
    //   1650: astore_1
    //   1651: aload 8
    //   1653: astore 10
    //   1655: aload 8
    //   1657: astore 9
    //   1659: new 79	com/arrownock/exception/ArrownockException
    //   1662: dup
    //   1663: aload_1
    //   1664: invokevirtual 580	java/lang/Exception:getMessage	()Ljava/lang/String;
    //   1667: sipush 2003
    //   1670: invokespecial 575	com/arrownock/exception/ArrownockException:<init>	(Ljava/lang/String;I)V
    //   1673: athrow
    //   1674: astore_1
    //   1675: aload 8
    //   1677: astore 10
    //   1679: aload 8
    //   1681: astore 9
    //   1683: new 79	com/arrownock/exception/ArrownockException
    //   1686: dup
    //   1687: aload_1
    //   1688: invokevirtual 579	java/io/IOException:getMessage	()Ljava/lang/String;
    //   1691: sipush 2003
    //   1694: invokespecial 575	com/arrownock/exception/ArrownockException:<init>	(Ljava/lang/String;I)V
    //   1697: athrow
    //   1698: astore_1
    //   1699: aload 10
    //   1701: astore 9
    //   1703: aload_1
    //   1704: instanceof 79
    //   1707: ifeq +186 -> 1893
    //   1710: aload 10
    //   1712: astore 9
    //   1714: aload_1
    //   1715: checkcast 79	com/arrownock/exception/ArrownockException
    //   1718: athrow
    //   1719: astore_1
    //   1720: aload 9
    //   1722: astore 8
    //   1724: aload 8
    //   1726: ifnull +8 -> 1734
    //   1729: aload 8
    //   1731: invokevirtual 350	java/net/HttpURLConnection:disconnect	()V
    //   1734: aload_1
    //   1735: athrow
    //   1736: aload 8
    //   1738: astore 10
    //   1740: aload 8
    //   1742: astore 9
    //   1744: new 79	com/arrownock/exception/ArrownockException
    //   1747: dup
    //   1748: ldc_w 956
    //   1751: sipush 2003
    //   1754: invokespecial 575	com/arrownock/exception/ArrownockException:<init>	(Ljava/lang/String;I)V
    //   1757: athrow
    //   1758: astore_1
    //   1759: aload 8
    //   1761: astore 10
    //   1763: aload 8
    //   1765: astore 9
    //   1767: new 79	com/arrownock/exception/ArrownockException
    //   1770: dup
    //   1771: aload_1
    //   1772: invokevirtual 578	org/json/JSONException:getMessage	()Ljava/lang/String;
    //   1775: sipush 2003
    //   1778: invokespecial 575	com/arrownock/exception/ArrownockException:<init>	(Ljava/lang/String;I)V
    //   1781: athrow
    //   1782: aload 8
    //   1784: astore 10
    //   1786: aload 8
    //   1788: astore 9
    //   1790: new 79	com/arrownock/exception/ArrownockException
    //   1793: dup
    //   1794: ldc_w 958
    //   1797: sipush 2003
    //   1800: invokespecial 575	com/arrownock/exception/ArrownockException:<init>	(Ljava/lang/String;I)V
    //   1803: athrow
    //   1804: aload 8
    //   1806: astore 10
    //   1808: aload 8
    //   1810: astore 9
    //   1812: new 317	java/io/BufferedInputStream
    //   1815: dup
    //   1816: aload 8
    //   1818: invokevirtual 355	java/net/HttpURLConnection:getErrorStream	()Ljava/io/InputStream;
    //   1821: invokespecial 322	java/io/BufferedInputStream:<init>	(Ljava/io/InputStream;)V
    //   1824: invokestatic 324	df:a	(Ljava/io/InputStream;)Ljava/lang/String;
    //   1827: astore_1
    //   1828: iload 7
    //   1830: sipush 503
    //   1833: if_icmpne +21 -> 1854
    //   1836: ldc_w 960
    //   1839: astore_2
    //   1840: aload 8
    //   1842: ifnull -986 -> 856
    //   1845: aload 8
    //   1847: invokevirtual 350	java/net/HttpURLConnection:disconnect	()V
    //   1850: ldc_w 960
    //   1853: areturn
    //   1854: aload 8
    //   1856: astore 10
    //   1858: aload 8
    //   1860: astore 9
    //   1862: new 79	com/arrownock/exception/ArrownockException
    //   1865: dup
    //   1866: new 315	org/json/JSONObject
    //   1869: dup
    //   1870: aload_1
    //   1871: invokespecial 325	org/json/JSONObject:<init>	(Ljava/lang/String;)V
    //   1874: ldc_w 568
    //   1877: invokevirtual 572	org/json/JSONObject:getJSONObject	(Ljava/lang/String;)Lorg/json/JSONObject;
    //   1880: ldc_w 357
    //   1883: invokevirtual 331	org/json/JSONObject:getString	(Ljava/lang/String;)Ljava/lang/String;
    //   1886: sipush 2003
    //   1889: invokespecial 575	com/arrownock/exception/ArrownockException:<init>	(Ljava/lang/String;I)V
    //   1892: athrow
    //   1893: aload 10
    //   1895: astore 9
    //   1897: new 79	com/arrownock/exception/ArrownockException
    //   1900: dup
    //   1901: aload_1
    //   1902: invokevirtual 580	java/lang/Exception:getMessage	()Ljava/lang/String;
    //   1905: sipush 2003
    //   1908: invokespecial 575	com/arrownock/exception/ArrownockException:<init>	(Ljava/lang/String;I)V
    //   1911: athrow
    //   1912: astore_1
    //   1913: goto -189 -> 1724
    //   1916: astore_1
    //   1917: aload 8
    //   1919: astore 10
    //   1921: goto -222 -> 1699
    // Local variable table:
    //   start	length	slot	name	signature
    //   0	1924	0	this	df
    //   0	1924	1	paramString1	String
    //   0	1924	2	paramString2	String
    //   0	1924	3	paramString3	String
    //   0	1924	4	paramBoolean	boolean
    //   0	1924	5	paramString4	String
    //   0	1924	6	paramString5	String
    //   719	1115	7	i	int
    //   4	1914	8	localObject1	Object
    //   12	1884	9	localObject2	Object
    //   8	1912	10	localObject3	Object
    //   1	1344	11	str1	String
    //   214	1184	12	localArrayList	java.util.ArrayList
    //   197	1366	13	str2	String
    // Exception table:
    //   from	to	target	type
    //   553	571	1650	java/lang/Exception
    //   575	582	1650	java/lang/Exception
    //   586	591	1650	java/lang/Exception
    //   595	625	1650	java/lang/Exception
    //   174	199	1674	java/io/IOException
    //   207	216	1674	java/io/IOException
    //   224	243	1674	java/io/IOException
    //   251	271	1674	java/io/IOException
    //   279	299	1674	java/io/IOException
    //   307	326	1674	java/io/IOException
    //   343	363	1674	java/io/IOException
    //   371	380	1674	java/io/IOException
    //   388	401	1674	java/io/IOException
    //   409	419	1674	java/io/IOException
    //   432	453	1674	java/io/IOException
    //   461	503	1674	java/io/IOException
    //   519	549	1674	java/io/IOException
    //   553	571	1674	java/io/IOException
    //   575	582	1674	java/io/IOException
    //   586	591	1674	java/io/IOException
    //   595	625	1674	java/io/IOException
    //   633	639	1674	java/io/IOException
    //   647	665	1674	java/io/IOException
    //   673	682	1674	java/io/IOException
    //   690	694	1674	java/io/IOException
    //   702	706	1674	java/io/IOException
    //   714	721	1674	java/io/IOException
    //   737	766	1674	java/io/IOException
    //   778	788	1674	java/io/IOException
    //   796	804	1674	java/io/IOException
    //   816	826	1674	java/io/IOException
    //   834	842	1674	java/io/IOException
    //   925	932	1674	java/io/IOException
    //   943	949	1674	java/io/IOException
    //   960	1002	1674	java/io/IOException
    //   1018	1048	1674	java/io/IOException
    //   1059	1065	1674	java/io/IOException
    //   1076	1096	1674	java/io/IOException
    //   1109	1130	1674	java/io/IOException
    //   1138	1180	1674	java/io/IOException
    //   1196	1237	1674	java/io/IOException
    //   1248	1254	1674	java/io/IOException
    //   1265	1307	1674	java/io/IOException
    //   1323	1364	1674	java/io/IOException
    //   1375	1381	1674	java/io/IOException
    //   1397	1418	1674	java/io/IOException
    //   1426	1468	1674	java/io/IOException
    //   1484	1514	1674	java/io/IOException
    //   1525	1531	1674	java/io/IOException
    //   1542	1584	1674	java/io/IOException
    //   1600	1630	1674	java/io/IOException
    //   1641	1647	1674	java/io/IOException
    //   1659	1674	1674	java/io/IOException
    //   1744	1758	1674	java/io/IOException
    //   1767	1782	1674	java/io/IOException
    //   1790	1804	1674	java/io/IOException
    //   1812	1828	1674	java/io/IOException
    //   1862	1893	1674	java/io/IOException
    //   14	27	1698	java/lang/Exception
    //   35	83	1698	java/lang/Exception
    //   130	138	1698	java/lang/Exception
    //   146	152	1698	java/lang/Exception
    //   160	166	1698	java/lang/Exception
    //   174	199	1698	java/lang/Exception
    //   207	216	1698	java/lang/Exception
    //   224	243	1698	java/lang/Exception
    //   251	271	1698	java/lang/Exception
    //   279	299	1698	java/lang/Exception
    //   307	326	1698	java/lang/Exception
    //   343	363	1698	java/lang/Exception
    //   371	380	1698	java/lang/Exception
    //   388	401	1698	java/lang/Exception
    //   409	419	1698	java/lang/Exception
    //   432	453	1698	java/lang/Exception
    //   461	503	1698	java/lang/Exception
    //   519	549	1698	java/lang/Exception
    //   633	639	1698	java/lang/Exception
    //   647	665	1698	java/lang/Exception
    //   673	682	1698	java/lang/Exception
    //   690	694	1698	java/lang/Exception
    //   702	706	1698	java/lang/Exception
    //   714	721	1698	java/lang/Exception
    //   737	766	1698	java/lang/Exception
    //   778	788	1698	java/lang/Exception
    //   796	804	1698	java/lang/Exception
    //   816	826	1698	java/lang/Exception
    //   834	842	1698	java/lang/Exception
    //   866	914	1698	java/lang/Exception
    //   925	932	1698	java/lang/Exception
    //   943	949	1698	java/lang/Exception
    //   960	1002	1698	java/lang/Exception
    //   1018	1048	1698	java/lang/Exception
    //   1059	1065	1698	java/lang/Exception
    //   1076	1096	1698	java/lang/Exception
    //   1109	1130	1698	java/lang/Exception
    //   1138	1180	1698	java/lang/Exception
    //   1196	1237	1698	java/lang/Exception
    //   1248	1254	1698	java/lang/Exception
    //   1265	1307	1698	java/lang/Exception
    //   1323	1364	1698	java/lang/Exception
    //   1375	1381	1698	java/lang/Exception
    //   1397	1418	1698	java/lang/Exception
    //   1426	1468	1698	java/lang/Exception
    //   1484	1514	1698	java/lang/Exception
    //   1525	1531	1698	java/lang/Exception
    //   1542	1584	1698	java/lang/Exception
    //   1600	1630	1698	java/lang/Exception
    //   1641	1647	1698	java/lang/Exception
    //   1659	1674	1698	java/lang/Exception
    //   1683	1698	1698	java/lang/Exception
    //   1744	1758	1698	java/lang/Exception
    //   1767	1782	1698	java/lang/Exception
    //   1790	1804	1698	java/lang/Exception
    //   1812	1828	1698	java/lang/Exception
    //   1862	1893	1698	java/lang/Exception
    //   14	27	1719	finally
    //   35	83	1719	finally
    //   130	138	1719	finally
    //   146	152	1719	finally
    //   160	166	1719	finally
    //   174	199	1719	finally
    //   207	216	1719	finally
    //   224	243	1719	finally
    //   251	271	1719	finally
    //   279	299	1719	finally
    //   307	326	1719	finally
    //   343	363	1719	finally
    //   371	380	1719	finally
    //   388	401	1719	finally
    //   409	419	1719	finally
    //   432	453	1719	finally
    //   461	503	1719	finally
    //   519	549	1719	finally
    //   553	571	1719	finally
    //   575	582	1719	finally
    //   586	591	1719	finally
    //   595	625	1719	finally
    //   633	639	1719	finally
    //   647	665	1719	finally
    //   673	682	1719	finally
    //   690	694	1719	finally
    //   702	706	1719	finally
    //   714	721	1719	finally
    //   737	766	1719	finally
    //   778	788	1719	finally
    //   796	804	1719	finally
    //   816	826	1719	finally
    //   834	842	1719	finally
    //   866	914	1719	finally
    //   925	932	1719	finally
    //   943	949	1719	finally
    //   960	1002	1719	finally
    //   1018	1048	1719	finally
    //   1059	1065	1719	finally
    //   1076	1096	1719	finally
    //   1109	1130	1719	finally
    //   1138	1180	1719	finally
    //   1196	1237	1719	finally
    //   1248	1254	1719	finally
    //   1265	1307	1719	finally
    //   1323	1364	1719	finally
    //   1375	1381	1719	finally
    //   1397	1418	1719	finally
    //   1426	1468	1719	finally
    //   1484	1514	1719	finally
    //   1525	1531	1719	finally
    //   1542	1584	1719	finally
    //   1600	1630	1719	finally
    //   1641	1647	1719	finally
    //   1659	1674	1719	finally
    //   1683	1698	1719	finally
    //   1703	1710	1719	finally
    //   1714	1719	1719	finally
    //   1744	1758	1719	finally
    //   1767	1782	1719	finally
    //   1790	1804	1719	finally
    //   1812	1828	1719	finally
    //   1862	1893	1719	finally
    //   1897	1912	1719	finally
    //   737	766	1758	org/json/JSONException
    //   778	788	1758	org/json/JSONException
    //   796	804	1758	org/json/JSONException
    //   816	826	1758	org/json/JSONException
    //   834	842	1758	org/json/JSONException
    //   1744	1758	1758	org/json/JSONException
    //   1790	1804	1758	org/json/JSONException
    //   1812	1828	1758	org/json/JSONException
    //   1862	1893	1758	org/json/JSONException
    //   83	122	1912	finally
    //   83	122	1916	java/lang/Exception
  }
  
  /* Error */
  public final org.json.JSONArray a(String paramString)
    throws ArrownockException
  {
    // Byte code:
    //   0: aconst_null
    //   1: astore 7
    //   3: aconst_null
    //   4: astore 8
    //   6: aconst_null
    //   7: astore 6
    //   9: aload 6
    //   11: astore 5
    //   13: aload 7
    //   15: astore 4
    //   17: aload 8
    //   19: astore_3
    //   20: new 464	java/text/SimpleDateFormat
    //   23: dup
    //   24: ldc_w 466
    //   27: getstatic 472	java/util/Locale:US	Ljava/util/Locale;
    //   30: invokespecial 475	java/text/SimpleDateFormat:<init>	(Ljava/lang/String;Ljava/util/Locale;)V
    //   33: new 477	java/util/Date
    //   36: dup
    //   37: invokespecial 478	java/util/Date:<init>	()V
    //   40: invokevirtual 482	java/text/SimpleDateFormat:format	(Ljava/util/Date;)Ljava/lang/String;
    //   43: astore 10
    //   45: aload 6
    //   47: astore 5
    //   49: aload 7
    //   51: astore 4
    //   53: aload 8
    //   55: astore_3
    //   56: new 484	java/util/ArrayList
    //   59: dup
    //   60: invokespecial 485	java/util/ArrayList:<init>	()V
    //   63: astore 9
    //   65: aload 6
    //   67: astore 5
    //   69: aload 7
    //   71: astore 4
    //   73: aload 8
    //   75: astore_3
    //   76: aload 9
    //   78: new 487	org/apache/http/message/BasicNameValuePair
    //   81: dup
    //   82: ldc_w 347
    //   85: aload_1
    //   86: invokespecial 489	org/apache/http/message/BasicNameValuePair:<init>	(Ljava/lang/String;Ljava/lang/String;)V
    //   89: invokeinterface 493 2 0
    //   94: pop
    //   95: aload 6
    //   97: astore 5
    //   99: aload 7
    //   101: astore 4
    //   103: aload 8
    //   105: astore_3
    //   106: aload 9
    //   108: new 487	org/apache/http/message/BasicNameValuePair
    //   111: dup
    //   112: ldc_w 495
    //   115: aload 10
    //   117: invokespecial 489	org/apache/http/message/BasicNameValuePair:<init>	(Ljava/lang/String;Ljava/lang/String;)V
    //   120: invokeinterface 493 2 0
    //   125: pop
    //   126: aload 6
    //   128: astore 5
    //   130: aload 7
    //   132: astore 4
    //   134: aload 8
    //   136: astore_3
    //   137: new 62	java/lang/StringBuilder
    //   140: dup
    //   141: ldc_w 963
    //   144: invokespecial 67	java/lang/StringBuilder:<init>	(Ljava/lang/String;)V
    //   147: aload 10
    //   149: invokevirtual 104	java/lang/StringBuilder:append	(Ljava/lang/String;)Ljava/lang/StringBuilder;
    //   152: ldc_w 965
    //   155: invokevirtual 104	java/lang/StringBuilder:append	(Ljava/lang/String;)Ljava/lang/StringBuilder;
    //   158: aload_1
    //   159: invokevirtual 104	java/lang/StringBuilder:append	(Ljava/lang/String;)Ljava/lang/StringBuilder;
    //   162: invokevirtual 74	java/lang/StringBuilder:toString	()Ljava/lang/String;
    //   165: astore_1
    //   166: aload 6
    //   168: astore 5
    //   170: aload 8
    //   172: astore_3
    //   173: new 510	javax/crypto/spec/SecretKeySpec
    //   176: dup
    //   177: aload_0
    //   178: invokespecial 513	df:e	()Ljava/lang/String;
    //   181: invokevirtual 517	java/lang/String:getBytes	()[B
    //   184: ldc_w 519
    //   187: invokespecial 522	javax/crypto/spec/SecretKeySpec:<init>	([BLjava/lang/String;)V
    //   190: astore 4
    //   192: aload 6
    //   194: astore 5
    //   196: aload 8
    //   198: astore_3
    //   199: ldc_w 519
    //   202: invokestatic 527	javax/crypto/Mac:getInstance	(Ljava/lang/String;)Ljavax/crypto/Mac;
    //   205: astore 10
    //   207: aload 6
    //   209: astore 5
    //   211: aload 8
    //   213: astore_3
    //   214: aload 10
    //   216: aload 4
    //   218: invokevirtual 531	javax/crypto/Mac:init	(Ljava/security/Key;)V
    //   221: aload 6
    //   223: astore 5
    //   225: aload 8
    //   227: astore_3
    //   228: aload 9
    //   230: new 487	org/apache/http/message/BasicNameValuePair
    //   233: dup
    //   234: ldc_w 533
    //   237: aload 10
    //   239: aload_1
    //   240: invokevirtual 517	java/lang/String:getBytes	()[B
    //   243: invokevirtual 537	javax/crypto/Mac:doFinal	([B)[B
    //   246: iconst_2
    //   247: invokestatic 543	android/util/Base64:encodeToString	([BI)Ljava/lang/String;
    //   250: invokespecial 489	org/apache/http/message/BasicNameValuePair:<init>	(Ljava/lang/String;Ljava/lang/String;)V
    //   253: invokeinterface 493 2 0
    //   258: pop
    //   259: aload 6
    //   261: astore 5
    //   263: aload 7
    //   265: astore 4
    //   267: aload 8
    //   269: astore_3
    //   270: aload_0
    //   271: getfield 34	df:jdField_a_of_type_AndroidContentContext	Landroid/content/Context;
    //   274: invokestatic 267	com/arrownock/push/AnPush:getInstance	(Landroid/content/Context;)Lcom/arrownock/push/AnPush;
    //   277: invokevirtual 270	com/arrownock/push/AnPush:isSecureConnection	()Z
    //   280: ifeq +285 -> 565
    //   283: aload 6
    //   285: astore 5
    //   287: aload 7
    //   289: astore 4
    //   291: aload 8
    //   293: astore_3
    //   294: new 272	java/net/URL
    //   297: dup
    //   298: new 62	java/lang/StringBuilder
    //   301: dup
    //   302: ldc_w 274
    //   305: invokespecial 67	java/lang/StringBuilder:<init>	(Ljava/lang/String;)V
    //   308: aload_0
    //   309: invokespecial 445	df:c	()Ljava/lang/String;
    //   312: invokevirtual 104	java/lang/StringBuilder:append	(Ljava/lang/String;)Ljava/lang/StringBuilder;
    //   315: ldc_w 967
    //   318: invokevirtual 104	java/lang/StringBuilder:append	(Ljava/lang/String;)Ljava/lang/StringBuilder;
    //   321: aload 9
    //   323: invokestatic 559	df:a	(Ljava/util/List;)Ljava/lang/String;
    //   326: invokevirtual 104	java/lang/StringBuilder:append	(Ljava/lang/String;)Ljava/lang/StringBuilder;
    //   329: invokevirtual 74	java/lang/StringBuilder:toString	()Ljava/lang/String;
    //   332: invokespecial 275	java/net/URL:<init>	(Ljava/lang/String;)V
    //   335: invokevirtual 279	java/net/URL:openConnection	()Ljava/net/URLConnection;
    //   338: checkcast 281	javax/net/ssl/HttpsURLConnection
    //   341: astore_1
    //   342: aload_1
    //   343: checkcast 281	javax/net/ssl/HttpsURLConnection
    //   346: getstatic 29	df:jdField_a_of_type_JavaxNetSslHostnameVerifier	Ljavax/net/ssl/HostnameVerifier;
    //   349: invokevirtual 285	javax/net/ssl/HttpsURLConnection:setHostnameVerifier	(Ljavax/net/ssl/HostnameVerifier;)V
    //   352: aload_1
    //   353: checkcast 281	javax/net/ssl/HttpsURLConnection
    //   356: aload_0
    //   357: invokespecial 288	df:f	()Ljava/lang/String;
    //   360: aload_0
    //   361: invokespecial 291	df:g	()Ljava/lang/String;
    //   364: aload_0
    //   365: invokespecial 294	df:h	()Ljava/lang/String;
    //   368: ldc -63
    //   370: ldc_w 296
    //   373: invokestatic 301	at:a	(Ljava/lang/String;Ljava/lang/String;Ljava/lang/String;Ljava/lang/String;Ljava/lang/String;)Ljavax/net/ssl/SSLSocketFactory;
    //   376: invokevirtual 305	javax/net/ssl/HttpsURLConnection:setSSLSocketFactory	(Ljavax/net/ssl/SSLSocketFactory;)V
    //   379: aload_1
    //   380: astore 5
    //   382: aload_1
    //   383: astore 4
    //   385: aload_1
    //   386: astore_3
    //   387: aload_1
    //   388: ldc_w 968
    //   391: invokevirtual 972	java/net/HttpURLConnection:setConnectTimeout	(I)V
    //   394: aload_1
    //   395: astore 5
    //   397: aload_1
    //   398: astore 4
    //   400: aload_1
    //   401: astore_3
    //   402: aload_1
    //   403: invokevirtual 310	java/net/HttpURLConnection:connect	()V
    //   406: aload_1
    //   407: astore 5
    //   409: aload_1
    //   410: astore 4
    //   412: aload_1
    //   413: astore_3
    //   414: aload_1
    //   415: invokevirtual 313	java/net/HttpURLConnection:getResponseCode	()I
    //   418: istore_2
    //   419: iload_2
    //   420: sipush 200
    //   423: if_icmpne +204 -> 627
    //   426: aload_1
    //   427: astore 5
    //   429: aload_1
    //   430: astore 4
    //   432: aload_1
    //   433: astore_3
    //   434: new 315	org/json/JSONObject
    //   437: dup
    //   438: new 317	java/io/BufferedInputStream
    //   441: dup
    //   442: aload_1
    //   443: invokevirtual 321	java/net/HttpURLConnection:getInputStream	()Ljava/io/InputStream;
    //   446: invokespecial 322	java/io/BufferedInputStream:<init>	(Ljava/io/InputStream;)V
    //   449: invokestatic 324	df:a	(Ljava/io/InputStream;)Ljava/lang/String;
    //   452: invokespecial 325	org/json/JSONObject:<init>	(Ljava/lang/String;)V
    //   455: ldc_w 944
    //   458: invokevirtual 572	org/json/JSONObject:getJSONObject	(Ljava/lang/String;)Lorg/json/JSONObject;
    //   461: ldc_w 974
    //   464: invokevirtual 977	org/json/JSONObject:getJSONArray	(Ljava/lang/String;)Lorg/json/JSONArray;
    //   467: astore 6
    //   469: aload_1
    //   470: ifnull +7 -> 477
    //   473: aload_1
    //   474: invokevirtual 350	java/net/HttpURLConnection:disconnect	()V
    //   477: aload 6
    //   479: areturn
    //   480: astore_1
    //   481: aload 6
    //   483: astore 5
    //   485: aload 7
    //   487: astore 4
    //   489: aload 8
    //   491: astore_3
    //   492: new 79	com/arrownock/exception/ArrownockException
    //   495: dup
    //   496: aload_1
    //   497: invokevirtual 580	java/lang/Exception:getMessage	()Ljava/lang/String;
    //   500: sipush 2010
    //   503: invokespecial 575	com/arrownock/exception/ArrownockException:<init>	(Ljava/lang/String;I)V
    //   506: athrow
    //   507: astore_1
    //   508: aload 5
    //   510: astore_3
    //   511: aload_3
    //   512: astore 4
    //   514: new 79	com/arrownock/exception/ArrownockException
    //   517: dup
    //   518: aload_1
    //   519: invokevirtual 579	java/io/IOException:getMessage	()Ljava/lang/String;
    //   522: sipush 2010
    //   525: invokespecial 575	com/arrownock/exception/ArrownockException:<init>	(Ljava/lang/String;I)V
    //   528: athrow
    //   529: astore_1
    //   530: aload 4
    //   532: astore_3
    //   533: aload_1
    //   534: instanceof 79
    //   537: ifeq +168 -> 705
    //   540: aload 4
    //   542: astore_3
    //   543: aload_1
    //   544: checkcast 79	com/arrownock/exception/ArrownockException
    //   547: athrow
    //   548: astore 4
    //   550: aload_3
    //   551: astore_1
    //   552: aload 4
    //   554: astore_3
    //   555: aload_1
    //   556: ifnull +7 -> 563
    //   559: aload_1
    //   560: invokevirtual 350	java/net/HttpURLConnection:disconnect	()V
    //   563: aload_3
    //   564: athrow
    //   565: aload 6
    //   567: astore 5
    //   569: aload 7
    //   571: astore 4
    //   573: aload 8
    //   575: astore_3
    //   576: new 272	java/net/URL
    //   579: dup
    //   580: new 62	java/lang/StringBuilder
    //   583: dup
    //   584: ldc_w 352
    //   587: invokespecial 67	java/lang/StringBuilder:<init>	(Ljava/lang/String;)V
    //   590: aload_0
    //   591: invokespecial 445	df:c	()Ljava/lang/String;
    //   594: invokevirtual 104	java/lang/StringBuilder:append	(Ljava/lang/String;)Ljava/lang/StringBuilder;
    //   597: ldc_w 967
    //   600: invokevirtual 104	java/lang/StringBuilder:append	(Ljava/lang/String;)Ljava/lang/StringBuilder;
    //   603: aload 9
    //   605: invokestatic 559	df:a	(Ljava/util/List;)Ljava/lang/String;
    //   608: invokevirtual 104	java/lang/StringBuilder:append	(Ljava/lang/String;)Ljava/lang/StringBuilder;
    //   611: invokevirtual 74	java/lang/StringBuilder:toString	()Ljava/lang/String;
    //   614: invokespecial 275	java/net/URL:<init>	(Ljava/lang/String;)V
    //   617: invokevirtual 279	java/net/URL:openConnection	()Ljava/net/URLConnection;
    //   620: checkcast 307	java/net/HttpURLConnection
    //   623: astore_1
    //   624: goto -245 -> 379
    //   627: aload_1
    //   628: astore 5
    //   630: aload_1
    //   631: astore 4
    //   633: aload_1
    //   634: astore_3
    //   635: new 79	com/arrownock/exception/ArrownockException
    //   638: dup
    //   639: new 315	org/json/JSONObject
    //   642: dup
    //   643: new 317	java/io/BufferedInputStream
    //   646: dup
    //   647: aload_1
    //   648: invokevirtual 355	java/net/HttpURLConnection:getErrorStream	()Ljava/io/InputStream;
    //   651: invokespecial 322	java/io/BufferedInputStream:<init>	(Ljava/io/InputStream;)V
    //   654: invokestatic 324	df:a	(Ljava/io/InputStream;)Ljava/lang/String;
    //   657: invokespecial 325	org/json/JSONObject:<init>	(Ljava/lang/String;)V
    //   660: ldc_w 568
    //   663: invokevirtual 572	org/json/JSONObject:getJSONObject	(Ljava/lang/String;)Lorg/json/JSONObject;
    //   666: ldc_w 357
    //   669: invokevirtual 331	org/json/JSONObject:getString	(Ljava/lang/String;)Ljava/lang/String;
    //   672: sipush 2010
    //   675: invokespecial 575	com/arrownock/exception/ArrownockException:<init>	(Ljava/lang/String;I)V
    //   678: athrow
    //   679: astore 6
    //   681: aload_1
    //   682: astore 5
    //   684: aload_1
    //   685: astore 4
    //   687: aload_1
    //   688: astore_3
    //   689: new 79	com/arrownock/exception/ArrownockException
    //   692: dup
    //   693: aload 6
    //   695: invokevirtual 578	org/json/JSONException:getMessage	()Ljava/lang/String;
    //   698: sipush 2010
    //   701: invokespecial 575	com/arrownock/exception/ArrownockException:<init>	(Ljava/lang/String;I)V
    //   704: athrow
    //   705: aload 4
    //   707: astore_3
    //   708: new 79	com/arrownock/exception/ArrownockException
    //   711: dup
    //   712: aload_1
    //   713: invokevirtual 580	java/lang/Exception:getMessage	()Ljava/lang/String;
    //   716: sipush 2010
    //   719: invokespecial 575	com/arrownock/exception/ArrownockException:<init>	(Ljava/lang/String;I)V
    //   722: athrow
    //   723: astore_3
    //   724: goto -169 -> 555
    //   727: astore_3
    //   728: aload_1
    //   729: astore 4
    //   731: aload_3
    //   732: astore_1
    //   733: goto -203 -> 530
    //   736: astore 4
    //   738: aload_1
    //   739: astore_3
    //   740: aload 4
    //   742: astore_1
    //   743: goto -232 -> 511
    // Local variable table:
    //   start	length	slot	name	signature
    //   0	746	0	this	df
    //   0	746	1	paramString	String
    //   418	6	2	i	int
    //   19	689	3	localObject1	Object
    //   723	1	3	localObject2	Object
    //   727	5	3	localException	Exception
    //   739	1	3	str	String
    //   15	526	4	localObject3	Object
    //   548	5	4	localObject4	Object
    //   571	159	4	localObject5	Object
    //   736	5	4	localIOException	IOException
    //   11	672	5	localObject6	Object
    //   7	559	6	localJSONArray	org.json.JSONArray
    //   679	15	6	localJSONException	org.json.JSONException
    //   1	569	7	localObject7	Object
    //   4	570	8	localObject8	Object
    //   63	541	9	localArrayList	java.util.ArrayList
    //   43	195	10	localObject9	Object
    // Exception table:
    //   from	to	target	type
    //   173	192	480	java/lang/Exception
    //   199	207	480	java/lang/Exception
    //   214	221	480	java/lang/Exception
    //   228	259	480	java/lang/Exception
    //   20	45	507	java/io/IOException
    //   56	65	507	java/io/IOException
    //   76	95	507	java/io/IOException
    //   106	126	507	java/io/IOException
    //   137	166	507	java/io/IOException
    //   173	192	507	java/io/IOException
    //   199	207	507	java/io/IOException
    //   214	221	507	java/io/IOException
    //   228	259	507	java/io/IOException
    //   270	283	507	java/io/IOException
    //   294	342	507	java/io/IOException
    //   387	394	507	java/io/IOException
    //   402	406	507	java/io/IOException
    //   414	419	507	java/io/IOException
    //   434	469	507	java/io/IOException
    //   492	507	507	java/io/IOException
    //   576	624	507	java/io/IOException
    //   635	679	507	java/io/IOException
    //   689	705	507	java/io/IOException
    //   20	45	529	java/lang/Exception
    //   56	65	529	java/lang/Exception
    //   76	95	529	java/lang/Exception
    //   106	126	529	java/lang/Exception
    //   137	166	529	java/lang/Exception
    //   270	283	529	java/lang/Exception
    //   294	342	529	java/lang/Exception
    //   387	394	529	java/lang/Exception
    //   402	406	529	java/lang/Exception
    //   414	419	529	java/lang/Exception
    //   434	469	529	java/lang/Exception
    //   492	507	529	java/lang/Exception
    //   514	529	529	java/lang/Exception
    //   576	624	529	java/lang/Exception
    //   635	679	529	java/lang/Exception
    //   689	705	529	java/lang/Exception
    //   20	45	548	finally
    //   56	65	548	finally
    //   76	95	548	finally
    //   106	126	548	finally
    //   137	166	548	finally
    //   173	192	548	finally
    //   199	207	548	finally
    //   214	221	548	finally
    //   228	259	548	finally
    //   270	283	548	finally
    //   294	342	548	finally
    //   387	394	548	finally
    //   402	406	548	finally
    //   414	419	548	finally
    //   434	469	548	finally
    //   492	507	548	finally
    //   514	529	548	finally
    //   533	540	548	finally
    //   543	548	548	finally
    //   576	624	548	finally
    //   635	679	548	finally
    //   689	705	548	finally
    //   708	723	548	finally
    //   434	469	679	org/json/JSONException
    //   635	679	679	org/json/JSONException
    //   342	379	723	finally
    //   342	379	727	java/lang/Exception
    //   342	379	736	java/io/IOException
  }
  
  public final void a()
    throws ArrownockException
  {
    Object localObject1 = jdField_a_of_type_AndroidContentContext.getSharedPreferences(PushService.LOG_TAG, 0);
    int i = ((SharedPreferences)localObject1).getInt("pushScheduledHour", -1);
    int j = ((SharedPreferences)localObject1).getInt("pushScheduledMinue", -1);
    long l2 = ((SharedPreferences)localObject1).getLong("pushScheduledDuration", -1L);
    Object localObject2;
    long l3;
    long l4;
    long l5;
    if ((i != -1) && (j != -1) && (l2 != -1L))
    {
      localObject1 = Calendar.getInstance(TimeZone.getTimeZone("GMT"));
      ((Calendar)localObject1).set(11, i);
      ((Calendar)localObject1).set(12, j);
      ((Calendar)localObject1).set(13, 0);
      localObject2 = Calendar.getInstance();
      l1 = ((Calendar)localObject1).getTime().getTime();
      l3 = ((Calendar)localObject2).getTime().getTime();
      l4 = l3 + 86400000L;
      l5 = l1 + l2;
      if (((l1 > l3) || (l5 <= l3)) && ((l1 > l4) || (l5 <= l4))) {}
    }
    else
    {
      for (;;)
      {
        try
        {
          if (AnPush.getInstance(jdField_a_of_type_AndroidContentContext).a())
          {
            localObject1 = new Intent();
            ((Intent)localObject1).setClass(jdField_a_of_type_AndroidContentContext, PushService.class);
            ((Intent)localObject1).setAction("AN.STOP");
            localObject1 = PendingIntent.getService(jdField_a_of_type_AndroidContentContext, 0, (Intent)localObject1, 0);
            ((AlarmManager)jdField_a_of_type_AndroidContentContext.getSystemService("alarm")).set(0, System.currentTimeMillis() - 1L, (PendingIntent)localObject1);
          }
          if (l1 < l3)
          {
            l1 = l5 - l3;
            l3 = l1 - l2 + 86400000L;
            l2 = l1;
            l1 = l3;
            Log.d(jdField_a_of_type_JavaLangString, "Stop connection in " + l1 / 1000L + " seconds ....");
            localObject1 = new Intent();
            ((Intent)localObject1).setClass(jdField_a_of_type_AndroidContentContext, PushService.class);
            ((Intent)localObject1).setAction("AN.STOP");
            localObject2 = PendingIntent.getService(jdField_a_of_type_AndroidContentContext, 0, (Intent)localObject1, 0);
            localObject1 = (AlarmManager)jdField_a_of_type_AndroidContentContext.getSystemService("alarm");
            ((AlarmManager)localObject1).setRepeating(0, l1 + System.currentTimeMillis(), 86400000L, (PendingIntent)localObject2);
            Log.d(jdField_a_of_type_JavaLangString, "Start connection in " + l2 / 1000L + " seconds ....");
            localObject2 = new Intent();
            ((Intent)localObject2).setClass(jdField_a_of_type_AndroidContentContext, PushService.class);
            ((Intent)localObject2).setAction("AN.START");
            localObject2 = PendingIntent.getService(jdField_a_of_type_AndroidContentContext, 0, (Intent)localObject2, 0);
            ((AlarmManager)localObject1).setRepeating(0, System.currentTimeMillis() + l2, 86400000L, (PendingIntent)localObject2);
            return;
          }
        }
        catch (ArrownockException localArrownockException)
        {
          throw localArrownockException;
        }
        l1 = l5 - l4;
      }
    }
    if (l1 < l3) {}
    for (long l1 = 86400000L + l1 - l3;; l1 -= l3)
    {
      l2 = l1 + l2;
      break;
    }
  }
  
  public final void a(Context paramContext, String paramString1, String paramString2, int paramInt, String paramString3, IAnPushRegisterAnIdCallback paramIAnPushRegisterAnIdCallback)
  {
    bk.a().a(jdField_a_of_type_JavaLangString, "try_time=" + paramInt + " type=" + paramString2);
    String str = a("hasAlreadyRegistered", "no");
    bk.a().a(jdField_a_of_type_JavaLangString, "hasAlreadyRegistered=" + str);
    if ("no".equals(str))
    {
      str = a("ANID", "");
      if (!"".equals(str))
      {
        bk.a().a(jdField_a_of_type_JavaLangString, "anid=" + str);
        a("hasAlreadyRegistered", "yes");
        paramIAnPushRegisterAnIdCallback.onSuccess();
        return;
      }
      if ((paramString3 != null) && (!"".equals(paramString3))) {}
      for (;;)
      {
        bk.a().a(jdField_a_of_type_JavaLangString, "anid=" + paramString3);
        new Thread(new dp(this, paramString2, paramIAnPushRegisterAnIdCallback, paramInt, paramString3, paramString1)).start();
        return;
        paramString3 = a(paramContext, paramString1);
      }
    }
    paramIAnPushRegisterAnIdCallback.onSuccess();
  }
  
  public final void a(String paramString)
  {
    jdField_a_of_type_AndroidContentContext.getSharedPreferences(PushService.LOG_TAG, 0).edit().remove(paramString).commit();
  }
  
  public final void a(String paramString1, String paramString2)
  {
    SharedPreferences.Editor localEditor = jdField_a_of_type_AndroidContentContext.getSharedPreferences(PushService.LOG_TAG, 0).edit();
    localEditor.putString(paramString1, paramString2);
    localEditor.commit();
  }
  
  @Deprecated
  public final void a(String paramString1, String paramString2, int paramInt1, int paramInt2, int paramInt3, IAnPushCallback paramIAnPushCallback)
  {
    new Thread(new dv(this, paramString1, paramString2, paramInt1, paramInt2, paramInt3, paramIAnPushCallback)).start();
  }
  
  public final void a(String paramString1, String paramString2, int paramInt1, int paramInt2, int paramInt3, IAnPushSettingsCallback paramIAnPushSettingsCallback)
  {
    new Thread(new dw(this, paramString1, paramString2, paramInt1, paramInt2, paramInt3, paramIAnPushSettingsCallback)).start();
  }
  
  @Deprecated
  public final void a(String paramString1, String paramString2, int paramInt1, int paramInt2, int paramInt3, boolean paramBoolean, IAnPushCallback paramIAnPushCallback)
  {
    new Thread(new dj(this, paramString1, paramString2, paramInt1, paramInt2, paramInt3, paramBoolean, paramIAnPushCallback)).start();
  }
  
  public final void a(String paramString1, String paramString2, int paramInt1, int paramInt2, int paramInt3, boolean paramBoolean, IAnPushSettingsCallback paramIAnPushSettingsCallback)
  {
    new Thread(new dk(this, paramString1, paramString2, paramInt1, paramInt2, paramInt3, paramBoolean, paramIAnPushSettingsCallback)).start();
  }
  
  @Deprecated
  public final void a(String paramString1, String paramString2, int paramInt, IAnPushCallback paramIAnPushCallback)
  {
    new Thread(new dn(this, paramString1, paramString2, paramInt, paramIAnPushCallback)).start();
  }
  
  public final void a(String paramString1, String paramString2, int paramInt, IAnPushSettingsCallback paramIAnPushSettingsCallback)
  {
    new Thread(new do(this, paramString1, paramString2, paramInt, paramIAnPushSettingsCallback)).start();
  }
  
  public final void a(String paramString1, String paramString2, IAnPushCallback paramIAnPushCallback)
  {
    new Thread(new dt(this, paramString1, paramString2, paramIAnPushCallback)).start();
  }
  
  public final void a(String paramString1, String paramString2, IAnPushCallback paramIAnPushCallback, boolean paramBoolean, String paramString3, String paramString4)
  {
    new Thread(new dg(this, paramString3, paramIAnPushCallback, paramString4, paramString1, paramString2, paramBoolean)).start();
  }
  
  public final void a(String paramString1, String paramString2, IAnPushRegistrationCallback paramIAnPushRegistrationCallback, boolean paramBoolean, String paramString3, String paramString4)
  {
    new Thread(new dq(this, paramString3, paramIAnPushRegistrationCallback, paramString4, paramString1, paramString2, paramBoolean)).start();
  }
  
  public final void a(String paramString1, String paramString2, IAnPushSettingsCallback paramIAnPushSettingsCallback)
  {
    new Thread(new du(this, paramString1, paramString2, paramIAnPushSettingsCallback)).start();
  }
  
  @Deprecated
  public final void a(String paramString1, String paramString2, String paramString3, IAnPushCallback paramIAnPushCallback, boolean paramBoolean, String paramString4)
  {
    new Thread(new dr(this, paramString1, paramString4, paramString2, paramString3, paramBoolean, paramIAnPushCallback)).start();
  }
  
  public final void a(String paramString1, String paramString2, String paramString3, IAnPushRegistrationCallback paramIAnPushRegistrationCallback, boolean paramBoolean, String paramString4)
  {
    new Thread(new ds(this, paramString1, paramString4, paramString2, paramString3, paramBoolean, paramIAnPushRegistrationCallback)).start();
  }
  
  /* Error */
  public final void a(String paramString1, String paramString2, String paramString3, boolean paramBoolean, String paramString4, String paramString5)
    throws ArrownockException
  {
    // Byte code:
    //   0: aconst_null
    //   1: astore 11
    //   3: aconst_null
    //   4: astore 9
    //   6: aload 9
    //   8: astore 10
    //   10: aload 11
    //   12: astore 8
    //   14: aload_0
    //   15: getfield 34	df:jdField_a_of_type_AndroidContentContext	Landroid/content/Context;
    //   18: invokestatic 267	com/arrownock/push/AnPush:getInstance	(Landroid/content/Context;)Lcom/arrownock/push/AnPush;
    //   21: invokevirtual 270	com/arrownock/push/AnPush:isSecureConnection	()Z
    //   24: ifeq +695 -> 719
    //   27: aload 9
    //   29: astore 10
    //   31: aload 11
    //   33: astore 8
    //   35: new 272	java/net/URL
    //   38: dup
    //   39: new 62	java/lang/StringBuilder
    //   42: dup
    //   43: ldc_w 274
    //   46: invokespecial 67	java/lang/StringBuilder:<init>	(Ljava/lang/String;)V
    //   49: aload_0
    //   50: invokespecial 445	df:c	()Ljava/lang/String;
    //   53: invokevirtual 104	java/lang/StringBuilder:append	(Ljava/lang/String;)Ljava/lang/StringBuilder;
    //   56: ldc_w 1140
    //   59: invokevirtual 104	java/lang/StringBuilder:append	(Ljava/lang/String;)Ljava/lang/StringBuilder;
    //   62: aload_1
    //   63: invokevirtual 450	java/lang/String:trim	()Ljava/lang/String;
    //   66: invokevirtual 104	java/lang/StringBuilder:append	(Ljava/lang/String;)Ljava/lang/StringBuilder;
    //   69: invokevirtual 74	java/lang/StringBuilder:toString	()Ljava/lang/String;
    //   72: invokespecial 275	java/net/URL:<init>	(Ljava/lang/String;)V
    //   75: invokevirtual 279	java/net/URL:openConnection	()Ljava/net/URLConnection;
    //   78: checkcast 281	javax/net/ssl/HttpsURLConnection
    //   81: astore 9
    //   83: aload 9
    //   85: checkcast 281	javax/net/ssl/HttpsURLConnection
    //   88: getstatic 29	df:jdField_a_of_type_JavaxNetSslHostnameVerifier	Ljavax/net/ssl/HostnameVerifier;
    //   91: invokevirtual 285	javax/net/ssl/HttpsURLConnection:setHostnameVerifier	(Ljavax/net/ssl/HostnameVerifier;)V
    //   94: aload 9
    //   96: checkcast 281	javax/net/ssl/HttpsURLConnection
    //   99: aload_0
    //   100: invokespecial 288	df:f	()Ljava/lang/String;
    //   103: aload_0
    //   104: invokespecial 291	df:g	()Ljava/lang/String;
    //   107: aload_0
    //   108: invokespecial 294	df:h	()Ljava/lang/String;
    //   111: ldc -63
    //   113: ldc_w 296
    //   116: invokestatic 301	at:a	(Ljava/lang/String;Ljava/lang/String;Ljava/lang/String;Ljava/lang/String;Ljava/lang/String;)Ljavax/net/ssl/SSLSocketFactory;
    //   119: invokevirtual 305	javax/net/ssl/HttpsURLConnection:setSSLSocketFactory	(Ljavax/net/ssl/SSLSocketFactory;)V
    //   122: aload 9
    //   124: astore 10
    //   126: aload 9
    //   128: astore 8
    //   130: aload 9
    //   132: ldc_w 452
    //   135: invokevirtual 455	java/net/HttpURLConnection:setRequestMethod	(Ljava/lang/String;)V
    //   138: aload 9
    //   140: astore 10
    //   142: aload 9
    //   144: astore 8
    //   146: aload 9
    //   148: iconst_1
    //   149: invokevirtual 459	java/net/HttpURLConnection:setDoInput	(Z)V
    //   152: aload 9
    //   154: astore 10
    //   156: aload 9
    //   158: astore 8
    //   160: aload 9
    //   162: iconst_1
    //   163: invokevirtual 462	java/net/HttpURLConnection:setDoOutput	(Z)V
    //   166: aload 9
    //   168: astore 10
    //   170: aload 9
    //   172: astore 8
    //   174: new 464	java/text/SimpleDateFormat
    //   177: dup
    //   178: ldc_w 466
    //   181: getstatic 472	java/util/Locale:US	Ljava/util/Locale;
    //   184: invokespecial 475	java/text/SimpleDateFormat:<init>	(Ljava/lang/String;Ljava/util/Locale;)V
    //   187: new 477	java/util/Date
    //   190: dup
    //   191: invokespecial 478	java/util/Date:<init>	()V
    //   194: invokevirtual 482	java/text/SimpleDateFormat:format	(Ljava/util/Date;)Ljava/lang/String;
    //   197: astore 12
    //   199: aload 9
    //   201: astore 10
    //   203: aload 9
    //   205: astore 8
    //   207: new 484	java/util/ArrayList
    //   210: dup
    //   211: invokespecial 485	java/util/ArrayList:<init>	()V
    //   214: astore 11
    //   216: aload_2
    //   217: ifnull +30 -> 247
    //   220: aload 9
    //   222: astore 10
    //   224: aload 9
    //   226: astore 8
    //   228: aload 11
    //   230: new 487	org/apache/http/message/BasicNameValuePair
    //   233: dup
    //   234: ldc_w 327
    //   237: aload_2
    //   238: invokespecial 489	org/apache/http/message/BasicNameValuePair:<init>	(Ljava/lang/String;Ljava/lang/String;)V
    //   241: invokeinterface 493 2 0
    //   246: pop
    //   247: aload 6
    //   249: ifnull +31 -> 280
    //   252: aload 9
    //   254: astore 10
    //   256: aload 9
    //   258: astore 8
    //   260: aload 11
    //   262: new 487	org/apache/http/message/BasicNameValuePair
    //   265: dup
    //   266: ldc_w 948
    //   269: aload 6
    //   271: invokespecial 489	org/apache/http/message/BasicNameValuePair:<init>	(Ljava/lang/String;Ljava/lang/String;)V
    //   274: invokeinterface 493 2 0
    //   279: pop
    //   280: aload 9
    //   282: astore 10
    //   284: aload 9
    //   286: astore 8
    //   288: aload 11
    //   290: new 487	org/apache/http/message/BasicNameValuePair
    //   293: dup
    //   294: ldc_w 495
    //   297: aload 12
    //   299: invokespecial 489	org/apache/http/message/BasicNameValuePair:<init>	(Ljava/lang/String;Ljava/lang/String;)V
    //   302: invokeinterface 493 2 0
    //   307: pop
    //   308: aload 9
    //   310: astore 10
    //   312: aload 9
    //   314: astore 8
    //   316: aload 11
    //   318: new 487	org/apache/http/message/BasicNameValuePair
    //   321: dup
    //   322: ldc_w 918
    //   325: aload 5
    //   327: invokespecial 489	org/apache/http/message/BasicNameValuePair:<init>	(Ljava/lang/String;Ljava/lang/String;)V
    //   330: invokeinterface 493 2 0
    //   335: pop
    //   336: iload 4
    //   338: ifeq +440 -> 778
    //   341: aload 9
    //   343: astore 10
    //   345: aload 9
    //   347: astore 8
    //   349: aload 11
    //   351: new 487	org/apache/http/message/BasicNameValuePair
    //   354: dup
    //   355: ldc_w 1141
    //   358: ldc_w 598
    //   361: invokespecial 489	org/apache/http/message/BasicNameValuePair:<init>	(Ljava/lang/String;Ljava/lang/String;)V
    //   364: invokeinterface 493 2 0
    //   369: pop
    //   370: aload 9
    //   372: astore 10
    //   374: aload 9
    //   376: astore 8
    //   378: new 62	java/lang/StringBuilder
    //   381: dup
    //   382: ldc_w 1143
    //   385: invokespecial 67	java/lang/StringBuilder:<init>	(Ljava/lang/String;)V
    //   388: aload 11
    //   390: aload_1
    //   391: invokevirtual 450	java/lang/String:trim	()Ljava/lang/String;
    //   394: invokestatic 1145	df:a	(Ljava/util/List;Ljava/lang/String;)Ljava/lang/String;
    //   397: invokevirtual 104	java/lang/StringBuilder:append	(Ljava/lang/String;)Ljava/lang/StringBuilder;
    //   400: invokevirtual 74	java/lang/StringBuilder:toString	()Ljava/lang/String;
    //   403: astore_1
    //   404: aload 9
    //   406: astore 8
    //   408: new 510	javax/crypto/spec/SecretKeySpec
    //   411: dup
    //   412: aload_0
    //   413: invokespecial 513	df:e	()Ljava/lang/String;
    //   416: invokevirtual 517	java/lang/String:getBytes	()[B
    //   419: ldc_w 519
    //   422: invokespecial 522	javax/crypto/spec/SecretKeySpec:<init>	([BLjava/lang/String;)V
    //   425: astore_2
    //   426: aload 9
    //   428: astore 8
    //   430: ldc_w 519
    //   433: invokestatic 527	javax/crypto/Mac:getInstance	(Ljava/lang/String;)Ljavax/crypto/Mac;
    //   436: astore_3
    //   437: aload 9
    //   439: astore 8
    //   441: aload_3
    //   442: aload_2
    //   443: invokevirtual 531	javax/crypto/Mac:init	(Ljava/security/Key;)V
    //   446: aload 9
    //   448: astore 8
    //   450: aload 11
    //   452: new 487	org/apache/http/message/BasicNameValuePair
    //   455: dup
    //   456: ldc_w 533
    //   459: aload_3
    //   460: aload_1
    //   461: invokevirtual 517	java/lang/String:getBytes	()[B
    //   464: invokevirtual 537	javax/crypto/Mac:doFinal	([B)[B
    //   467: iconst_2
    //   468: invokestatic 543	android/util/Base64:encodeToString	([BI)Ljava/lang/String;
    //   471: invokespecial 489	org/apache/http/message/BasicNameValuePair:<init>	(Ljava/lang/String;Ljava/lang/String;)V
    //   474: invokeinterface 493 2 0
    //   479: pop
    //   480: aload 9
    //   482: astore 10
    //   484: aload 9
    //   486: astore 8
    //   488: aload 9
    //   490: invokevirtual 547	java/net/HttpURLConnection:getOutputStream	()Ljava/io/OutputStream;
    //   493: astore_1
    //   494: aload 9
    //   496: astore 10
    //   498: aload 9
    //   500: astore 8
    //   502: new 549	java/io/BufferedWriter
    //   505: dup
    //   506: new 551	java/io/OutputStreamWriter
    //   509: dup
    //   510: aload_1
    //   511: ldc -118
    //   513: invokespecial 554	java/io/OutputStreamWriter:<init>	(Ljava/io/OutputStream;Ljava/lang/String;)V
    //   516: invokespecial 557	java/io/BufferedWriter:<init>	(Ljava/io/Writer;)V
    //   519: astore_2
    //   520: aload 9
    //   522: astore 10
    //   524: aload 9
    //   526: astore 8
    //   528: aload_2
    //   529: aload 11
    //   531: invokestatic 559	df:a	(Ljava/util/List;)Ljava/lang/String;
    //   534: invokevirtual 562	java/io/BufferedWriter:write	(Ljava/lang/String;)V
    //   537: aload 9
    //   539: astore 10
    //   541: aload 9
    //   543: astore 8
    //   545: aload_2
    //   546: invokevirtual 563	java/io/BufferedWriter:close	()V
    //   549: aload 9
    //   551: astore 10
    //   553: aload 9
    //   555: astore 8
    //   557: aload_1
    //   558: invokevirtual 566	java/io/OutputStream:close	()V
    //   561: aload 9
    //   563: astore 10
    //   565: aload 9
    //   567: astore 8
    //   569: aload 9
    //   571: invokevirtual 313	java/net/HttpURLConnection:getResponseCode	()I
    //   574: istore 7
    //   576: iload 7
    //   578: sipush 200
    //   581: if_icmpeq +285 -> 866
    //   584: aload 9
    //   586: astore 10
    //   588: aload 9
    //   590: astore 8
    //   592: new 79	com/arrownock/exception/ArrownockException
    //   595: dup
    //   596: new 315	org/json/JSONObject
    //   599: dup
    //   600: new 317	java/io/BufferedInputStream
    //   603: dup
    //   604: aload 9
    //   606: invokevirtual 355	java/net/HttpURLConnection:getErrorStream	()Ljava/io/InputStream;
    //   609: invokespecial 322	java/io/BufferedInputStream:<init>	(Ljava/io/InputStream;)V
    //   612: invokestatic 324	df:a	(Ljava/io/InputStream;)Ljava/lang/String;
    //   615: invokespecial 325	org/json/JSONObject:<init>	(Ljava/lang/String;)V
    //   618: ldc_w 568
    //   621: invokevirtual 572	org/json/JSONObject:getJSONObject	(Ljava/lang/String;)Lorg/json/JSONObject;
    //   624: ldc_w 357
    //   627: invokevirtual 331	org/json/JSONObject:getString	(Ljava/lang/String;)Ljava/lang/String;
    //   630: sipush 2004
    //   633: invokespecial 575	com/arrownock/exception/ArrownockException:<init>	(Ljava/lang/String;I)V
    //   636: athrow
    //   637: astore_1
    //   638: aload 9
    //   640: astore 10
    //   642: aload 9
    //   644: astore 8
    //   646: new 79	com/arrownock/exception/ArrownockException
    //   649: dup
    //   650: aload_1
    //   651: invokevirtual 578	org/json/JSONException:getMessage	()Ljava/lang/String;
    //   654: sipush 2004
    //   657: invokespecial 575	com/arrownock/exception/ArrownockException:<init>	(Ljava/lang/String;I)V
    //   660: athrow
    //   661: astore_1
    //   662: aload 9
    //   664: astore 10
    //   666: aload 9
    //   668: astore 8
    //   670: new 79	com/arrownock/exception/ArrownockException
    //   673: dup
    //   674: aload_1
    //   675: invokevirtual 579	java/io/IOException:getMessage	()Ljava/lang/String;
    //   678: sipush 2004
    //   681: invokespecial 575	com/arrownock/exception/ArrownockException:<init>	(Ljava/lang/String;I)V
    //   684: athrow
    //   685: astore_1
    //   686: aload 10
    //   688: astore 8
    //   690: aload_1
    //   691: instanceof 79
    //   694: ifeq +207 -> 901
    //   697: aload 10
    //   699: astore 8
    //   701: aload_1
    //   702: checkcast 79	com/arrownock/exception/ArrownockException
    //   705: athrow
    //   706: astore_1
    //   707: aload 8
    //   709: ifnull +8 -> 717
    //   712: aload 8
    //   714: invokevirtual 350	java/net/HttpURLConnection:disconnect	()V
    //   717: aload_1
    //   718: athrow
    //   719: aload 9
    //   721: astore 10
    //   723: aload 11
    //   725: astore 8
    //   727: new 272	java/net/URL
    //   730: dup
    //   731: new 62	java/lang/StringBuilder
    //   734: dup
    //   735: ldc_w 352
    //   738: invokespecial 67	java/lang/StringBuilder:<init>	(Ljava/lang/String;)V
    //   741: aload_0
    //   742: invokespecial 445	df:c	()Ljava/lang/String;
    //   745: invokevirtual 104	java/lang/StringBuilder:append	(Ljava/lang/String;)Ljava/lang/StringBuilder;
    //   748: ldc_w 1140
    //   751: invokevirtual 104	java/lang/StringBuilder:append	(Ljava/lang/String;)Ljava/lang/StringBuilder;
    //   754: aload_1
    //   755: invokevirtual 450	java/lang/String:trim	()Ljava/lang/String;
    //   758: invokevirtual 104	java/lang/StringBuilder:append	(Ljava/lang/String;)Ljava/lang/StringBuilder;
    //   761: invokevirtual 74	java/lang/StringBuilder:toString	()Ljava/lang/String;
    //   764: invokespecial 275	java/net/URL:<init>	(Ljava/lang/String;)V
    //   767: invokevirtual 279	java/net/URL:openConnection	()Ljava/net/URLConnection;
    //   770: checkcast 307	java/net/HttpURLConnection
    //   773: astore 9
    //   775: goto -653 -> 122
    //   778: aload 9
    //   780: astore 10
    //   782: aload 9
    //   784: astore 8
    //   786: aload 11
    //   788: new 487	org/apache/http/message/BasicNameValuePair
    //   791: dup
    //   792: ldc_w 920
    //   795: aload_3
    //   796: invokespecial 489	org/apache/http/message/BasicNameValuePair:<init>	(Ljava/lang/String;Ljava/lang/String;)V
    //   799: invokeinterface 493 2 0
    //   804: pop
    //   805: aload 9
    //   807: astore 10
    //   809: aload 9
    //   811: astore 8
    //   813: new 62	java/lang/StringBuilder
    //   816: dup
    //   817: ldc_w 1143
    //   820: invokespecial 67	java/lang/StringBuilder:<init>	(Ljava/lang/String;)V
    //   823: aload 11
    //   825: aload_1
    //   826: invokevirtual 450	java/lang/String:trim	()Ljava/lang/String;
    //   829: invokestatic 1145	df:a	(Ljava/util/List;Ljava/lang/String;)Ljava/lang/String;
    //   832: invokevirtual 104	java/lang/StringBuilder:append	(Ljava/lang/String;)Ljava/lang/StringBuilder;
    //   835: invokevirtual 74	java/lang/StringBuilder:toString	()Ljava/lang/String;
    //   838: astore_1
    //   839: goto -435 -> 404
    //   842: astore_1
    //   843: aload 9
    //   845: astore 10
    //   847: aload 9
    //   849: astore 8
    //   851: new 79	com/arrownock/exception/ArrownockException
    //   854: dup
    //   855: aload_1
    //   856: invokevirtual 580	java/lang/Exception:getMessage	()Ljava/lang/String;
    //   859: sipush 2004
    //   862: invokespecial 575	com/arrownock/exception/ArrownockException:<init>	(Ljava/lang/String;I)V
    //   865: athrow
    //   866: aload 9
    //   868: astore 10
    //   870: aload 9
    //   872: astore 8
    //   874: new 317	java/io/BufferedInputStream
    //   877: dup
    //   878: aload 9
    //   880: invokevirtual 321	java/net/HttpURLConnection:getInputStream	()Ljava/io/InputStream;
    //   883: invokespecial 322	java/io/BufferedInputStream:<init>	(Ljava/io/InputStream;)V
    //   886: invokestatic 324	df:a	(Ljava/io/InputStream;)Ljava/lang/String;
    //   889: pop
    //   890: aload 9
    //   892: ifnull +8 -> 900
    //   895: aload 9
    //   897: invokevirtual 350	java/net/HttpURLConnection:disconnect	()V
    //   900: return
    //   901: aload 10
    //   903: astore 8
    //   905: new 79	com/arrownock/exception/ArrownockException
    //   908: dup
    //   909: aload_1
    //   910: invokevirtual 580	java/lang/Exception:getMessage	()Ljava/lang/String;
    //   913: sipush 2004
    //   916: invokespecial 575	com/arrownock/exception/ArrownockException:<init>	(Ljava/lang/String;I)V
    //   919: athrow
    //   920: astore_1
    //   921: aload 9
    //   923: astore 8
    //   925: goto -218 -> 707
    //   928: astore_1
    //   929: aload 9
    //   931: astore 10
    //   933: goto -247 -> 686
    // Local variable table:
    //   start	length	slot	name	signature
    //   0	936	0	this	df
    //   0	936	1	paramString1	String
    //   0	936	2	paramString2	String
    //   0	936	3	paramString3	String
    //   0	936	4	paramBoolean	boolean
    //   0	936	5	paramString4	String
    //   0	936	6	paramString5	String
    //   574	8	7	i	int
    //   12	912	8	localObject1	Object
    //   4	926	9	localObject2	Object
    //   8	924	10	localObject3	Object
    //   1	823	11	localArrayList	java.util.ArrayList
    //   197	101	12	str	String
    // Exception table:
    //   from	to	target	type
    //   592	637	637	org/json/JSONException
    //   874	890	637	org/json/JSONException
    //   174	199	661	java/io/IOException
    //   207	216	661	java/io/IOException
    //   228	247	661	java/io/IOException
    //   260	280	661	java/io/IOException
    //   288	308	661	java/io/IOException
    //   316	336	661	java/io/IOException
    //   349	370	661	java/io/IOException
    //   378	404	661	java/io/IOException
    //   408	426	661	java/io/IOException
    //   430	437	661	java/io/IOException
    //   441	446	661	java/io/IOException
    //   450	480	661	java/io/IOException
    //   488	494	661	java/io/IOException
    //   502	520	661	java/io/IOException
    //   528	537	661	java/io/IOException
    //   545	549	661	java/io/IOException
    //   557	561	661	java/io/IOException
    //   569	576	661	java/io/IOException
    //   592	637	661	java/io/IOException
    //   646	661	661	java/io/IOException
    //   786	805	661	java/io/IOException
    //   813	839	661	java/io/IOException
    //   851	866	661	java/io/IOException
    //   874	890	661	java/io/IOException
    //   14	27	685	java/lang/Exception
    //   35	83	685	java/lang/Exception
    //   130	138	685	java/lang/Exception
    //   146	152	685	java/lang/Exception
    //   160	166	685	java/lang/Exception
    //   174	199	685	java/lang/Exception
    //   207	216	685	java/lang/Exception
    //   228	247	685	java/lang/Exception
    //   260	280	685	java/lang/Exception
    //   288	308	685	java/lang/Exception
    //   316	336	685	java/lang/Exception
    //   349	370	685	java/lang/Exception
    //   378	404	685	java/lang/Exception
    //   488	494	685	java/lang/Exception
    //   502	520	685	java/lang/Exception
    //   528	537	685	java/lang/Exception
    //   545	549	685	java/lang/Exception
    //   557	561	685	java/lang/Exception
    //   569	576	685	java/lang/Exception
    //   592	637	685	java/lang/Exception
    //   646	661	685	java/lang/Exception
    //   670	685	685	java/lang/Exception
    //   727	775	685	java/lang/Exception
    //   786	805	685	java/lang/Exception
    //   813	839	685	java/lang/Exception
    //   851	866	685	java/lang/Exception
    //   874	890	685	java/lang/Exception
    //   14	27	706	finally
    //   35	83	706	finally
    //   130	138	706	finally
    //   146	152	706	finally
    //   160	166	706	finally
    //   174	199	706	finally
    //   207	216	706	finally
    //   228	247	706	finally
    //   260	280	706	finally
    //   288	308	706	finally
    //   316	336	706	finally
    //   349	370	706	finally
    //   378	404	706	finally
    //   408	426	706	finally
    //   430	437	706	finally
    //   441	446	706	finally
    //   450	480	706	finally
    //   488	494	706	finally
    //   502	520	706	finally
    //   528	537	706	finally
    //   545	549	706	finally
    //   557	561	706	finally
    //   569	576	706	finally
    //   592	637	706	finally
    //   646	661	706	finally
    //   670	685	706	finally
    //   690	697	706	finally
    //   701	706	706	finally
    //   727	775	706	finally
    //   786	805	706	finally
    //   813	839	706	finally
    //   851	866	706	finally
    //   874	890	706	finally
    //   905	920	706	finally
    //   408	426	842	java/lang/Exception
    //   430	437	842	java/lang/Exception
    //   441	446	842	java/lang/Exception
    //   450	480	842	java/lang/Exception
    //   83	122	920	finally
    //   83	122	928	java/lang/Exception
  }
  
  /* Error */
  public final org.json.JSONArray b(String paramString)
    throws ArrownockException
  {
    // Byte code:
    //   0: aconst_null
    //   1: astore 7
    //   3: aconst_null
    //   4: astore 8
    //   6: aconst_null
    //   7: astore 6
    //   9: aload 6
    //   11: astore 5
    //   13: aload 7
    //   15: astore 4
    //   17: aload 8
    //   19: astore_3
    //   20: new 464	java/text/SimpleDateFormat
    //   23: dup
    //   24: ldc_w 466
    //   27: getstatic 472	java/util/Locale:US	Ljava/util/Locale;
    //   30: invokespecial 475	java/text/SimpleDateFormat:<init>	(Ljava/lang/String;Ljava/util/Locale;)V
    //   33: new 477	java/util/Date
    //   36: dup
    //   37: invokespecial 478	java/util/Date:<init>	()V
    //   40: invokevirtual 482	java/text/SimpleDateFormat:format	(Ljava/util/Date;)Ljava/lang/String;
    //   43: astore 10
    //   45: aload 6
    //   47: astore 5
    //   49: aload 7
    //   51: astore 4
    //   53: aload 8
    //   55: astore_3
    //   56: new 484	java/util/ArrayList
    //   59: dup
    //   60: invokespecial 485	java/util/ArrayList:<init>	()V
    //   63: astore 9
    //   65: aload 6
    //   67: astore 5
    //   69: aload 7
    //   71: astore 4
    //   73: aload 8
    //   75: astore_3
    //   76: aload 9
    //   78: new 487	org/apache/http/message/BasicNameValuePair
    //   81: dup
    //   82: ldc_w 347
    //   85: aload_1
    //   86: invokespecial 489	org/apache/http/message/BasicNameValuePair:<init>	(Ljava/lang/String;Ljava/lang/String;)V
    //   89: invokeinterface 493 2 0
    //   94: pop
    //   95: aload 6
    //   97: astore 5
    //   99: aload 7
    //   101: astore 4
    //   103: aload 8
    //   105: astore_3
    //   106: aload 9
    //   108: new 487	org/apache/http/message/BasicNameValuePair
    //   111: dup
    //   112: ldc_w 495
    //   115: aload 10
    //   117: invokespecial 489	org/apache/http/message/BasicNameValuePair:<init>	(Ljava/lang/String;Ljava/lang/String;)V
    //   120: invokeinterface 493 2 0
    //   125: pop
    //   126: aload 6
    //   128: astore 5
    //   130: aload 7
    //   132: astore 4
    //   134: aload 8
    //   136: astore_3
    //   137: aload_0
    //   138: ldc_w 1147
    //   141: ldc -63
    //   143: invokevirtual 638	df:a	(Ljava/lang/String;Ljava/lang/String;)Ljava/lang/String;
    //   146: astore 11
    //   148: aload 6
    //   150: astore 5
    //   152: aload 7
    //   154: astore 4
    //   156: aload 8
    //   158: astore_3
    //   159: aload 9
    //   161: new 487	org/apache/http/message/BasicNameValuePair
    //   164: dup
    //   165: ldc -95
    //   167: aload 11
    //   169: invokespecial 489	org/apache/http/message/BasicNameValuePair:<init>	(Ljava/lang/String;Ljava/lang/String;)V
    //   172: invokeinterface 493 2 0
    //   177: pop
    //   178: aload 6
    //   180: astore 5
    //   182: aload 7
    //   184: astore 4
    //   186: aload 8
    //   188: astore_3
    //   189: new 62	java/lang/StringBuilder
    //   192: dup
    //   193: ldc_w 1149
    //   196: invokespecial 67	java/lang/StringBuilder:<init>	(Ljava/lang/String;)V
    //   199: aload 10
    //   201: invokevirtual 104	java/lang/StringBuilder:append	(Ljava/lang/String;)Ljava/lang/StringBuilder;
    //   204: ldc_w 508
    //   207: invokevirtual 104	java/lang/StringBuilder:append	(Ljava/lang/String;)Ljava/lang/StringBuilder;
    //   210: aload 11
    //   212: invokevirtual 104	java/lang/StringBuilder:append	(Ljava/lang/String;)Ljava/lang/StringBuilder;
    //   215: ldc_w 965
    //   218: invokevirtual 104	java/lang/StringBuilder:append	(Ljava/lang/String;)Ljava/lang/StringBuilder;
    //   221: aload_1
    //   222: invokevirtual 104	java/lang/StringBuilder:append	(Ljava/lang/String;)Ljava/lang/StringBuilder;
    //   225: invokevirtual 74	java/lang/StringBuilder:toString	()Ljava/lang/String;
    //   228: astore_1
    //   229: aload 6
    //   231: astore 5
    //   233: aload 8
    //   235: astore_3
    //   236: new 510	javax/crypto/spec/SecretKeySpec
    //   239: dup
    //   240: aload_0
    //   241: invokespecial 513	df:e	()Ljava/lang/String;
    //   244: invokevirtual 517	java/lang/String:getBytes	()[B
    //   247: ldc_w 519
    //   250: invokespecial 522	javax/crypto/spec/SecretKeySpec:<init>	([BLjava/lang/String;)V
    //   253: astore 4
    //   255: aload 6
    //   257: astore 5
    //   259: aload 8
    //   261: astore_3
    //   262: ldc_w 519
    //   265: invokestatic 527	javax/crypto/Mac:getInstance	(Ljava/lang/String;)Ljavax/crypto/Mac;
    //   268: astore 10
    //   270: aload 6
    //   272: astore 5
    //   274: aload 8
    //   276: astore_3
    //   277: aload 10
    //   279: aload 4
    //   281: invokevirtual 531	javax/crypto/Mac:init	(Ljava/security/Key;)V
    //   284: aload 6
    //   286: astore 5
    //   288: aload 8
    //   290: astore_3
    //   291: aload 9
    //   293: new 487	org/apache/http/message/BasicNameValuePair
    //   296: dup
    //   297: ldc_w 533
    //   300: aload 10
    //   302: aload_1
    //   303: invokevirtual 517	java/lang/String:getBytes	()[B
    //   306: invokevirtual 537	javax/crypto/Mac:doFinal	([B)[B
    //   309: iconst_2
    //   310: invokestatic 543	android/util/Base64:encodeToString	([BI)Ljava/lang/String;
    //   313: invokespecial 489	org/apache/http/message/BasicNameValuePair:<init>	(Ljava/lang/String;Ljava/lang/String;)V
    //   316: invokeinterface 493 2 0
    //   321: pop
    //   322: aload 6
    //   324: astore 5
    //   326: aload 7
    //   328: astore 4
    //   330: aload 8
    //   332: astore_3
    //   333: aload_0
    //   334: getfield 34	df:jdField_a_of_type_AndroidContentContext	Landroid/content/Context;
    //   337: invokestatic 267	com/arrownock/push/AnPush:getInstance	(Landroid/content/Context;)Lcom/arrownock/push/AnPush;
    //   340: invokevirtual 270	com/arrownock/push/AnPush:isSecureConnection	()Z
    //   343: ifeq +285 -> 628
    //   346: aload 6
    //   348: astore 5
    //   350: aload 7
    //   352: astore 4
    //   354: aload 8
    //   356: astore_3
    //   357: new 272	java/net/URL
    //   360: dup
    //   361: new 62	java/lang/StringBuilder
    //   364: dup
    //   365: ldc_w 274
    //   368: invokespecial 67	java/lang/StringBuilder:<init>	(Ljava/lang/String;)V
    //   371: aload_0
    //   372: invokespecial 445	df:c	()Ljava/lang/String;
    //   375: invokevirtual 104	java/lang/StringBuilder:append	(Ljava/lang/String;)Ljava/lang/StringBuilder;
    //   378: ldc_w 1151
    //   381: invokevirtual 104	java/lang/StringBuilder:append	(Ljava/lang/String;)Ljava/lang/StringBuilder;
    //   384: aload 9
    //   386: invokestatic 559	df:a	(Ljava/util/List;)Ljava/lang/String;
    //   389: invokevirtual 104	java/lang/StringBuilder:append	(Ljava/lang/String;)Ljava/lang/StringBuilder;
    //   392: invokevirtual 74	java/lang/StringBuilder:toString	()Ljava/lang/String;
    //   395: invokespecial 275	java/net/URL:<init>	(Ljava/lang/String;)V
    //   398: invokevirtual 279	java/net/URL:openConnection	()Ljava/net/URLConnection;
    //   401: checkcast 281	javax/net/ssl/HttpsURLConnection
    //   404: astore_1
    //   405: aload_1
    //   406: checkcast 281	javax/net/ssl/HttpsURLConnection
    //   409: getstatic 29	df:jdField_a_of_type_JavaxNetSslHostnameVerifier	Ljavax/net/ssl/HostnameVerifier;
    //   412: invokevirtual 285	javax/net/ssl/HttpsURLConnection:setHostnameVerifier	(Ljavax/net/ssl/HostnameVerifier;)V
    //   415: aload_1
    //   416: checkcast 281	javax/net/ssl/HttpsURLConnection
    //   419: aload_0
    //   420: invokespecial 288	df:f	()Ljava/lang/String;
    //   423: aload_0
    //   424: invokespecial 291	df:g	()Ljava/lang/String;
    //   427: aload_0
    //   428: invokespecial 294	df:h	()Ljava/lang/String;
    //   431: ldc -63
    //   433: ldc_w 296
    //   436: invokestatic 301	at:a	(Ljava/lang/String;Ljava/lang/String;Ljava/lang/String;Ljava/lang/String;Ljava/lang/String;)Ljavax/net/ssl/SSLSocketFactory;
    //   439: invokevirtual 305	javax/net/ssl/HttpsURLConnection:setSSLSocketFactory	(Ljavax/net/ssl/SSLSocketFactory;)V
    //   442: aload_1
    //   443: astore 5
    //   445: aload_1
    //   446: astore 4
    //   448: aload_1
    //   449: astore_3
    //   450: aload_1
    //   451: ldc_w 968
    //   454: invokevirtual 972	java/net/HttpURLConnection:setConnectTimeout	(I)V
    //   457: aload_1
    //   458: astore 5
    //   460: aload_1
    //   461: astore 4
    //   463: aload_1
    //   464: astore_3
    //   465: aload_1
    //   466: invokevirtual 310	java/net/HttpURLConnection:connect	()V
    //   469: aload_1
    //   470: astore 5
    //   472: aload_1
    //   473: astore 4
    //   475: aload_1
    //   476: astore_3
    //   477: aload_1
    //   478: invokevirtual 313	java/net/HttpURLConnection:getResponseCode	()I
    //   481: istore_2
    //   482: iload_2
    //   483: sipush 200
    //   486: if_icmpne +204 -> 690
    //   489: aload_1
    //   490: astore 5
    //   492: aload_1
    //   493: astore 4
    //   495: aload_1
    //   496: astore_3
    //   497: new 315	org/json/JSONObject
    //   500: dup
    //   501: new 317	java/io/BufferedInputStream
    //   504: dup
    //   505: aload_1
    //   506: invokevirtual 321	java/net/HttpURLConnection:getInputStream	()Ljava/io/InputStream;
    //   509: invokespecial 322	java/io/BufferedInputStream:<init>	(Ljava/io/InputStream;)V
    //   512: invokestatic 324	df:a	(Ljava/io/InputStream;)Ljava/lang/String;
    //   515: invokespecial 325	org/json/JSONObject:<init>	(Ljava/lang/String;)V
    //   518: ldc_w 944
    //   521: invokevirtual 572	org/json/JSONObject:getJSONObject	(Ljava/lang/String;)Lorg/json/JSONObject;
    //   524: ldc_w 1153
    //   527: invokevirtual 977	org/json/JSONObject:getJSONArray	(Ljava/lang/String;)Lorg/json/JSONArray;
    //   530: astore 6
    //   532: aload_1
    //   533: ifnull +7 -> 540
    //   536: aload_1
    //   537: invokevirtual 350	java/net/HttpURLConnection:disconnect	()V
    //   540: aload 6
    //   542: areturn
    //   543: astore_1
    //   544: aload 6
    //   546: astore 5
    //   548: aload 7
    //   550: astore 4
    //   552: aload 8
    //   554: astore_3
    //   555: new 79	com/arrownock/exception/ArrownockException
    //   558: dup
    //   559: aload_1
    //   560: invokevirtual 580	java/lang/Exception:getMessage	()Ljava/lang/String;
    //   563: sipush 2010
    //   566: invokespecial 575	com/arrownock/exception/ArrownockException:<init>	(Ljava/lang/String;I)V
    //   569: athrow
    //   570: astore_1
    //   571: aload 5
    //   573: astore_3
    //   574: aload_3
    //   575: astore 4
    //   577: new 79	com/arrownock/exception/ArrownockException
    //   580: dup
    //   581: aload_1
    //   582: invokevirtual 579	java/io/IOException:getMessage	()Ljava/lang/String;
    //   585: sipush 2010
    //   588: invokespecial 575	com/arrownock/exception/ArrownockException:<init>	(Ljava/lang/String;I)V
    //   591: athrow
    //   592: astore_1
    //   593: aload 4
    //   595: astore_3
    //   596: aload_1
    //   597: instanceof 79
    //   600: ifeq +168 -> 768
    //   603: aload 4
    //   605: astore_3
    //   606: aload_1
    //   607: checkcast 79	com/arrownock/exception/ArrownockException
    //   610: athrow
    //   611: astore 4
    //   613: aload_3
    //   614: astore_1
    //   615: aload 4
    //   617: astore_3
    //   618: aload_1
    //   619: ifnull +7 -> 626
    //   622: aload_1
    //   623: invokevirtual 350	java/net/HttpURLConnection:disconnect	()V
    //   626: aload_3
    //   627: athrow
    //   628: aload 6
    //   630: astore 5
    //   632: aload 7
    //   634: astore 4
    //   636: aload 8
    //   638: astore_3
    //   639: new 272	java/net/URL
    //   642: dup
    //   643: new 62	java/lang/StringBuilder
    //   646: dup
    //   647: ldc_w 352
    //   650: invokespecial 67	java/lang/StringBuilder:<init>	(Ljava/lang/String;)V
    //   653: aload_0
    //   654: invokespecial 445	df:c	()Ljava/lang/String;
    //   657: invokevirtual 104	java/lang/StringBuilder:append	(Ljava/lang/String;)Ljava/lang/StringBuilder;
    //   660: ldc_w 1151
    //   663: invokevirtual 104	java/lang/StringBuilder:append	(Ljava/lang/String;)Ljava/lang/StringBuilder;
    //   666: aload 9
    //   668: invokestatic 559	df:a	(Ljava/util/List;)Ljava/lang/String;
    //   671: invokevirtual 104	java/lang/StringBuilder:append	(Ljava/lang/String;)Ljava/lang/StringBuilder;
    //   674: invokevirtual 74	java/lang/StringBuilder:toString	()Ljava/lang/String;
    //   677: invokespecial 275	java/net/URL:<init>	(Ljava/lang/String;)V
    //   680: invokevirtual 279	java/net/URL:openConnection	()Ljava/net/URLConnection;
    //   683: checkcast 307	java/net/HttpURLConnection
    //   686: astore_1
    //   687: goto -245 -> 442
    //   690: aload_1
    //   691: astore 5
    //   693: aload_1
    //   694: astore 4
    //   696: aload_1
    //   697: astore_3
    //   698: new 79	com/arrownock/exception/ArrownockException
    //   701: dup
    //   702: new 315	org/json/JSONObject
    //   705: dup
    //   706: new 317	java/io/BufferedInputStream
    //   709: dup
    //   710: aload_1
    //   711: invokevirtual 355	java/net/HttpURLConnection:getErrorStream	()Ljava/io/InputStream;
    //   714: invokespecial 322	java/io/BufferedInputStream:<init>	(Ljava/io/InputStream;)V
    //   717: invokestatic 324	df:a	(Ljava/io/InputStream;)Ljava/lang/String;
    //   720: invokespecial 325	org/json/JSONObject:<init>	(Ljava/lang/String;)V
    //   723: ldc_w 568
    //   726: invokevirtual 572	org/json/JSONObject:getJSONObject	(Ljava/lang/String;)Lorg/json/JSONObject;
    //   729: ldc_w 357
    //   732: invokevirtual 331	org/json/JSONObject:getString	(Ljava/lang/String;)Ljava/lang/String;
    //   735: sipush 2010
    //   738: invokespecial 575	com/arrownock/exception/ArrownockException:<init>	(Ljava/lang/String;I)V
    //   741: athrow
    //   742: astore 6
    //   744: aload_1
    //   745: astore 5
    //   747: aload_1
    //   748: astore 4
    //   750: aload_1
    //   751: astore_3
    //   752: new 79	com/arrownock/exception/ArrownockException
    //   755: dup
    //   756: aload 6
    //   758: invokevirtual 578	org/json/JSONException:getMessage	()Ljava/lang/String;
    //   761: sipush 2010
    //   764: invokespecial 575	com/arrownock/exception/ArrownockException:<init>	(Ljava/lang/String;I)V
    //   767: athrow
    //   768: aload 4
    //   770: astore_3
    //   771: new 79	com/arrownock/exception/ArrownockException
    //   774: dup
    //   775: aload_1
    //   776: invokevirtual 580	java/lang/Exception:getMessage	()Ljava/lang/String;
    //   779: sipush 2010
    //   782: invokespecial 575	com/arrownock/exception/ArrownockException:<init>	(Ljava/lang/String;I)V
    //   785: athrow
    //   786: astore_3
    //   787: goto -169 -> 618
    //   790: astore_3
    //   791: aload_1
    //   792: astore 4
    //   794: aload_3
    //   795: astore_1
    //   796: goto -203 -> 593
    //   799: astore 4
    //   801: aload_1
    //   802: astore_3
    //   803: aload 4
    //   805: astore_1
    //   806: goto -232 -> 574
    // Local variable table:
    //   start	length	slot	name	signature
    //   0	809	0	this	df
    //   0	809	1	paramString	String
    //   481	6	2	i	int
    //   19	752	3	localObject1	Object
    //   786	1	3	localObject2	Object
    //   790	5	3	localException	Exception
    //   802	1	3	str1	String
    //   15	589	4	localObject3	Object
    //   611	5	4	localObject4	Object
    //   634	159	4	localObject5	Object
    //   799	5	4	localIOException	IOException
    //   11	735	5	localObject6	Object
    //   7	622	6	localJSONArray	org.json.JSONArray
    //   742	15	6	localJSONException	org.json.JSONException
    //   1	632	7	localObject7	Object
    //   4	633	8	localObject8	Object
    //   63	604	9	localArrayList	java.util.ArrayList
    //   43	258	10	localObject9	Object
    //   146	65	11	str2	String
    // Exception table:
    //   from	to	target	type
    //   236	255	543	java/lang/Exception
    //   262	270	543	java/lang/Exception
    //   277	284	543	java/lang/Exception
    //   291	322	543	java/lang/Exception
    //   20	45	570	java/io/IOException
    //   56	65	570	java/io/IOException
    //   76	95	570	java/io/IOException
    //   106	126	570	java/io/IOException
    //   137	148	570	java/io/IOException
    //   159	178	570	java/io/IOException
    //   189	229	570	java/io/IOException
    //   236	255	570	java/io/IOException
    //   262	270	570	java/io/IOException
    //   277	284	570	java/io/IOException
    //   291	322	570	java/io/IOException
    //   333	346	570	java/io/IOException
    //   357	405	570	java/io/IOException
    //   450	457	570	java/io/IOException
    //   465	469	570	java/io/IOException
    //   477	482	570	java/io/IOException
    //   497	532	570	java/io/IOException
    //   555	570	570	java/io/IOException
    //   639	687	570	java/io/IOException
    //   698	742	570	java/io/IOException
    //   752	768	570	java/io/IOException
    //   20	45	592	java/lang/Exception
    //   56	65	592	java/lang/Exception
    //   76	95	592	java/lang/Exception
    //   106	126	592	java/lang/Exception
    //   137	148	592	java/lang/Exception
    //   159	178	592	java/lang/Exception
    //   189	229	592	java/lang/Exception
    //   333	346	592	java/lang/Exception
    //   357	405	592	java/lang/Exception
    //   450	457	592	java/lang/Exception
    //   465	469	592	java/lang/Exception
    //   477	482	592	java/lang/Exception
    //   497	532	592	java/lang/Exception
    //   555	570	592	java/lang/Exception
    //   577	592	592	java/lang/Exception
    //   639	687	592	java/lang/Exception
    //   698	742	592	java/lang/Exception
    //   752	768	592	java/lang/Exception
    //   20	45	611	finally
    //   56	65	611	finally
    //   76	95	611	finally
    //   106	126	611	finally
    //   137	148	611	finally
    //   159	178	611	finally
    //   189	229	611	finally
    //   236	255	611	finally
    //   262	270	611	finally
    //   277	284	611	finally
    //   291	322	611	finally
    //   333	346	611	finally
    //   357	405	611	finally
    //   450	457	611	finally
    //   465	469	611	finally
    //   477	482	611	finally
    //   497	532	611	finally
    //   555	570	611	finally
    //   577	592	611	finally
    //   596	603	611	finally
    //   606	611	611	finally
    //   639	687	611	finally
    //   698	742	611	finally
    //   752	768	611	finally
    //   771	786	611	finally
    //   497	532	742	org/json/JSONException
    //   698	742	742	org/json/JSONException
    //   405	442	786	finally
    //   405	442	790	java/lang/Exception
    //   405	442	799	java/io/IOException
  }
  
  @Deprecated
  public final void b(String paramString1, String paramString2, IAnPushCallback paramIAnPushCallback)
  {
    new Thread(new dh(this, paramString1, paramString2, paramIAnPushCallback)).start();
  }
  
  public final void b(String paramString1, String paramString2, IAnPushSettingsCallback paramIAnPushSettingsCallback)
  {
    new Thread(new di(this, paramString1, paramString2, paramIAnPushSettingsCallback)).start();
  }
  
  @Deprecated
  public final void c(String paramString1, String paramString2, IAnPushCallback paramIAnPushCallback)
  {
    new Thread(new dl(this, paramString1, paramString2, paramIAnPushCallback)).start();
  }
  
  public final void c(String paramString1, String paramString2, IAnPushSettingsCallback paramIAnPushSettingsCallback)
  {
    new Thread(new dm(this, paramString1, paramString2, paramIAnPushSettingsCallback)).start();
  }
}
